Workbook

Sheet HDSD
A1: LƯƠNG KHOÁN SẢN XUẤT & ĐỘI XE CONTAINER – FILE CHUẨN HOÁ
A2: Bản chuẩn hoá từ sheet "BCC sx khoán" (file Lương nội bộ HAPĐ T8/2026) và file "Theo dõi chi phí đội xe container". Bước đệm trước khi đưa lên ERP.
A4: QUY ƯỚC MÀU
A5: Chữ xanh dương, nền vàng nhạt | B5: Ô NHẬP LIỆU – người dùng gõ vào. Không gõ vào bất kỳ ô nào khác.
A6: Nền vàng đậm | B6: Tham số/đơn giá CẦN HCNS – KẾ TOÁN XÁC NHẬN (giá trị hiện tại lấy từ file cũ hoặc là ví dụ).
A7: Chữ đen | B7: Công thức – không sửa. Sheet đã khoá vùng công thức (mật khẩu trống, bỏ khoá: Review → Unprotect).
A8: Nền xanh lá | B8: Kết quả cuối – là số đưa sang Bảng lương (cột "Lương khoán + ăn khoán" và "Số ngày công khoán").
A10: QUY TRÌNH HÀNG THÁNG – SẢN XUẤT KHOÁN
A11: 1. THAM_SO | B11: Nhập tháng/năm, tổng tấn chế biến, tấn hàng hanging, tấn hàng chèn. Các đơn giá/định mức chỉ sửa khi có quyết định mới.
A12: 2. NHAN_VIEN | B12: Thêm người mới (mã NV lấy từ máy chấm công), hệ số, hình thức Khoán / Công nhật. Người nghỉ: đổi Tình trạng, không xoá dòng.
A13: 3. KHOAN_KHAC | B13: Nhập các việc khoán khác (chèn hàng, vệ sinh máy, khẩu trang…) và khoản trừ (thời vụ A Lưới). Để trống "Mã NV nhận" = chia chung theo giờ; điền mã = trả đích danh người đó.
A14: 4. BCC_KHOAN | B14: Nhập số giờ từng ngày cho từng mã NV (đúng như sheet cũ). Ngày/thứ tự sinh theo tháng.
A15: 5. LUONG_KHOAN | B15: Tự tính. Cột "Tổng lương khoán" và "Tiền ăn" là số đưa sang Bảng lương. Không có ô nào phải gõ.
A16: 6. KIEM_TRA | B16: Mọi dòng phải là OK trước khi chốt. Có dòng LỖI thì xem ghi chú bên cạnh.
A18: QUY TRÌNH HÀNG THÁNG – ĐỘI XE
A19: 1. XE_THAM_SO / XE_TUYEN | B19: Bảng đơn giá theo tuyến, hỗ trợ vượt ngày, hỗ trợ dầu, tỷ giá kíp. Đây là phần file cũ CHƯA CÓ – số hiện tại là VÍ DỤ, HCNS phải điền theo quy chế lương tài xế.
A20: 2. XE_CHUYEN | B20: Mỗi chuyến một dòng (tài xế, tuyến, ngày đi/về, km, số PĐĐ). Lương chuyến tự tính.
A21: 3. XE_CHI_PHI | B21: Mỗi khoản tạm ứng / chi phí một dòng, ghi rõ tiền tệ (VND/LAK) và "Được tính" (Có/Không). Thay cho việc ghi xen kẽ trong 6 sheet tài xế.
A22: 4. XE_LUONG | B22: Tự tổng hợp theo tài xế: lương khoán chuyến (đưa sang Bảng lương cột X), quyết toán tạm ứng.
A24: ĐỐI CHIẾU VỚI SHEET CŨ "BCC sx khoán"
A25: W2 Khối lượng chế biến | B25: → THAM_SO!C6
A26: AH2/AH3 Hàng hanging | B26: → THAM_SO!C7, C8
A27: AN2/AN3 Hàng chèn | B27: → THAM_SO!C9, C10
A28: W4 = W3/42 | B28: → 42 = THAM_SO!C11 "Số LĐ định mức" (trước đây gõ cứng trong công thức)
A29: (W2*500*41) tiền ăn | B29: → THAM_SO!C12 = 20.500 đ/tấn (trước đây gõ cứng)
A30: (M15 − 400.000) và +100.000/+200.000 | B30: → KHOAN_KHAC: để trống mã = chia chung; điền mã = đích danh. Không còn số cứng.
A31: '[5]HS sx'!B4:C16 (file ngoài) | B31: → sheet HS_SX trong file này
A32: Bảng công nhật T6:AN14 | B32: → NHAN_VIEN với Hình thức = "Công nhật" + chấm giờ chung trong BCC_KHOAN
A33: Cột AS "Tổng lương khoán", AU "Tiền ăn sau khoán" | B33: → LUONG_KHOAN cột Q, R (công thức giống hệt, đã kiểm chứng bằng số liệu T8/2026)

Sheet THAM_SO
A1: THAM SỐ KỲ LƯƠNG KHOÁN SẢN XUẤT
A2: Ô xanh/nền vàng nhạt: nhập mỗi tháng. Ô nền vàng đậm: định mức – chỉ đổi khi có quyết định. Phần "Tính toán" là công thức.
B3: Tháng | C3: 8
B4: Năm | C4: 2026
B6: Khối lượng chế biến trong tháng (tấn) | C6: 1077.49 | D6: Ô W2 cũ. Đã gồm hàng hanging, đã trích lại 10%, không gồm hàng chèn.
B7: Khối lượng hàng hanging (tấn) | C7: 0 | D7: Ô AH2 cũ
B8: Đơn giá cộng thêm hàng hanging (đ/tấn) | C8: 252000 | D8: Ô AH3 cũ
B9: Khối lượng hàng chèn (tấn) | C9: 105.37 | D9: Ô AN2 cũ. Hàng chèn đã nhập kho nên không nằm trong tấn chế biến.
B10: Đơn giá hàng chèn (đ/tấn) | C10: 140000 | D10: Ô AN3 cũ
B11: Số lao động định mức (N) | C11: 42 | D11: Số 42 gõ cứng trong công thức W4 = W3/42. Ghi chú A1 sheet cũ: "check số lượng nhân công khoán sửa lại số nhân". CẦN XÁC NHẬN đây là hằng số định mức hay là số người thực tế.
B12: Định mức tiền ăn theo sản lượng (đ/tấn) | C12: 20500 | D12: Bằng 500 × 41 gõ cứng trong công thức tiền ăn cũ (W2*500*41). CẦN XÁC NHẬN.
B13: Số giờ của 1 công | C13: 8
B14: Đơn giá công nhật mặc định (đ/công) | C14: 270000 | D14: Sheet cũ: 270.000/8 và 300.000/8 – đơn giá riêng từng người khai ở NHAN_VIEN cột G
B15: Làm tròn xuống đến (đ) | C15: 1000 | D15: ROUNDDOWN(…, -3)
B17: TÍNH TOÁN (không sửa)
B18: Tổng giờ công khoán trong tháng (giờ) | C18: =SUMIFS(LUONG_KHOAN!$G$6:$G$100,LUONG_KHOAN!$D$6:$D$100,"Khoán") -> 455 | D18: Ô W3 cũ (=AN64)
B19: Số giờ làm trung bình / người | C19: =IF(C11>0,C18/C11,0) -> 10.833333 | D19: Ô W4 cũ = W3/42
B20: Quỹ hàng hanging (đ) | C20: =C7*C8 -> 0 | D20: Ô AH4 cũ
B21: Quỹ hàng chèn (đ) | C21: =C9*C10 -> 14751800 | D21: Ô AN4 cũ
B22: Quỹ khoán CV khác chia chung theo giờ (đ) | C22: =SUMIFS(KHOAN_KHAC!$F$5:$F$39,KHOAN_KHAC!$G$5:$G$39,"") -> -22450000 | D22: Ô (M15 − 400.000) cũ. Gồm cả khoản trừ (số âm).
B23: Tổng CV khác trả đích danh (đ) | C23: =SUMIFS(KHOAN_KHAC!$F$5:$F$39,KHOAN_KHAC!$G$5:$G$39,"<>") -> 400000 | D23: Các khoản +100.000/+200.000 gõ tay trong cột AQ cũ
B24: Tổng lương công nhật trừ khỏi quỹ khoán (đ) | C24: =SUMIFS(LUONG_KHOAN!$P$6:$P$100,LUONG_KHOAN!$D$6:$D$100,"Công nhật") -> 0 | D24: Ô AL14 cũ
B25: Tổng công tính tiền ăn (khoán + công nhật) | C25: =SUM(LUONG_KHOAN!$H$6:$H$100) -> 56.875 | D25: Ô (AT64 + AF14/8) cũ
B26: Quỹ tiền ăn theo sản lượng (đ) | C26: =C6*C12 -> 22088545 | D26: W2*500*41 cũ
B27: Tiền ăn cho 1 công (đ/công) | C27: =IF(C25>0,C26/C25,0) -> 388370.02
B28: Tổng quỹ lương khoán sản phẩm phân bổ (đ) | C28: =SUMIFS(LUONG_KHOAN!$J$6:$J$100,LUONG_KHOAN!$D$6:$D$100,"Khoán") -> 3.4073218e+08 | D28: Tương đương tấn × 42 × đơn giá bình quân
B29: Chi phí lương khoán bình quân (đ/tấn chế biến) | C29: =IF(C6>0,C28/C6,0) -> 316227.69 | D29: Chỉ số quản trị để so sánh giữa các tháng

Sheet HS_SX
A1: BẢNG ĐƠN GIÁ KHOÁN THEO HỆ SỐ (thay cho file ngoài '[5]HS sx')
A2: 10 cặp giá trị dưới đây lấy từ giá trị đã tính trong sheet cũ. Cột D là quy luật suy ra (400 + 6.000 × hệ số) để kiểm tra – CẦN đối chiếu với file "HS sx" gốc và bổ sung hệ số còn thiếu.
A4: Hệ số | B4: Đơn giá khoán (đ/tấn) | C4: Kiểm tra quy luật 400+6000×hs | D4: Lệch
A5: 0.9 | B5: 5800 | C5: =400+6000*A5 -> 5800 | D5: =B5-C5 -> 0
A6: 1 | B6: 6400 | C6: =400+6000*A6 -> 6400 | D6: =B6-C6 -> 0
A7: 1.05 | B7: 6700 | C7: =400+6000*A7 -> 6700 | D7: =B7-C7 -> 0
A8: 1.1 | B8: 7100 | C8: =400+6000*A8 -> 7000 | D8: =B8-C8 -> 100
A9: 1.15 | B9: 7400 | C9: =400+6000*A9 -> 7300 | D9: =B9-C9 -> 100
A10: 1.2 | B10: 7700 | C10: =400+6000*A10 -> 7600 | D10: =B10-C10 -> 100
A11: 1.25 | B11: 8000 | C11: =400+6000*A11 -> 7900 | D11: =B11-C11 -> 100
A12: 1.3 | B12: 8300 | C12: =400+6000*A12 -> 8200 | D12: =B12-C12 -> 100
A13: 1.35 | B13: 8600 | C13: =400+6000*A13 -> 8500 | D13: =B13-C13 -> 100
A14: 1.4 | B14: 8800 | C14: =400+6000*A14 -> 8800 | D14: =B14-C14 -> 0 | E14: Hệ số 1.4 không có trong dữ liệu tháng 8 – giá trị suy ra từ quy luật, CẦN XÁC NHẬN
A15: 1.5 | B15: 9600 | C15: =400+6000*A15 -> 9400 | D15: =B15-C15 -> 200

Sheet NHAN_VIEN
A1: DANH MỤC NHÂN VIÊN KHOÁN SẢN XUẤT & TÀI XẾ
A2: Mã NV là khoá duy nhất (dùng mã máy chấm công / CCCD như file cũ). Mọi sheet khác tra cứu theo mã, không theo tên. Không xoá dòng người nghỉ – đổi Tình trạng.
A4: STT | B4: Mã NV | C4: Họ và tên | D4: Chức vụ | E4: Bộ phận | F4: Hình thức | G4: Hệ số khoán | H4: Đơn giá công nhật (đ/công) | I4: Tình trạng | J4: Ghi chú
A5: 1 | B5: 046085007061 | C5: Lê Vang | D5: Quản lý SX | E5: Sản xuất | F5: Khoán | G5: 1.5 | I5: Chính thức
A6: 2 | B6: 046077003925 | C6: Trần Đình Mạnh | D6: Tổ phó ca sản xuất | E6: Sản xuất | F6: Khoán | G6: 1.35 | I6: Chính thức
A7: 3 | B7: 046177012486 | C7: Lê Thị Bình | D7: Công nhân Chế biến | E7: Sản xuất | F7: Khoán | G7: 1.1 | I7: Chính thức
A8: 4 | B8: 046179008435 | C8: Trần Thị Tích | D8: Công nhân Chế biến | E8: Sản xuất | F8: Khoán | G8: 1.15 | I8: Chính thức
A9: 5 | B9: 046175005132 | C9: Lê Thị Nga | D9: Công nhân Chế biến | E9: Sản xuất | F9: Khoán | G9: 1.15 | I9: Chính thức
A10: 6 | B10: 046090006706 | C10: Phạm Bá Lượng | D10: Công nhân Chế biến | E10: Sản xuất | F10: Khoán | G10: 1.3 | I10: Chính thức
A11: 7 | B11: 046178011746 | C11: Văn Thị Vinh | D11: Công nhân Chế biến | E11: Sản xuất | F11: Khoán | G11: 1.1 | I11: Chính thức
A12: 8 | B12: 046172008975 | C12: Nguyễn Thị Điệp | D12: Công nhân Chế biến | E12: Sản xuất | F12: Khoán | G12: 1.1 | I12: Chính thức
A13: 9 | B13: NV_KIMANH | C13: Lê Thị Kim Anh | D13: Công nhân Chế biến | E13: Sản xuất | F13: Khoán | G13: 1 | I13: Chính thức | J13: File cũ không có mã NV – tạm đặt, cần bổ sung
A14: 10 | B14: 046074011254 | C14: Trần Đức Phúc | D14: Công nhân Chế biến | E14: Sản xuất | F14: Khoán | G14: 1.1 | I14: Chính thức
A15: 11 | B15: 046172013837 | C15: Nguyễn Thị Nhung | D15: Công nhân Chế biến | E15: Sản xuất | F15: Khoán | G15: 0.9 | I15: Chính thức
A16: 12 | B16: 046175008129 | C16: Lê Thị Thu Hữu | D16: Công nhân Chế biến | E16: Sản xuất | F16: Khoán | G16: 1.1 | I16: Chính thức
A17: 13 | B17: 046206004482 | C17: Trần Đình Lĩnh | D17: Công nhân Chế biến | E17: Sản xuất | F17: Khoán | G17: 1.05 | I17: Thử việc
A18: 14 | B18: 046178006439 | C18: Nguyễn Thị Thúy Vân | D18: Công nhân Chế biến | E18: Sản xuất | F18: Khoán | G18: 1.15 | I18: Chính thức
A19: 15 | B19: 046172008914 | C19: Trần Thị Thùy | D19: Công nhân Chế biến | E19: Sản xuất | F19: Khoán | G19: 1.1 | I19: Chính thức
A20: 16 | B20: 046177011413 | C20: Lê Thị Thơ | D20: Công nhân Chế biến | E20: Sản xuất | F20: Khoán | G20: 1.1 | I20: Chính thức
A21: 17 | B21: 046176012012 | C21: Lê Thị Hồng Lan | D21: Công nhân Chế biến | E21: Sản xuất | F21: Khoán | G21: 1 | I21: Chính thức
A22: 18 | B22: 046091004633 | C22: Nguyễn Quang Thọ | D22: Công nhân Chế biến | E22: Sản xuất | F22: Khoán | G22: 0.9 | I22: Chính thức | J22: File cũ mã có khoảng trắng thừa – đã cắt
A23: 19 | B23: 046074013724 | C23: Nguyễn Ngọc Phương | D23: Công nhân Chế biến | E23: Sản xuất | F23: Khoán | G23: 1.3 | I23: Chính thức
A24: 20 | B24: 046099007864 | C24: Lê Lộc | D24: Công nhân Chế biến | E24: Sản xuất | F24: Khoán | G24: 1.15 | I24: Chính thức
A25: 21 | B25: 002191001272 | C25: Thèn Thị Giang | D25: Công nhân Chế biến | E25: Sản xuất | F25: Khoán | G25: 1.15 | I25: Thử việc
A26: 22 | B26: 046087002473 | C26: Nguyễn Tình | D26: Công nhân Chế biến | E26: Sản xuất | F26: Khoán | G26: 0.9 | I26: Thử việc
A27: 23 | B27: 046178010147 | C27: Đặng Thị Huế | D27: Công nhân Chế biến | E27: Sản xuất | F27: Khoán | G27: 1.1 | I27: Chính thức
A28: 24 | B28: 046089009803 | C28: Trần Văn Trình | D28: Tổ trưởng ca sản xuất | E28: Sản xuất | F28: Khoán | G28: 0.9 | I28: Chính thức
A29: 25 | B29: 046084009142 | C29: Trần Văn Hiền | D29: Tổ phó ca sản xuất | E29: Sản xuất | F29: Khoán | G29: 1.5 | I29: Chính thức
A30: 26 | B30: 046207415351 | C30: Trần Văn Tâm | D30: Công nhân Chế biến | E30: Sản xuất | F30: Khoán | G30: 1.15 | I30: Chính thức
A31: 27 | B31: NV_DINHHAI | C31: Trần Đình Hải | D31: Công nhân Chế biến | E31: Sản xuất | F31: Khoán | G31: 1.2 | I31: Chính thức | J31: File cũ dùng TRÙNG mã với Trần Văn Tâm – tạm đặt, cần bổ sung mã đúng
A32: 28 | B32: 046064009756 | C32: Hoàng Lự | D32: Công nhân Chế biến | E32: Sản xuất | F32: Khoán | G32: 1.1 | I32: Chính thức
A33: 29 | B33: 046172013307 | C33: Ngô Thị Thủy | D33: Công nhân Chế biến | E33: Sản xuất | F33: Khoán | G33: 1.1 | I33: Chính thức
A34: 30 | B34: 046165007228 | C34: Lê Thị Hương | D34: Công nhân Chế biến | E34: Sản xuất | F34: Khoán | G34: 1 | I34: Chính thức
A35: 31 | B35: 046181009164 | C35: Hoàng Thị Nhung | D35: Công nhân Chế biến | E35: Sản xuất | F35: Khoán | G35: 1.15 | I35: Chính thức
A36: 32 | B36: 046173005614 | C36: Trần Thị Thu Thủy | D36: Công nhân Chế biến | E36: Sản xuất | F36: Khoán | G36: 1.1 | I36: Chính thức
A37: 33 | B37: 046180005626 | C37: Trần Thị Cẩm Hà | D37: Công nhân Chế biến | E37: Sản xuất | F37: Khoán | G37: 1.15 | I37: Chính thức
A38: 34 | B38: 046177004568 | C38: Nguyễn Thị Kim Tin | D38: Công nhân Chế biến | E38: Sản xuất | F38: Khoán | G38: 1.15 | I38: Chính thức
A39: 35 | B39: 046176012968 | C39: Nguyễn Thị Loan | D39: Công nhân Chế biến | E39: Sản xuất | F39: Khoán | G39: 1.1 | I39: Chính thức
A40: 36 | B40: 046183006914 | C40: Nguyễn Thị Thu Hà | D40: Công nhân Chế biến | E40: Sản xuất | F40: Khoán | G40: 1.1 | I40: Chính thức
A41: 37 | B41: 046077008985 | C41: Ngô Văn Đính | D41: Công nhân Chế biến | E41: Sản xuất | F41: Khoán | G41: 1.25 | I41: Chính thức
A42: 38 | B42: 046180009217 | C42: Ngô Thị Quý | D42: Công nhân Chế biến | E42: Sản xuất | F42: Khoán | G42: 1.15 | I42: Chính thức
A43: 39 | B43: 046075012004 | C43: Ngô Văn Tịnh | D43: Công nhân Chế biến | E43: Sản xuất | F43: Khoán | G43: 1.1 | I43: Chính thức
... A47: 43 | B47: 045200002742 | C47: Hoàng Văn Anh | D47: Công nhân Chế biến | E47: Sản xuất | F47: Khoán | G47: 1.1 | I47: Thử việc
A48: 44 | B48: CN_MAU_01 | C48: (Ví dụ) Nguyễn Văn A | D48: Công nhật sản xuất | E48: Sản xuất | F48: Công nhật | H48: 270000 | I48: Thời vụ | J48: DÒNG VÍ DỤ – người làm công nhật, không nhận khoán, lương = công × đơn giá; tiền ăn tính chung
A49: 45 | B49: 046083009048 | C49: Hoàng Hòa | D49: Lái xe cont | E49: Đội xe | F49: Lái xe | I49: Chính thức | J49: Lương BHXH 4.163.000
A50: 46 | B50: 046096005123 | C50: Bùi Văn Nghĩa | D50: Lái xe cont | E50: Đội xe | F50: Lái xe | I50: Chính thức | J50: Lương BHXH 4.163.000
A51: 47 | B51: 046082013042 | C51: Nguyễn Hữu Mạnh Cường | D51: Lái xe cont | E51: Đội xe | F51: Lái xe | I51: Chính thức | J51: Lương BHXH 4.163.000
A52: 48 | B52: 046074006536 | C52: Nguyễn Đình Hiếu | D52: Lái xe cont | E52: Đội xe | F52: Lái xe | I52: Chính thức | J52: Lương BHXH 4.163.000
A53: 49 | B53: 046091016108 | C53: Nguyễn Đăng Thiện | D53: Lái xe cont | E53: Đội xe | F53: Lái xe | I53: Chính thức | J53: Lương BHXH 4.163.000
A54: 50 | B54: 046074005943 | C54: Lê Tấn Anh | D54: Lái xe cont | E54: Đội xe | F54: Lái xe | I54: Chính thức | J54: Lương BHXH 4.163.000

Sheet KHOAN_KHAC
A1: KHOÁN CÔNG VIỆC KHÁC & CÁC KHOẢN CỘNG/TRỪ VÀO QUỸ KHOÁN
A2: Thay bảng C6:P15 cũ. Để trống "Mã NV nhận" → chia chung theo giờ cho cả tổ (ô M15−400.000 cũ). Điền mã → trả đích danh (các ô +100.000/+200.000 gõ tay cũ). Khoản trừ nhập đơn giá âm.
A4: STT | B4: Ngày | C4: Nội dung công việc | D4: Số công | E4: Đơn giá (đ/công) | F4: Thành tiền | G4: Mã NV nhận (đích danh) | H4: Tên (tự tra) | I4: Ghi chú
A5: 1 | B5: 06/07/2026 | C5: Chèn hàng băng tải – phần Lê Vang | D5: 0.5 | E5: 200000 | F5: =D5*E5 -> 100000 | G5: 046085007061 | H5: =IF(G5="","",IFERROR(INDEX(NV_TEN,MATCH(G5,NV_MA,0)),"MÃ KHÔNG CÓ")) -> Lê Vang | I5: Sheet cũ: 2 công × 200.000 = 400.000 rồi chia tay +100k/+100k/+200k
A6: 2 | B6: 06/07/2026 | C6: Chèn hàng băng tải – phần Phạm Bá Lượng | D6: 0.5 | E6: 200000 | F6: =D6*E6 -> 100000 | G6: 046090006706 | H6: =IF(G6="","",IFERROR(INDEX(NV_TEN,MATCH(G6,NV_MA,0)),"MÃ KHÔNG CÓ")) -> Phạm Bá Lượng
A7: 3 | B7: 06/07/2026 | C7: Chèn hàng băng tải – phần Trần Văn Hiền | D7: 1 | E7: 200000 | F7: =D7*E7 -> 200000 | G7: 046084009142 | H7: =IF(G7="","",IFERROR(INDEX(NV_TEN,MATCH(G7,NV_MA,0)),"MÃ KHÔNG CÓ")) -> Trần Văn Hiền
A8: 4 | B8: 22/07/2026 | C8: Xử lý hàng 3L chất vào thùng đóng SW | D8: 4 | E8: 200000 | F8: =D8*E8 -> 800000 | H8: =IF(G8="","",IFERROR(INDEX(NV_TEN,MATCH(G8,NV_MA,0)),"MÃ KHÔNG CÓ"))
A9: 5 | B9: 29/07/2026 | C9: Thay bao dày, đóng kiện SW | D9: 5 | E9: 200000 | F9: =D9*E9 -> 1000000 | H9: =IF(G9="","",IFERROR(INDEX(NV_TEN,MATCH(G9,NV_MA,0)),"MÃ KHÔNG CÓ"))
A10: 6 | B10: 30/07/2026 | C10: Chất hàng đóng SW RSS1 | D10: 10 | E10: 200000 | F10: =D10*E10 -> 2000000 | H10: =IF(G10="","",IFERROR(INDEX(NV_TEN,MATCH(G10,NV_MA,0)),"MÃ KHÔNG CÓ"))
A11: 7 | B11: 08/2026 | C11: Khẩu trang tháng 08 | D11: 4 | E11: 100000 | F11: =D11*E11 -> 400000 | H11: =IF(G11="","",IFERROR(INDEX(NV_TEN,MATCH(G11,NV_MA,0)),"MÃ KHÔNG CÓ"))
A12: 8 | B12: 08/2026 | C12: Khấu trừ CN thời vụ A Lưới làm sản xuất (trừ khỏi quỹ) | D12: 101.5 | E12: -300000 | F12: =D12*E12 -> -30450000 | H12: =IF(G12="","",IFERROR(INDEX(NV_TEN,MATCH(G12,NV_MA,0)),"MÃ KHÔNG CÓ")) | I12: Lấy từ file lương thời vụ A Lưới; đơn giá âm = trừ
A13: 9 | B13: 08/2026 | C13: Vệ sinh máy mix 38 ca | D13: 38 | E13: 100000 | F13: =D13*E13 -> 3800000 | H13: =IF(G13="","",IFERROR(INDEX(NV_TEN,MATCH(G13,NV_MA,0)),"MÃ KHÔNG CÓ"))
F14: =IF(D14="",0,D14*E14) -> 0 | H14: =IF(G14="","",IFERROR(INDEX(NV_TEN,MATCH(G14,NV_MA,0)),"MÃ KHÔNG CÓ"))
F15: =IF(D15="",0,D15*E15) -> 0 | H15: =IF(G15="","",IFERROR(INDEX(NV_TEN,MATCH(G15,NV_MA,0)),"MÃ KHÔNG CÓ"))
F16: =IF(D16="",0,D16*E16) -> 0 | H16: =IF(G16="","",IFERROR(INDEX(NV_TEN,MATCH(G16,NV_MA,0)),"MÃ KHÔNG CÓ"))
F17: =IF(D17="",0,D17*E17) -> 0 | H17: =IF(G17="","",IFERROR(INDEX(NV_TEN,MATCH(G17,NV_MA,0)),"MÃ KHÔNG CÓ"))
F18: =IF(D18="",0,D18*E18) -> 0 | H18: =IF(G18="","",IFERROR(INDEX(NV_TEN,MATCH(G18,NV_MA,0)),"MÃ KHÔNG CÓ"))
F19: =IF(D19="",0,D19*E19) -> 0 | H19: =IF(G19="","",IFERROR(INDEX(NV_TEN,MATCH(G19,NV_MA,0)),"MÃ KHÔNG CÓ"))
F20: =IF(D20="",0,D20*E20) -> 0 | H20: =IF(G20="","",IFERROR(INDEX(NV_TEN,MATCH(G20,NV_MA,0)),"MÃ KHÔNG CÓ"))
F21: =IF(D21="",0,D21*E21) -> 0 | H21: =IF(G21="","",IFERROR(INDEX(NV_TEN,MATCH(G21,NV_MA,0)),"MÃ KHÔNG CÓ"))
F22: =IF(D22="",0,D22*E22) -> 0 | H22: =IF(G22="","",IFERROR(INDEX(NV_TEN,MATCH(G22,NV_MA,0)),"MÃ KHÔNG CÓ"))
F23: =IF(D23="",0,D23*E23) -> 0 | H23: =IF(G23="","",IFERROR(INDEX(NV_TEN,MATCH(G23,NV_MA,0)),"MÃ KHÔNG CÓ"))
F24: =IF(D24="",0,D24*E24) -> 0 | H24: =IF(G24="","",IFERROR(INDEX(NV_TEN,MATCH(G24,NV_MA,0)),"MÃ KHÔNG CÓ"))
F25: =IF(D25="",0,D25*E25) -> 0 | H25: =IF(G25="","",IFERROR(INDEX(NV_TEN,MATCH(G25,NV_MA,0)),"MÃ KHÔNG CÓ"))
... F39: =IF(D39="",0,D39*E39) -> 0 | H39: =IF(G39="","",IFERROR(INDEX(NV_TEN,MATCH(G39,NV_MA,0)),"MÃ KHÔNG CÓ"))
C41: Tổng chia chung theo giờ | F41: =SUMIFS(F5:F39,G5:G39,"") -> -22450000
C42: Tổng trả đích danh | F42: =SUMIFS(F5:F39,G5:G39,"<>") -> 400000
C43: Tổng cộng (ô M15 cũ) | F43: =F41+F42 -> -22050000

Sheet BCC_KHOAN
A1: BẢNG CHẤM CÔNG KHOÁN SẢN XUẤT (giờ/ngày)
A2: Nhập số giờ vào ô xanh. Chỉ nhập số. Ngày lễ nghỉ để trống. Mã NV tra tên tự động; dòng có mã lạ sẽ báo "MÃ KHÔNG CÓ".
A3: Ngày → | E3: =IF(0<DAY(EOMONTH(DATE(NAM,THANG,1),0)),DATE(NAM,THANG,1)+0,"") -> 46235 | F3: =IF(1<DAY(EOMONTH(DATE(NAM,THANG,1),0)),DATE(NAM,THANG,1)+1,"") -> 46236 | G3: =IF(2<DAY(EOMONTH(DATE(NAM,THANG,1),0)),DATE(NAM,THANG,1)+2,"") -> 46237 | H3: =IF(3<DAY(EOMONTH(DATE(NAM,THANG,1),0)),DATE(NAM,THANG,1)+3,"") -> 46238 | I3: =IF(4<DAY(EOMONTH(DATE(NAM,THANG,1),0)),DATE(NAM,THANG,1)+4,"") -> 46239 | J3: =IF(5<DAY(EOMONTH(DATE(NAM,THANG,1),0)),DATE(NAM,THANG,1)+5,"") -> 46240 | K3: =IF(6<DAY(EOMONTH(DATE(NAM,THANG,1),0)),DATE(NAM,THANG,1)+6,"") -> 46241 | L3: =IF(7<DAY(EOMONTH(DATE(NAM,THANG,1),0)),DATE(NAM,THANG,1)+7,"") -> 46242 | M3: =IF(8<DAY(EOMONTH(DATE(NAM,THANG,1),0)),DATE(NAM,THANG,1)+8,"") -> 46243 | N3: =IF(9<DAY(EOMONTH(DATE(NAM,THANG,1),0)),DATE(NAM,THANG,1)+9,"") -> 46244 | O3: =IF(10<DAY(EOMONTH(DATE(NAM,THANG,1),0)),DATE(NAM,THANG,1)+10,"") -> 46245 | P3: =IF(11<DAY(EOMONTH(DATE(NAM,THANG,1),0)),DATE(NAM,THANG,1)+11,"") -> 46246 | Q3: =IF(12<DAY(EOMONTH(DATE(NAM,THANG,1),0)),DATE(NAM,THANG,1)+12,"") -> 46247 | R3: =IF(13<DAY(EOMONTH(DATE(NAM,THANG,1),0)),DATE(NAM,THANG,1)+13,"") -> 46248 | S3: =IF(14<DAY(EOMONTH(DATE(NAM,THANG,1),0)),DATE(NAM,THANG,1)+14,"") -> 46249 | T3: =IF(15<DAY(EOMONTH(DATE(NAM,THANG,1),0)),DATE(NAM,THANG,1)+15,"") -> 46250 | U3: =IF(16<DAY(EOMONTH(DATE(NAM,THANG,1),0)),DATE(NAM,THANG,1)+16,"") -> 46251 | V3: =IF(17<DAY(EOMONTH(DATE(NAM,THANG,1),0)),DATE(NAM,THANG,1)+17,"") -> 46252 | W3: =IF(18<DAY(EOMONTH(DATE(NAM,THANG,1),0)),DATE(NAM,THANG,1)+18,"") -> 46253 | X3: =IF(19<DAY(EOMONTH(DATE(NAM,THANG,1),0)),DATE(NAM,THANG,1)+19,"") -> 46254 | Y3: =IF(20<DAY(EOMONTH(DATE(NAM,THANG,1),0)),DATE(NAM,THANG,1)+20,"") -> 46255 | Z3: =IF(21<DAY(EOMONTH(DATE(NAM,THANG,1),0)),DATE(NAM,THANG,1)+21,"") -> 46256 | AA3: =IF(22<DAY(EOMONTH(DATE(NAM,THANG,1),0)),DATE(NAM,THANG,1)+22,"") -> 46257 | AB3: =IF(23<DAY(EOMONTH(DATE(NAM,THANG,1),0)),DATE(NAM,THANG,1)+23,"") -> 46258 | AC3: =IF(24<DAY(EOMONTH(DATE(NAM,THANG,1),0)),DATE(NAM,THANG,1)+24,"") -> 46259 | AD3: =IF(25<DAY(EOMONTH(DATE(NAM,THANG,1),0)),DATE(NAM,THANG,1)+25,"") -> 46260 | AE3: =IF(26<DAY(EOMONTH(DATE(NAM,THANG,1),0)),DATE(NAM,THANG,1)+26,"") -> 46261 | AF3: =IF(27<DAY(EOMONTH(DATE(NAM,THANG,1),0)),DATE(NAM,THANG,1)+27,"") -> 46262 | AG3: =IF(28<DAY(EOMONTH(DATE(NAM,THANG,1),0)),DATE(NAM,THANG,1)+28,"") -> 46263 | AH3: =IF(29<DAY(EOMONTH(DATE(NAM,THANG,1),0)),DATE(NAM,THANG,1)+29,"") -> 46264 | AI3: =IF(30<DAY(EOMONTH(DATE(NAM,THANG,1),0)),DATE(NAM,THANG,1)+30,"") -> 46265
E4: =IF(E3="","",CHOOSE(WEEKDAY(E3),"CN","T2","T3","T4","T5","T6","T7")) -> T7 | F4: =IF(F3="","",CHOOSE(WEEKDAY(F3),"CN","T2","T3","T4","T5","T6","T7")) -> CN | G4: =IF(G3="","",CHOOSE(WEEKDAY(G3),"CN","T2","T3","T4","T5","T6","T7")) -> T2 | H4: =IF(H3="","",CHOOSE(WEEKDAY(H3),"CN","T2","T3","T4","T5","T6","T7")) -> T3 | I4: =IF(I3="","",CHOOSE(WEEKDAY(I3),"CN","T2","T3","T4","T5","T6","T7")) -> T4 | J4: =IF(J3="","",CHOOSE(WEEKDAY(J3),"CN","T2","T3","T4","T5","T6","T7")) -> T5 | K4: =IF(K3="","",CHOOSE(WEEKDAY(K3),"CN","T2","T3","T4","T5","T6","T7")) -> T6 | L4: =IF(L3="","",CHOOSE(WEEKDAY(L3),"CN","T2","T3","T4","T5","T6","T7")) -> T7 | ... AI4: =IF(AI3="","",CHOOSE(WEEKDAY(AI3),"CN","T2","T3","T4","T5","T6","T7")) -> T2
A5: STT | B5: Mã NV | C5: Họ và tên | D5: Hình thức | E5: 1 | F5: 2 | G5: 3 | H5: 4 | I5: 5 | J5: 6 | K5: 7 | L5: 8 | M5: 9 | N5: 10 | O5: 11 | P5: 12 | Q5: 13 | R5: 14 | S5: 15 | T5: 16 | U5: 17 | V5: 18 | W5: 19 | X5: 20 | Y5: 21 | Z5: 22 | AA5: 23 | AB5: 24 | AC5: 25 | AD5: 26 | AE5: 27 | AF5: 28 | AG5: 29 | AH5: 30 | AI5: 31 | AJ5: Tổng giờ | AK5: Công
A6: 1 | B6: 046085007061 | C6: =IFERROR(INDEX(NV_TEN,MATCH(B6,NV_MA,0)),"MÃ KHÔNG CÓ") -> Lê Vang | D6: =IFERROR(INDEX(NV_HINHTHUC,MATCH(B6,NV_MA,0)),"") -> Khoán | AJ6: =SUM(E6:AI6) -> 0 | AK6: =IF(AJ6=0,0,AJ6/GIO_CONG) -> 0
A7: 2 | B7: 046077003925 | C7: =IFERROR(INDEX(NV_TEN,MATCH(B7,NV_MA,0)),"MÃ KHÔNG CÓ") -> Trần Đình Mạnh | D7: =IFERROR(INDEX(NV_HINHTHUC,MATCH(B7,NV_MA,0)),"") -> Khoán | AJ7: =SUM(E7:AI7) -> 0 | AK7: =IF(AJ7=0,0,AJ7/GIO_CONG) -> 0
A8: 3 | B8: 046177012486 | C8: =IFERROR(INDEX(NV_TEN,MATCH(B8,NV_MA,0)),"MÃ KHÔNG CÓ") -> Lê Thị Bình | D8: =IFERROR(INDEX(NV_HINHTHUC,MATCH(B8,NV_MA,0)),"") -> Khoán | AJ8: =SUM(E8:AI8) -> 0 | AK8: =IF(AJ8=0,0,AJ8/GIO_CONG) -> 0
A9: 4 | B9: 046179008435 | C9: =IFERROR(INDEX(NV_TEN,MATCH(B9,NV_MA,0)),"MÃ KHÔNG CÓ") -> Trần Thị Tích | D9: =IFERROR(INDEX(NV_HINHTHUC,MATCH(B9,NV_MA,0)),"") -> Khoán | AJ9: =SUM(E9:AI9) -> 0 | AK9: =IF(AJ9=0,0,AJ9/GIO_CONG) -> 0
A10: 5 | B10: 046175005132 | C10: =IFERROR(INDEX(NV_TEN,MATCH(B10,NV_MA,0)),"MÃ KHÔNG CÓ") -> Lê Thị Nga | D10: =IFERROR(INDEX(NV_HINHTHUC,MATCH(B10,NV_MA,0)),"") -> Khoán | AJ10: =SUM(E10:AI10) -> 0 | AK10: =IF(AJ10=0,0,AJ10/GIO_CONG) -> 0
A11: 6 | B11: 046090006706 | C11: =IFERROR(INDEX(NV_TEN,MATCH(B11,NV_MA,0)),"MÃ KHÔNG CÓ") -> Phạm Bá Lượng | D11: =IFERROR(INDEX(NV_HINHTHUC,MATCH(B11,NV_MA,0)),"") -> Khoán | AJ11: =SUM(E11:AI11) -> 0 | AK11: =IF(AJ11=0,0,AJ11/GIO_CONG) -> 0
A12: 7 | B12: 046178011746 | C12: =IFERROR(INDEX(NV_TEN,MATCH(B12,NV_MA,0)),"MÃ KHÔNG CÓ") -> Văn Thị Vinh | D12: =IFERROR(INDEX(NV_HINHTHUC,MATCH(B12,NV_MA,0)),"") -> Khoán | AJ12: =SUM(E12:AI12) -> 0 | AK12: =IF(AJ12=0,0,AJ12/GIO_CONG) -> 0
A13: 8 | B13: 046172008975 | C13: =IFERROR(INDEX(NV_TEN,MATCH(B13,NV_MA,0)),"MÃ KHÔNG CÓ") -> Nguyễn Thị Điệp | D13: =IFERROR(INDEX(NV_HINHTHUC,MATCH(B13,NV_MA,0)),"") -> Khoán | AJ13: =SUM(E13:AI13) -> 0 | AK13: =IF(AJ13=0,0,AJ13/GIO_CONG) -> 0
A14: 9 | B14: NV_KIMANH | C14: =IFERROR(INDEX(NV_TEN,MATCH(B14,NV_MA,0)),"MÃ KHÔNG CÓ") -> Lê Thị Kim Anh | D14: =IFERROR(INDEX(NV_HINHTHUC,MATCH(B14,NV_MA,0)),"") -> Khoán | AJ14: =SUM(E14:AI14) -> 0 | AK14: =IF(AJ14=0,0,AJ14/GIO_CONG) -> 0
A15: 10 | B15: 046074011254 | C15: =IFERROR(INDEX(NV_TEN,MATCH(B15,NV_MA,0)),"MÃ KHÔNG CÓ") -> Trần Đức Phúc | D15: =IFERROR(INDEX(NV_HINHTHUC,MATCH(B15,NV_MA,0)),"") -> Khoán | AJ15: =SUM(E15:AI15) -> 0 | AK15: =IF(AJ15=0,0,AJ15/GIO_CONG) -> 0
A16: 11 | B16: 046172013837 | C16: =IFERROR(INDEX(NV_TEN,MATCH(B16,NV_MA,0)),"MÃ KHÔNG CÓ") -> Nguyễn Thị Nhung | D16: =IFERROR(INDEX(NV_HINHTHUC,MATCH(B16,NV_MA,0)),"") -> Khoán | AJ16: =SUM(E16:AI16) -> 0 | AK16: =IF(AJ16=0,0,AJ16/GIO_CONG) -> 0
A17: 12 | B17: 046175008129 | C17: =IFERROR(INDEX(NV_TEN,MATCH(B17,NV_MA,0)),"MÃ KHÔNG CÓ") -> Lê Thị Thu Hữu | D17: =IFERROR(INDEX(NV_HINHTHUC,MATCH(B17,NV_MA,0)),"") -> Khoán | AJ17: =SUM(E17:AI17) -> 0 | AK17: =IF(AJ17=0,0,AJ17/GIO_CONG) -> 0
... A23: 18 | B23: 046091004633 | C23: =IFERROR(INDEX(NV_TEN,MATCH(B23,NV_MA,0)),"MÃ KHÔNG CÓ") -> Nguyễn Quang Thọ | D23: =IFERROR(INDEX(NV_HINHTHUC,MATCH(B23,NV_MA,0)),"") -> Khoán | AJ23: =SUM(E23:AI23) -> 0 | AK23: =IF(AJ23=0,0,AJ23/GIO_CONG) -> 0
A24: 19 | B24: 046074013724 | C24: =IFERROR(INDEX(NV_TEN,MATCH(B24,NV_MA,0)),"MÃ KHÔNG CÓ") -> Nguyễn Ngọc Phương | D24: =IFERROR(INDEX(NV_HINHTHUC,MATCH(B24,NV_MA,0)),"") -> Khoán | G24: 8 | I24: 8 | O24: 8 | P24: 12 | Q24: 8 | R24: 12 | Z24: 12 | AA24: 16 | AB24: 12 | AC24: 4 | AD24: 12 | AE24: 8 | AF24: 4 | AG24: 8 | AJ24: =SUM(E24:AI24) -> 132 | AK24: =IF(AJ24=0,0,AJ24/GIO_CONG) -> 16.5
A25: 20 | B25: 046099007864 | C25: =IFERROR(INDEX(NV_TEN,MATCH(B25,NV_MA,0)),"MÃ KHÔNG CÓ") -> Lê Lộc | D25: =IFERROR(INDEX(NV_HINHTHUC,MATCH(B25,NV_MA,0)),"") -> Khoán | AJ25: =SUM(E25:AI25) -> 0 | AK25: =IF(AJ25=0,0,AJ25/GIO_CONG) -> 0
A26: 21 | B26: 002191001272 | C26: =IFERROR(INDEX(NV_TEN,MATCH(B26,NV_MA,0)),"MÃ KHÔNG CÓ") -> Thèn Thị Giang | D26: =IFERROR(INDEX(NV_HINHTHUC,MATCH(B26,NV_MA,0)),"") -> Khoán | AJ26: =SUM(E26:AI26) -> 0 | AK26: =IF(AJ26=0,0,AJ26/GIO_CONG) -> 0
A27: 22 | B27: 046087002473 | C27: =IFERROR(INDEX(NV_TEN,MATCH(B27,NV_MA,0)),"MÃ KHÔNG CÓ") -> Nguyễn Tình | D27: =IFERROR(INDEX(NV_HINHTHUC,MATCH(B27,NV_MA,0)),"") -> Khoán | AJ27: =SUM(E27:AI27) -> 0 | AK27: =IF(AJ27=0,0,AJ27/GIO_CONG) -> 0
A28: 23 | B28: 046178010147 | C28: =IFERROR(INDEX(NV_TEN,MATCH(B28,NV_MA,0)),"MÃ KHÔNG CÓ") -> Đặng Thị Huế | D28: =IFERROR(INDEX(NV_HINHTHUC,MATCH(B28,NV_MA,0)),"") -> Khoán | AJ28: =SUM(E28:AI28) -> 0 | AK28: =IF(AJ28=0,0,AJ28/GIO_CONG) -> 0
A29: 24 | B29: 046089009803 | C29: =IFERROR(INDEX(NV_TEN,MATCH(B29,NV_MA,0)),"MÃ KHÔNG CÓ") -> Trần Văn Trình | D29: =IFERROR(INDEX(NV_HINHTHUC,MATCH(B29,NV_MA,0)),"") -> Khoán | AJ29: =SUM(E29:AI29) -> 0 | AK29: =IF(AJ29=0,0,AJ29/GIO_CONG) -> 0
A30: 25 | B30: 046084009142 | C30: =IFERROR(INDEX(NV_TEN,MATCH(B30,NV_MA,0)),"MÃ KHÔNG CÓ") -> Trần Văn Hiền | D30: =IFERROR(INDEX(NV_HINHTHUC,MATCH(B30,NV_MA,0)),"") -> Khoán | AJ30: =SUM(E30:AI30) -> 0 | AK30: =IF(AJ30=0,0,AJ30/GIO_CONG) -> 0
A31: 26 | B31: 046207415351 | C31: =IFERROR(INDEX(NV_TEN,MATCH(B31,NV_MA,0)),"MÃ KHÔNG CÓ") -> Trần Văn Tâm | D31: =IFERROR(INDEX(NV_HINHTHUC,MATCH(B31,NV_MA,0)),"") -> Khoán | G31: 8 | I31: 8 | O31: 8 | P31: 12 | Q31: 8 | R31: 12 | Z31: 3 | AA31: 16 | AB31: 12 | AC31: 4 | AD31: 12 | AE31: 8 | AF31: 4 | AG31: 8 | AJ31: =SUM(E31:AI31) -> 123 | AK31: =IF(AJ31=0,0,AJ31/GIO_CONG) -> 15.375
A32: 27 | B32: NV_DINHHAI | C32: =IFERROR(INDEX(NV_TEN,MATCH(B32,NV_MA,0)),"MÃ KHÔNG CÓ") -> Trần Đình Hải | D32: =IFERROR(INDEX(NV_HINHTHUC,MATCH(B32,NV_MA,0)),"") -> Khoán | AJ32: =SUM(E32:AI32) -> 0 | AK32: =IF(AJ32=0,0,AJ32/GIO_CONG) -> 0
A33: 28 | B33: 046064009756 | C33: =IFERROR(INDEX(NV_TEN,MATCH(B33,NV_MA,0)),"MÃ KHÔNG CÓ") -> Hoàng Lự | D33: =IFERROR(INDEX(NV_HINHTHUC,MATCH(B33,NV_MA,0)),"") -> Khoán | AJ33: =SUM(E33:AI33) -> 0 | AK33: =IF(AJ33=0,0,AJ33/GIO_CONG) -> 0
A34: 29 | B34: 046172013307 | C34: =IFERROR(INDEX(NV_TEN,MATCH(B34,NV_MA,0)),"MÃ KHÔNG CÓ") -> Ngô Thị Thủy | D34: =IFERROR(INDEX(NV_HINHTHUC,MATCH(B34,NV_MA,0)),"") -> Khoán | AJ34: =SUM(E34:AI34) -> 0 | AK34: =IF(AJ34=0,0,AJ34/GIO_CONG) -> 0
A35: 30 | B35: 046165007228 | C35: =IFERROR(INDEX(NV_TEN,MATCH(B35,NV_MA,0)),"MÃ KHÔNG CÓ") -> Lê Thị Hương | D35: =IFERROR(INDEX(NV_HINHTHUC,MATCH(B35,NV_MA,0)),"") -> Khoán | AJ35: =SUM(E35:AI35) -> 0 | AK35: =IF(AJ35=0,0,AJ35/GIO_CONG) -> 0
A36: 31 | B36: 046181009164 | C36: =IFERROR(INDEX(NV_TEN,MATCH(B36,NV_MA,0)),"MÃ KHÔNG CÓ") -> Hoàng Thị Nhung | D36: =IFERROR(INDEX(NV_HINHTHUC,MATCH(B36,NV_MA,0)),"") -> Khoán | AJ36: =SUM(E36:AI36) -> 0 | AK36: =IF(AJ36=0,0,AJ36/GIO_CONG) -> 0
A37: 32 | B37: 046173005614 | C37: =IFERROR(INDEX(NV_TEN,MATCH(B37,NV_MA,0)),"MÃ KHÔNG CÓ") -> Trần Thị Thu Thủy | D37: =IFERROR(INDEX(NV_HINHTHUC,MATCH(B37,NV_MA,0)),"") -> Khoán | AJ37: =SUM(E37:AI37) -> 0 | AK37: =IF(AJ37=0,0,AJ37/GIO_CONG) -> 0
A38: 33 | B38: 046180005626 | C38: =IFERROR(INDEX(NV_TEN,MATCH(B38,NV_MA,0)),"MÃ KHÔNG CÓ") -> Trần Thị Cẩm Hà | D38: =IFERROR(INDEX(NV_HINHTHUC,MATCH(B38,NV_MA,0)),"") -> Khoán | AJ38: =SUM(E38:AI38) -> 0 | AK38: =IF(AJ38=0,0,AJ38/GIO_CONG) -> 0
A39: 34 | B39: 046177004568 | C39: =IFERROR(INDEX(NV_TEN,MATCH(B39,NV_MA,0)),"MÃ KHÔNG CÓ") -> Nguyễn Thị Kim Tin | D39: =IFERROR(INDEX(NV_HINHTHUC,MATCH(B39,NV_MA,0)),"") -> Khoán | AJ39: =SUM(E39:AI39) -> 0 | AK39: =IF(AJ39=0,0,AJ39/GIO_CONG) -> 0
A40: 35 | B40: 046176012968 | C40: =IFERROR(INDEX(NV_TEN,MATCH(B40,NV_MA,0)),"MÃ KHÔNG CÓ") -> Nguyễn Thị Loan | D40: =IFERROR(INDEX(NV_HINHTHUC,MATCH(B40,NV_MA,0)),"") -> Khoán | AJ40: =SUM(E40:AI40) -> 0 | AK40: =IF(AJ40=0,0,AJ40/GIO_CONG) -> 0
A41: 36 | B41: 046183006914 | C41: =IFERROR(INDEX(NV_TEN,MATCH(B41,NV_MA,0)),"MÃ KHÔNG CÓ") -> Nguyễn Thị Thu Hà | D41: =IFERROR(INDEX(NV_HINHTHUC,MATCH(B41,NV_MA,0)),"") -> Khoán | AJ41: =SUM(E41:AI41) -> 0 | AK41: =IF(AJ41=0,0,AJ41/GIO_CONG) -> 0
A42: 37 | B42: 046077008985 | C42: =IFERROR(INDEX(NV_TEN,MATCH(B42,NV_MA,0)),"MÃ KHÔNG CÓ") -> Ngô Văn Đính | D42: =IFERROR(INDEX(NV_HINHTHUC,MATCH(B42,NV_MA,0)),"") -> Khoán | AJ42: =SUM(E42:AI42) -> 0 | AK42: =IF(AJ42=0,0,AJ42/GIO_CONG) -> 0
A43: 38 | B43: 046180009217 | C43: =IFERROR(INDEX(NV_TEN,MATCH(B43,NV_MA,0)),"MÃ KHÔNG CÓ") -> Ngô Thị Quý | D43: =IFERROR(INDEX(NV_HINHTHUC,MATCH(B43,NV_MA,0)),"") -> Khoán | AJ43: =SUM(E43:AI43) -> 0 | AK43: =IF(AJ43=0,0,AJ43/GIO_CONG) -> 0
... A47: 42 | B47: 046095008572 | C47: =IFERROR(INDEX(NV_TEN,MATCH(B47,NV_MA,0)),"MÃ KHÔNG CÓ") -> Trần Văn Tấn | D47: =IFERROR(INDEX(NV_HINHTHUC,MATCH(B47,NV_MA,0)),"") -> Khoán | AJ47: =SUM(E47:AI47) -> 0 | AK47: =IF(AJ47=0,0,AJ47/GIO_CONG) -> 0
A48: 43 | B48: 045200002742 | C48: =IFERROR(INDEX(NV_TEN,MATCH(B48,NV_MA,0)),"MÃ KHÔNG CÓ") -> Hoàng Văn Anh | D48: =IFERROR(INDEX(NV_HINHTHUC,MATCH(B48,NV_MA,0)),"") -> Khoán | E48: 8 | F48: 8 | G48: 8 | H48: 8 | I48: 8 | J48: 8 | K48: 8 | L48: 8 | M48: 8 | N48: 8 | O48: 8 | P48: 8 | Q48: 8 | R48: 8 | S48: 8 | T48: 8 | U48: 8 | V48: 8 | W48: 8 | X48: 8 | Y48: 8 | Z48: 8 | AA48: 8 | AB48: 8 | AC48: 8 | AJ48: =SUM(E48:AI48) -> 200 | AK48: =IF(AJ48=0,0,AJ48/GIO_CONG) -> 25
A49: 44 | B49: CN_MAU_01 | C49: =IFERROR(INDEX(NV_TEN,MATCH(B49,NV_MA,0)),"MÃ KHÔNG CÓ") -> (Ví dụ) Nguyễn Văn A | D49: =IFERROR(INDEX(NV_HINHTHUC,MATCH(B49,NV_MA,0)),"") -> Công nhật | AJ49: =SUM(E49:AI49) -> 0 | AK49: =IF(AJ49=0,0,AJ49/GIO_CONG) -> 0
C50: =IF(B50="","",IFERROR(INDEX(NV_TEN,MATCH(B50,NV_MA,0)),"MÃ KHÔNG CÓ")) | D50: =IF(B50="","",IFERROR(INDEX(NV_HINHTHUC,MATCH(B50,NV_MA,0)),"")) | AJ50: =IF(B50="","",SUM(E50:AI50)) | AK50: =IF(B50="","",AJ50/GIO_CONG)
C51: =IF(B51="","",IFERROR(INDEX(NV_TEN,MATCH(B51,NV_MA,0)),"MÃ KHÔNG CÓ")) | D51: =IF(B51="","",IFERROR(INDEX(NV_HINHTHUC,MATCH(B51,NV_MA,0)),"")) | AJ51: =IF(B51="","",SUM(E51:AI51)) | AK51: =IF(B51="","",AJ51/GIO_CONG)
C52: =IF(B52="","",IFERROR(INDEX(NV_TEN,MATCH(B52,NV_MA,0)),"MÃ KHÔNG CÓ")) | D52: =IF(B52="","",IFERROR(INDEX(NV_HINHTHUC,MATCH(B52,NV_MA,0)),"")) | AJ52: =IF(B52="","",SUM(E52:AI52)) | AK52: =IF(B52="","",AJ52/GIO_CONG)
C53: =IF(B53="","",IFERROR(INDEX(NV_TEN,MATCH(B53,NV_MA,0)),"MÃ KHÔNG CÓ")) | D53: =IF(B53="","",IFERROR(INDEX(NV_HINHTHUC,MATCH(B53,NV_MA,0)),"")) | AJ53: =IF(B53="","",SUM(E53:AI53)) | AK53: =IF(B53="","",AJ53/GIO_CONG)
C54: =IF(B54="","",IFERROR(INDEX(NV_TEN,MATCH(B54,NV_MA,0)),"MÃ KHÔNG CÓ")) | D54: =IF(B54="","",IFERROR(INDEX(NV_HINHTHUC,MATCH(B54,NV_MA,0)),"")) | AJ54: =IF(B54="","",SUM(E54:AI54)) | AK54: =IF(B54="","",AJ54/GIO_CONG)
C55: =IF(B55="","",IFERROR(INDEX(NV_TEN,MATCH(B55,NV_MA,0)),"MÃ KHÔNG CÓ")) | D55: =IF(B55="","",IFERROR(INDEX(NV_HINHTHUC,MATCH(B55,NV_MA,0)),"")) | AJ55: =IF(B55="","",SUM(E55:AI55)) | AK55: =IF(B55="","",AJ55/GIO_CONG)
C56: =IF(B56="","",IFERROR(INDEX(NV_TEN,MATCH(B56,NV_MA,0)),"MÃ KHÔNG CÓ")) | D56: =IF(B56="","",IFERROR(INDEX(NV_HINHTHUC,MATCH(B56,NV_MA,0)),"")) | AJ56: =IF(B56="","",SUM(E56:AI56)) | AK56: =IF(B56="","",AJ56/GIO_CONG)
C57: =IF(B57="","",IFERROR(INDEX(NV_TEN,MATCH(B57,NV_MA,0)),"MÃ KHÔNG CÓ")) | D57: =IF(B57="","",IFERROR(INDEX(NV_HINHTHUC,MATCH(B57,NV_MA,0)),"")) | AJ57: =IF(B57="","",SUM(E57:AI57)) | AK57: =IF(B57="","",AJ57/GIO_CONG)
C58: =IF(B58="","",IFERROR(INDEX(NV_TEN,MATCH(B58,NV_MA,0)),"MÃ KHÔNG CÓ")) | D58: =IF(B58="","",IFERROR(INDEX(NV_HINHTHUC,MATCH(B58,NV_MA,0)),"")) | AJ58: =IF(B58="","",SUM(E58:AI58)) | AK58: =IF(B58="","",AJ58/GIO_CONG)
C59: =IF(B59="","",IFERROR(INDEX(NV_TEN,MATCH(B59,NV_MA,0)),"MÃ KHÔNG CÓ")) | D59: =IF(B59="","",IFERROR(INDEX(NV_HINHTHUC,MATCH(B59,NV_MA,0)),"")) | AJ59: =IF(B59="","",SUM(E59:AI59)) | AK59: =IF(B59="","",AJ59/GIO_CONG)
C60: =IF(B60="","",IFERROR(INDEX(NV_TEN,MATCH(B60,NV_MA,0)),"MÃ KHÔNG CÓ")) | D60: =IF(B60="","",IFERROR(INDEX(NV_HINHTHUC,MATCH(B60,NV_MA,0)),"")) | AJ60: =IF(B60="","",SUM(E60:AI60)) | AK60: =IF(B60="","",AJ60/GIO_CONG)
C61: =IF(B61="","",IFERROR(INDEX(NV_TEN,MATCH(B61,NV_MA,0)),"MÃ KHÔNG CÓ")) | D61: =IF(B61="","",IFERROR(INDEX(NV_HINHTHUC,MATCH(B61,NV_MA,0)),"")) | AJ61: =IF(B61="","",SUM(E61:AI61)) | AK61: =IF(B61="","",AJ61/GIO_CONG)
... C100: =IF(B100="","",IFERROR(INDEX(NV_TEN,MATCH(B100,NV_MA,0)),"MÃ KHÔNG CÓ")) | D100: =IF(B100="","",IFERROR(INDEX(NV_HINHTHUC,MATCH(B100,NV_MA,0)),"")) | AJ100: =IF(B100="","",SUM(E100:AI100)) | AK100: =IF(B100="","",AJ100/GIO_CONG)
C102: TỔNG | AJ102: =SUM(AJ6:AJ100) -> 455 | AK102: =SUM(AK6:AK100) -> 56.875

Sheet LUONG_KHOAN
A1: BẢNG TÍNH LƯƠNG KHOÁN SẢN XUẤT
A2: Toàn bộ là công thức. Cột Q, R, S (nền xanh) là số đưa sang Bảng lương. Cột tham chiếu sheet cũ ghi ở dòng 5.
A4: STT | B4: Mã NV | C4: Họ và tên | D4: Hình thức | E4: Hệ số | F4: Đơn giá khoán (đ/tấn) | G4: Tổng giờ công | H4: Ngày công | I4: Tấn quy đổi/người | J4: Lương khoán SP | K4: Lương hàng hanging | L4: CV khác chia chung | M4: CV khác đích danh | N4: Lương hàng chèn | O4: Phân bổ trừ lương công nhật | P4: Lương công nhật | Q4: TỔNG LƯƠNG KHOÁN (→ Bảng lương) | R4: TIỀN ĂN SAU KHOÁN (→ Bảng lương) | S4: TỔNG CỘNG | T4: Ghi chú
B5: Cũ: B | C5: Cũ: C | E5: Cũ: AL | F5: Cũ: AM | G5: Cũ: AN | H5: Cũ: AT | I5: Cũ: AO | J5: Cũ: AP (phần 1) | K5: Cũ: AP (phần 2) | L5: Cũ: AQ | M5: Cũ: AQ (+100k/200k) | N5: Cũ: AR | O5: Cũ: AS (−AL14/W3×giờ) | P5: Cũ: AL bảng công nhật | Q5: Cũ: AS | R5: Cũ: AU | S5: Cũ: X Bảng lương
A6: =IF(B6="","",1) -> 1 | B6: =IF(BCC_KHOAN!B6="","",BCC_KHOAN!B6) -> 046085007061 | C6: =IF(B6="","",IFERROR(INDEX(NV_TEN,MATCH(B6,NV_MA,0)),"MÃ KHÔNG CÓ")) -> Lê Vang | D6: =IF(B6="","",IFERROR(INDEX(NV_HINHTHUC,MATCH(B6,NV_MA,0)),"")) -> Khoán | E6: =IF(D6="Khoán",IFERROR(INDEX(NV_HESO,MATCH(B6,NV_MA,0)),0),"") -> 1.5 | F6: =IF(D6="Khoán",IFERROR(INDEX(HS_SX!$B$5:$B$30,MATCH(E6,HS_SX!$A$5:$A$30,0)),0),"") -> 9600 | G6: =IF(B6="","",IFERROR(INDEX(BCC_GIO,MATCH(B6,BCC_MA,0)),0)) -> 0 | H6: =IF(B6="","",G6/GIO_CONG) -> 0 | I6: =IF(D6="Khoán",IF(GIO_TB>0,G6/GIO_TB*KL_CHEBIEN,0),0) -> 0 | J6: =IF(D6="Khoán",F6*I6,0) -> 0 | K6: =IF(D6="Khoán",IF(TONG_GIO_KHOAN>0,QUY_HANGING/TONG_GIO_KHOAN*G6,0),0) -> 0 | L6: =IF(D6="Khoán",IF(TONG_GIO_KHOAN>0,QUY_KHAC/TONG_GIO_KHOAN*G6,0),0) -> 0 | M6: =IF(B6="",0,SUMIFS(KHOAN_KHAC!$F$5:$F$39,KHOAN_KHAC!$G$5:$G$39,B6)) -> 100000 | N6: =IF(D6="Khoán",IF(TONG_GIO_KHOAN>0,QUY_CHEN/TONG_GIO_KHOAN*G6,0),0) -> 0 | O6: =IF(D6="Khoán",IF(TONG_GIO_KHOAN>0,-TONG_CONGNHAT/TONG_GIO_KHOAN*G6,0),0) -> 0 | P6: =IF(D6="Công nhật",H6*IFERROR(IF(INDEX(NV_DGCN,MATCH(B6,NV_MA,0))="",DG_CONGNHAT,INDEX(NV_DGCN,MATCH(B6,NV_MA,0))),DG_CONGNHAT),0) -> 0 | Q6: =IF(B6="","",IF(D6="Khoán",ROUNDDOWN(J6+K6+L6+M6+N6+O6,-3),P6+M6)) -> 100000 | R6: =IF(B6="","",ROUNDDOWN(TIENAN_CONG*H6,-3)) -> 0 | S6: =IF(B6="","",Q6+R6) -> 100000
A7: =IF(B7="","",2) -> 2 | B7: =IF(BCC_KHOAN!B7="","",BCC_KHOAN!B7) -> 046077003925 | C7: =IF(B7="","",IFERROR(INDEX(NV_TEN,MATCH(B7,NV_MA,0)),"MÃ KHÔNG CÓ")) -> Trần Đình Mạnh | D7: =IF(B7="","",IFERROR(INDEX(NV_HINHTHUC,MATCH(B7,NV_MA,0)),"")) -> Khoán | E7: =IF(D7="Khoán",IFERROR(INDEX(NV_HESO,MATCH(B7,NV_MA,0)),0),"") -> 1.35 | F7: =IF(D7="Khoán",IFERROR(INDEX(HS_SX!$B$5:$B$30,MATCH(E7,HS_SX!$A$5:$A$30,0)),0),"") -> 8600 | G7: =IF(B7="","",IFERROR(INDEX(BCC_GIO,MATCH(B7,BCC_MA,0)),0)) -> 0 | H7: =IF(B7="","",G7/GIO_CONG) -> 0 | I7: =IF(D7="Khoán",IF(GIO_TB>0,G7/GIO_TB*KL_CHEBIEN,0),0) -> 0 | J7: =IF(D7="Khoán",F7*I7,0) -> 0 | K7: =IF(D7="Khoán",IF(TONG_GIO_KHOAN>0,QUY_HANGING/TONG_GIO_KHOAN*G7,0),0) -> 0 | L7: =IF(D7="Khoán",IF(TONG_GIO_KHOAN>0,QUY_KHAC/TONG_GIO_KHOAN*G7,0),0) -> 0 | M7: =IF(B7="",0,SUMIFS(KHOAN_KHAC!$F$5:$F$39,KHOAN_KHAC!$G$5:$G$39,B7)) -> 0 | N7: =IF(D7="Khoán",IF(TONG_GIO_KHOAN>0,QUY_CHEN/TONG_GIO_KHOAN*G7,0),0) -> 0 | O7: =IF(D7="Khoán",IF(TONG_GIO_KHOAN>0,-TONG_CONGNHAT/TONG_GIO_KHOAN*G7,0),0) -> 0 | P7: =IF(D7="Công nhật",H7*IFERROR(IF(INDEX(NV_DGCN,MATCH(B7,NV_MA,0))="",DG_CONGNHAT,INDEX(NV_DGCN,MATCH(B7,NV_MA,0))),DG_CONGNHAT),0) -> 0 | Q7: =IF(B7="","",IF(D7="Khoán",ROUNDDOWN(J7+K7+L7+M7+N7+O7,-3),P7+M7)) -> 0 | R7: =IF(B7="","",ROUNDDOWN(TIENAN_CONG*H7,-3)) -> 0 | S7: =IF(B7="","",Q7+R7) -> 0
A8: =IF(B8="","",3) -> 3 | B8: =IF(BCC_KHOAN!B8="","",BCC_KHOAN!B8) -> 046177012486 | C8: =IF(B8="","",IFERROR(INDEX(NV_TEN,MATCH(B8,NV_MA,0)),"MÃ KHÔNG CÓ")) -> Lê Thị Bình | D8: =IF(B8="","",IFERROR(INDEX(NV_HINHTHUC,MATCH(B8,NV_MA,0)),"")) -> Khoán | E8: =IF(D8="Khoán",IFERROR(INDEX(NV_HESO,MATCH(B8,NV_MA,0)),0),"") -> 1.1 | F8: =IF(D8="Khoán",IFERROR(INDEX(HS_SX!$B$5:$B$30,MATCH(E8,HS_SX!$A$5:$A$30,0)),0),"") -> 7100 | G8: =IF(B8="","",IFERROR(INDEX(BCC_GIO,MATCH(B8,BCC_MA,0)),0)) -> 0 | H8: =IF(B8="","",G8/GIO_CONG) -> 0 | I8: =IF(D8="Khoán",IF(GIO_TB>0,G8/GIO_TB*KL_CHEBIEN,0),0) -> 0 | J8: =IF(D8="Khoán",F8*I8,0) -> 0 | K8: =IF(D8="Khoán",IF(TONG_GIO_KHOAN>0,QUY_HANGING/TONG_GIO_KHOAN*G8,0),0) -> 0 | L8: =IF(D8="Khoán",IF(TONG_GIO_KHOAN>0,QUY_KHAC/TONG_GIO_KHOAN*G8,0),0) -> 0 | M8: =IF(B8="",0,SUMIFS(KHOAN_KHAC!$F$5:$F$39,KHOAN_KHAC!$G$5:$G$39,B8)) -> 0 | N8: =IF(D8="Khoán",IF(TONG_GIO_KHOAN>0,QUY_CHEN/TONG_GIO_KHOAN*G8,0),0) -> 0 | O8: =IF(D8="Khoán",IF(TONG_GIO_KHOAN>0,-TONG_CONGNHAT/TONG_GIO_KHOAN*G8,0),0) -> 0 | P8: =IF(D8="Công nhật",H8*IFERROR(IF(INDEX(NV_DGCN,MATCH(B8,NV_MA,0))="",DG_CONGNHAT,INDEX(NV_DGCN,MATCH(B8,NV_MA,0))),DG_CONGNHAT),0) -> 0 | Q8: =IF(B8="","",IF(D8="Khoán",ROUNDDOWN(J8+K8+L8+M8+N8+O8,-3),P8+M8)) -> 0 | R8: =IF(B8="","",ROUNDDOWN(TIENAN_CONG*H8,-3)) -> 0 | S8: =IF(B8="","",Q8+R8) -> 0
A9: =IF(B9="","",4) -> 4 | B9: =IF(BCC_KHOAN!B9="","",BCC_KHOAN!B9) -> 046179008435 | C9: =IF(B9="","",IFERROR(INDEX(NV_TEN,MATCH(B9,NV_MA,0)),"MÃ KHÔNG CÓ")) -> Trần Thị Tích | D9: =IF(B9="","",IFERROR(INDEX(NV_HINHTHUC,MATCH(B9,NV_MA,0)),"")) -> Khoán | E9: =IF(D9="Khoán",IFERROR(INDEX(NV_HESO,MATCH(B9,NV_MA,0)),0),"") -> 1.15 | F9: =IF(D9="Khoán",IFERROR(INDEX(HS_SX!$B$5:$B$30,MATCH(E9,HS_SX!$A$5:$A$30,0)),0),"") -> 7400 | G9: =IF(B9="","",IFERROR(INDEX(BCC_GIO,MATCH(B9,BCC_MA,0)),0)) -> 0 | H9: =IF(B9="","",G9/GIO_CONG) -> 0 | I9: =IF(D9="Khoán",IF(GIO_TB>0,G9/GIO_TB*KL_CHEBIEN,0),0) -> 0 | J9: =IF(D9="Khoán",F9*I9,0) -> 0 | K9: =IF(D9="Khoán",IF(TONG_GIO_KHOAN>0,QUY_HANGING/TONG_GIO_KHOAN*G9,0),0) -> 0 | L9: =IF(D9="Khoán",IF(TONG_GIO_KHOAN>0,QUY_KHAC/TONG_GIO_KHOAN*G9,0),0) -> 0 | M9: =IF(B9="",0,SUMIFS(KHOAN_KHAC!$F$5:$F$39,KHOAN_KHAC!$G$5:$G$39,B9)) -> 0 | N9: =IF(D9="Khoán",IF(TONG_GIO_KHOAN>0,QUY_CHEN/TONG_GIO_KHOAN*G9,0),0) -> 0 | O9: =IF(D9="Khoán",IF(TONG_GIO_KHOAN>0,-TONG_CONGNHAT/TONG_GIO_KHOAN*G9,0),0) -> 0 | P9: =IF(D9="Công nhật",H9*IFERROR(IF(INDEX(NV_DGCN,MATCH(B9,NV_MA,0))="",DG_CONGNHAT,INDEX(NV_DGCN,MATCH(B9,NV_MA,0))),DG_CONGNHAT),0) -> 0 | Q9: =IF(B9="","",IF(D9="Khoán",ROUNDDOWN(J9+K9+L9+M9+N9+O9,-3),P9+M9)) -> 0 | R9: =IF(B9="","",ROUNDDOWN(TIENAN_CONG*H9,-3)) -> 0 | S9: =IF(B9="","",Q9+R9) -> 0
A10: =IF(B10="","",5) -> 5 | B10: =IF(BCC_KHOAN!B10="","",BCC_KHOAN!B10) -> 046175005132 | C10: =IF(B10="","",IFERROR(INDEX(NV_TEN,MATCH(B10,NV_MA,0)),"MÃ KHÔNG CÓ")) -> Lê Thị Nga | D10: =IF(B10="","",IFERROR(INDEX(NV_HINHTHUC,MATCH(B10,NV_MA,0)),"")) -> Khoán | E10: =IF(D10="Khoán",IFERROR(INDEX(NV_HESO,MATCH(B10,NV_MA,0)),0),"") -> 1.15 | F10: =IF(D10="Khoán",IFERROR(INDEX(HS_SX!$B$5:$B$30,MATCH(E10,HS_SX!$A$5:$A$30,0)),0),"") -> 7400 | G10: =IF(B10="","",IFERROR(INDEX(BCC_GIO,MATCH(B10,BCC_MA,0)),0)) -> 0 | H10: =IF(B10="","",G10/GIO_CONG) -> 0 | I10: =IF(D10="Khoán",IF(GIO_TB>0,G10/GIO_TB*KL_CHEBIEN,0),0) -> 0 | J10: =IF(D10="Khoán",F10*I10,0) -> 0 | K10: =IF(D10="Khoán",IF(TONG_GIO_KHOAN>0,QUY_HANGING/TONG_GIO_KHOAN*G10,0),0) -> 0 | L10: =IF(D10="Khoán",IF(TONG_GIO_KHOAN>0,QUY_KHAC/TONG_GIO_KHOAN*G10,0),0) -> 0 | M10: =IF(B10="",0,SUMIFS(KHOAN_KHAC!$F$5:$F$39,KHOAN_KHAC!$G$5:$G$39,B10)) -> 0 | N10: =IF(D10="Khoán",IF(TONG_GIO_KHOAN>0,QUY_CHEN/TONG_GIO_KHOAN*G10,0),0) -> 0 | O10: =IF(D10="Khoán",IF(TONG_GIO_KHOAN>0,-TONG_CONGNHAT/TONG_GIO_KHOAN*G10,0),0) -> 0 | P10: =IF(D10="Công nhật",H10*IFERROR(IF(INDEX(NV_DGCN,MATCH(B10,NV_MA,0))="",DG_CONGNHAT,INDEX(NV_DGCN,MATCH(B10,NV_MA,0))),DG_CONGNHAT),0) -> 0 | Q10: =IF(B10="","",IF(D10="Khoán",ROUNDDOWN(J10+K10+L10+M10+N10+O10,-3),P10+M10)) -> 0 | R10: =IF(B10="","",ROUNDDOWN(TIENAN_CONG*H10,-3)) -> 0 | S10: =IF(B10="","",Q10+R10) -> 0
A11: =IF(B11="","",6) -> 6 | B11: =IF(BCC_KHOAN!B11="","",BCC_KHOAN!B11) -> 046090006706 | C11: =IF(B11="","",IFERROR(INDEX(NV_TEN,MATCH(B11,NV_MA,0)),"MÃ KHÔNG CÓ")) -> Phạm Bá Lượng | D11: =IF(B11="","",IFERROR(INDEX(NV_HINHTHUC,MATCH(B11,NV_MA,0)),"")) -> Khoán | E11: =IF(D11="Khoán",IFERROR(INDEX(NV_HESO,MATCH(B11,NV_MA,0)),0),"") -> 1.3 | F11: =IF(D11="Khoán",IFERROR(INDEX(HS_SX!$B$5:$B$30,MATCH(E11,HS_SX!$A$5:$A$30,0)),0),"") -> 8300 | G11: =IF(B11="","",IFERROR(INDEX(BCC_GIO,MATCH(B11,BCC_MA,0)),0)) -> 0 | H11: =IF(B11="","",G11/GIO_CONG) -> 0 | I11: =IF(D11="Khoán",IF(GIO_TB>0,G11/GIO_TB*KL_CHEBIEN,0),0) -> 0 | J11: =IF(D11="Khoán",F11*I11,0) -> 0 | K11: =IF(D11="Khoán",IF(TONG_GIO_KHOAN>0,QUY_HANGING/TONG_GIO_KHOAN*G11,0),0) -> 0 | L11: =IF(D11="Khoán",IF(TONG_GIO_KHOAN>0,QUY_KHAC/TONG_GIO_KHOAN*G11,0),0) -> 0 | M11: =IF(B11="",0,SUMIFS(KHOAN_KHAC!$F$5:$F$39,KHOAN_KHAC!$G$5:$G$39,B11)) -> 100000 | N11: =IF(D11="Khoán",IF(TONG_GIO_KHOAN>0,QUY_CHEN/TONG_GIO_KHOAN*G11,0),0) -> 0 | O11: =IF(D11="Khoán",IF(TONG_GIO_KHOAN>0,-TONG_CONGNHAT/TONG_GIO_KHOAN*G11,0),0) -> 0 | P11: =IF(D11="Công nhật",H11*IFERROR(IF(INDEX(NV_DGCN,MATCH(B11,NV_MA,0))="",DG_CONGNHAT,INDEX(NV_DGCN,MATCH(B11,NV_MA,0))),DG_CONGNHAT),0) -> 0 | Q11: =IF(B11="","",IF(D11="Khoán",ROUNDDOWN(J11+K11+L11+M11+N11+O11,-3),P11+M11)) -> 100000 | R11: =IF(B11="","",ROUNDDOWN(TIENAN_CONG*H11,-3)) -> 0 | S11: =IF(B11="","",Q11+R11) -> 100000
A12: =IF(B12="","",7) -> 7 | B12: =IF(BCC_KHOAN!B12="","",BCC_KHOAN!B12) -> 046178011746 | C12: =IF(B12="","",IFERROR(INDEX(NV_TEN,MATCH(B12,NV_MA,0)),"MÃ KHÔNG CÓ")) -> Văn Thị Vinh | D12: =IF(B12="","",IFERROR(INDEX(NV_HINHTHUC,MATCH(B12,NV_MA,0)),"")) -> Khoán | E12: =IF(D12="Khoán",IFERROR(INDEX(NV_HESO,MATCH(B12,NV_MA,0)),0),"") -> 1.1 | F12: =IF(D12="Khoán",IFERROR(INDEX(HS_SX!$B$5:$B$30,MATCH(E12,HS_SX!$A$5:$A$30,0)),0),"") -> 7100 | G12: =IF(B12="","",IFERROR(INDEX(BCC_GIO,MATCH(B12,BCC_MA,0)),0)) -> 0 | H12: =IF(B12="","",G12/GIO_CONG) -> 0 | I12: =IF(D12="Khoán",IF(GIO_TB>0,G12/GIO_TB*KL_CHEBIEN,0),0) -> 0 | J12: =IF(D12="Khoán",F12*I12,0) -> 0 | K12: =IF(D12="Khoán",IF(TONG_GIO_KHOAN>0,QUY_HANGING/TONG_GIO_KHOAN*G12,0),0) -> 0 | L12: =IF(D12="Khoán",IF(TONG_GIO_KHOAN>0,QUY_KHAC/TONG_GIO_KHOAN*G12,0),0) -> 0 | M12: =IF(B12="",0,SUMIFS(KHOAN_KHAC!$F$5:$F$39,KHOAN_KHAC!$G$5:$G$39,B12)) -> 0 | N12: =IF(D12="Khoán",IF(TONG_GIO_KHOAN>0,QUY_CHEN/TONG_GIO_KHOAN*G12,0),0) -> 0 | O12: =IF(D12="Khoán",IF(TONG_GIO_KHOAN>0,-TONG_CONGNHAT/TONG_GIO_KHOAN*G12,0),0) -> 0 | P12: =IF(D12="Công nhật",H12*IFERROR(IF(INDEX(NV_DGCN,MATCH(B12,NV_MA,0))="",DG_CONGNHAT,INDEX(NV_DGCN,MATCH(B12,NV_MA,0))),DG_CONGNHAT),0) -> 0 | Q12: =IF(B12="","",IF(D12="Khoán",ROUNDDOWN(J12+K12+L12+M12+N12+O12,-3),P12+M12)) -> 0 | R12: =IF(B12="","",ROUNDDOWN(TIENAN_CONG*H12,-3)) -> 0 | S12: =IF(B12="","",Q12+R12) -> 0
A13: =IF(B13="","",8) -> 8 | B13: =IF(BCC_KHOAN!B13="","",BCC_KHOAN!B13) -> 046172008975 | C13: =IF(B13="","",IFERROR(INDEX(NV_TEN,MATCH(B13,NV_MA,0)),"MÃ KHÔNG CÓ")) -> Nguyễn Thị Điệp | D13: =IF(B13="","",IFERROR(INDEX(NV_HINHTHUC,MATCH(B13,NV_MA,0)),"")) -> Khoán | E13: =IF(D13="Khoán",IFERROR(INDEX(NV_HESO,MATCH(B13,NV_MA,0)),0),"") -> 1.1 | F13: =IF(D13="Khoán",IFERROR(INDEX(HS_SX!$B$5:$B$30,MATCH(E13,HS_SX!$A$5:$A$30,0)),0),"") -> 7100 | G13: =IF(B13="","",IFERROR(INDEX(BCC_GIO,MATCH(B13,BCC_MA,0)),0)) -> 0 | H13: =IF(B13="","",G13/GIO_CONG) -> 0 | I13: =IF(D13="Khoán",IF(GIO_TB>0,G13/GIO_TB*KL_CHEBIEN,0),0) -> 0 | J13: =IF(D13="Khoán",F13*I13,0) -> 0 | K13: =IF(D13="Khoán",IF(TONG_GIO_KHOAN>0,QUY_HANGING/TONG_GIO_KHOAN*G13,0),0) -> 0 | L13: =IF(D13="Khoán",IF(TONG_GIO_KHOAN>0,QUY_KHAC/TONG_GIO_KHOAN*G13,0),0) -> 0 | M13: =IF(B13="",0,SUMIFS(KHOAN_KHAC!$F$5:$F$39,KHOAN_KHAC!$G$5:$G$39,B13)) -> 0 | N13: =IF(D13="Khoán",IF(TONG_GIO_KHOAN>0,QUY_CHEN/TONG_GIO_KHOAN*G13,0),0) -> 0 | O13: =IF(D13="Khoán",IF(TONG_GIO_KHOAN>0,-TONG_CONGNHAT/TONG_GIO_KHOAN*G13,0),0) -> 0 | P13: =IF(D13="Công nhật",H13*IFERROR(IF(INDEX(NV_DGCN,MATCH(B13,NV_MA,0))="",DG_CONGNHAT,INDEX(NV_DGCN,MATCH(B13,NV_MA,0))),DG_CONGNHAT),0) -> 0 | Q13: =IF(B13="","",IF(D13="Khoán",ROUNDDOWN(J13+K13+L13+M13+N13+O13,-3),P13+M13)) -> 0 | R13: =IF(B13="","",ROUNDDOWN(TIENAN_CONG*H13,-3)) -> 0 | S13: =IF(B13="","",Q13+R13) -> 0
A14: =IF(B14="","",9) -> 9 | B14: =IF(BCC_KHOAN!B14="","",BCC_KHOAN!B14) -> NV_KIMANH | C14: =IF(B14="","",IFERROR(INDEX(NV_TEN,MATCH(B14,NV_MA,0)),"MÃ KHÔNG CÓ")) -> Lê Thị Kim Anh | D14: =IF(B14="","",IFERROR(INDEX(NV_HINHTHUC,MATCH(B14,NV_MA,0)),"")) -> Khoán | E14: =IF(D14="Khoán",IFERROR(INDEX(NV_HESO,MATCH(B14,NV_MA,0)),0),"") -> 1 | F14: =IF(D14="Khoán",IFERROR(INDEX(HS_SX!$B$5:$B$30,MATCH(E14,HS_SX!$A$5:$A$30,0)),0),"") -> 6400 | G14: =IF(B14="","",IFERROR(INDEX(BCC_GIO,MATCH(B14,BCC_MA,0)),0)) -> 0 | H14: =IF(B14="","",G14/GIO_CONG) -> 0 | I14: =IF(D14="Khoán",IF(GIO_TB>0,G14/GIO_TB*KL_CHEBIEN,0),0) -> 0 | J14: =IF(D14="Khoán",F14*I14,0) -> 0 | K14: =IF(D14="Khoán",IF(TONG_GIO_KHOAN>0,QUY_HANGING/TONG_GIO_KHOAN*G14,0),0) -> 0 | L14: =IF(D14="Khoán",IF(TONG_GIO_KHOAN>0,QUY_KHAC/TONG_GIO_KHOAN*G14,0),0) -> 0 | M14: =IF(B14="",0,SUMIFS(KHOAN_KHAC!$F$5:$F$39,KHOAN_KHAC!$G$5:$G$39,B14)) -> 0 | N14: =IF(D14="Khoán",IF(TONG_GIO_KHOAN>0,QUY_CHEN/TONG_GIO_KHOAN*G14,0),0) -> 0 | O14: =IF(D14="Khoán",IF(TONG_GIO_KHOAN>0,-TONG_CONGNHAT/TONG_GIO_KHOAN*G14,0),0) -> 0 | P14: =IF(D14="Công nhật",H14*IFERROR(IF(INDEX(NV_DGCN,MATCH(B14,NV_MA,0))="",DG_CONGNHAT,INDEX(NV_DGCN,MATCH(B14,NV_MA,0))),DG_CONGNHAT),0) -> 0 | Q14: =IF(B14="","",IF(D14="Khoán",ROUNDDOWN(J14+K14+L14+M14+N14+O14,-3),P14+M14)) -> 0 | R14: =IF(B14="","",ROUNDDOWN(TIENAN_CONG*H14,-3)) -> 0 | S14: =IF(B14="","",Q14+R14) -> 0
A15: =IF(B15="","",10) -> 10 | B15: =IF(BCC_KHOAN!B15="","",BCC_KHOAN!B15) -> 046074011254 | C15: =IF(B15="","",IFERROR(INDEX(NV_TEN,MATCH(B15,NV_MA,0)),"MÃ KHÔNG CÓ")) -> Trần Đức Phúc | D15: =IF(B15="","",IFERROR(INDEX(NV_HINHTHUC,MATCH(B15,NV_MA,0)),"")) -> Khoán | E15: =IF(D15="Khoán",IFERROR(INDEX(NV_HESO,MATCH(B15,NV_MA,0)),0),"") -> 1.1 | F15: =IF(D15="Khoán",IFERROR(INDEX(HS_SX!$B$5:$B$30,MATCH(E15,HS_SX!$A$5:$A$30,0)),0),"") -> 7100 | G15: =IF(B15="","",IFERROR(INDEX(BCC_GIO,MATCH(B15,BCC_MA,0)),0)) -> 0 | H15: =IF(B15="","",G15/GIO_CONG) -> 0 | I15: =IF(D15="Khoán",IF(GIO_TB>0,G15/GIO_TB*KL_CHEBIEN,0),0) -> 0 | J15: =IF(D15="Khoán",F15*I15,0) -> 0 | K15: =IF(D15="Khoán",IF(TONG_GIO_KHOAN>0,QUY_HANGING/TONG_GIO_KHOAN*G15,0),0) -> 0 | L15: =IF(D15="Khoán",IF(TONG_GIO_KHOAN>0,QUY_KHAC/TONG_GIO_KHOAN*G15,0),0) -> 0 | M15: =IF(B15="",0,SUMIFS(KHOAN_KHAC!$F$5:$F$39,KHOAN_KHAC!$G$5:$G$39,B15)) -> 0 | N15: =IF(D15="Khoán",IF(TONG_GIO_KHOAN>0,QUY_CHEN/TONG_GIO_KHOAN*G15,0),0) -> 0 | O15: =IF(D15="Khoán",IF(TONG_GIO_KHOAN>0,-TONG_CONGNHAT/TONG_GIO_KHOAN*G15,0),0) -> 0 | P15: =IF(D15="Công nhật",H15*IFERROR(IF(INDEX(NV_DGCN,MATCH(B15,NV_MA,0))="",DG_CONGNHAT,INDEX(NV_DGCN,MATCH(B15,NV_MA,0))),DG_CONGNHAT),0) -> 0 | Q15: =IF(B15="","",IF(D15="Khoán",ROUNDDOWN(J15+K15+L15+M15+N15+O15,-3),P15+M15)) -> 0 | R15: =IF(B15="","",ROUNDDOWN(TIENAN_CONG*H15,-3)) -> 0 | S15: =IF(B15="","",Q15+R15) -> 0
A16: =IF(B16="","",11) -> 11 | B16: =IF(BCC_KHOAN!B16="","",BCC_KHOAN!B16) -> 046172013837 | C16: =IF(B16="","",IFERROR(INDEX(NV_TEN,MATCH(B16,NV_MA,0)),"MÃ KHÔNG CÓ")) -> Nguyễn Thị Nhung | D16: =IF(B16="","",IFERROR(INDEX(NV_HINHTHUC,MATCH(B16,NV_MA,0)),"")) -> Khoán | E16: =IF(D16="Khoán",IFERROR(INDEX(NV_HESO,MATCH(B16,NV_MA,0)),0),"") -> 0.9 | F16: =IF(D16="Khoán",IFERROR(INDEX(HS_SX!$B$5:$B$30,MATCH(E16,HS_SX!$A$5:$A$30,0)),0),"") -> 5800 | G16: =IF(B16="","",IFERROR(INDEX(BCC_GIO,MATCH(B16,BCC_MA,0)),0)) -> 0 | H16: =IF(B16="","",G16/GIO_CONG) -> 0 | I16: =IF(D16="Khoán",IF(GIO_TB>0,G16/GIO_TB*KL_CHEBIEN,0),0) -> 0 | J16: =IF(D16="Khoán",F16*I16,0) -> 0 | K16: =IF(D16="Khoán",IF(TONG_GIO_KHOAN>0,QUY_HANGING/TONG_GIO_KHOAN*G16,0),0) -> 0 | L16: =IF(D16="Khoán",IF(TONG_GIO_KHOAN>0,QUY_KHAC/TONG_GIO_KHOAN*G16,0),0) -> 0 | M16: =IF(B16="",0,SUMIFS(KHOAN_KHAC!$F$5:$F$39,KHOAN_KHAC!$G$5:$G$39,B16)) -> 0 | N16: =IF(D16="Khoán",IF(TONG_GIO_KHOAN>0,QUY_CHEN/TONG_GIO_KHOAN*G16,0),0) -> 0 | O16: =IF(D16="Khoán",IF(TONG_GIO_KHOAN>0,-TONG_CONGNHAT/TONG_GIO_KHOAN*G16,0),0) -> 0 | P16: =IF(D16="Công nhật",H16*IFERROR(IF(INDEX(NV_DGCN,MATCH(B16,NV_MA,0))="",DG_CONGNHAT,INDEX(NV_DGCN,MATCH(B16,NV_MA,0))),DG_CONGNHAT),0) -> 0 | Q16: =IF(B16="","",IF(D16="Khoán",ROUNDDOWN(J16+K16+L16+M16+N16+O16,-3),P16+M16)) -> 0 | R16: =IF(B16="","",ROUNDDOWN(TIENAN_CONG*H16,-3)) -> 0 | S16: =IF(B16="","",Q16+R16) -> 0
A17: =IF(B17="","",12) -> 12 | B17: =IF(BCC_KHOAN!B17="","",BCC_KHOAN!B17) -> 046175008129 | C17: =IF(B17="","",IFERROR(INDEX(NV_TEN,MATCH(B17,NV_MA,0)),"MÃ KHÔNG CÓ")) -> Lê Thị Thu Hữu | D17: =IF(B17="","",IFERROR(INDEX(NV_HINHTHUC,MATCH(B17,NV_MA,0)),"")) -> Khoán | E17: =IF(D17="Khoán",IFERROR(INDEX(NV_HESO,MATCH(B17,NV_MA,0)),0),"") -> 1.1 | F17: =IF(D17="Khoán",IFERROR(INDEX(HS_SX!$B$5:$B$30,MATCH(E17,HS_SX!$A$5:$A$30,0)),0),"") -> 7100 | G17: =IF(B17="","",IFERROR(INDEX(BCC_GIO,MATCH(B17,BCC_MA,0)),0)) -> 0 | H17: =IF(B17="","",G17/GIO_CONG) -> 0 | I17: =IF(D17="Khoán",IF(GIO_TB>0,G17/GIO_TB*KL_CHEBIEN,0),0) -> 0 | J17: =IF(D17="Khoán",F17*I17,0) -> 0 | K17: =IF(D17="Khoán",IF(TONG_GIO_KHOAN>0,QUY_HANGING/TONG_GIO_KHOAN*G17,0),0) -> 0 | L17: =IF(D17="Khoán",IF(TONG_GIO_KHOAN>0,QUY_KHAC/TONG_GIO_KHOAN*G17,0),0) -> 0 | M17: =IF(B17="",0,SUMIFS(KHOAN_KHAC!$F$5:$F$39,KHOAN_KHAC!$G$5:$G$39,B17)) -> 0 | N17: =IF(D17="Khoán",IF(TONG_GIO_KHOAN>0,QUY_CHEN/TONG_GIO_KHOAN*G17,0),0) -> 0 | O17: =IF(D17="Khoán",IF(TONG_GIO_KHOAN>0,-TONG_CONGNHAT/TONG_GIO_KHOAN*G17,0),0) -> 0 | P17: =IF(D17="Công nhật",H17*IFERROR(IF(INDEX(NV_DGCN,MATCH(B17,NV_MA,0))="",DG_CONGNHAT,INDEX(NV_DGCN,MATCH(B17,NV_MA,0))),DG_CONGNHAT),0) -> 0 | Q17: =IF(B17="","",IF(D17="Khoán",ROUNDDOWN(J17+K17+L17+M17+N17+O17,-3),P17+M17)) -> 0 | R17: =IF(B17="","",ROUNDDOWN(TIENAN_CONG*H17,-3)) -> 0 | S17: =IF(B17="","",Q17+R17) -> 0
A18: =IF(B18="","",13) -> 13 | B18: =IF(BCC_KHOAN!B18="","",BCC_KHOAN!B18) -> 046206004482 | C18: =IF(B18="","",IFERROR(INDEX(NV_TEN,MATCH(B18,NV_MA,0)),"MÃ KHÔNG CÓ")) -> Trần Đình Lĩnh | D18: =IF(B18="","",IFERROR(INDEX(NV_HINHTHUC,MATCH(B18,NV_MA,0)),"")) -> Khoán | E18: =IF(D18="Khoán",IFERROR(INDEX(NV_HESO,MATCH(B18,NV_MA,0)),0),"") -> 1.05 | F18: =IF(D18="Khoán",IFERROR(INDEX(HS_SX!$B$5:$B$30,MATCH(E18,HS_SX!$A$5:$A$30,0)),0),"") -> 6700 | G18: =IF(B18="","",IFERROR(INDEX(BCC_GIO,MATCH(B18,BCC_MA,0)),0)) -> 0 | H18: =IF(B18="","",G18/GIO_CONG) -> 0 | I18: =IF(D18="Khoán",IF(GIO_TB>0,G18/GIO_TB*KL_CHEBIEN,0),0) -> 0 | J18: =IF(D18="Khoán",F18*I18,0) -> 0 | K18: =IF(D18="Khoán",IF(TONG_GIO_KHOAN>0,QUY_HANGING/TONG_GIO_KHOAN*G18,0),0) -> 0 | L18: =IF(D18="Khoán",IF(TONG_GIO_KHOAN>0,QUY_KHAC/TONG_GIO_KHOAN*G18,0),0) -> 0 | M18: =IF(B18="",0,SUMIFS(KHOAN_KHAC!$F$5:$F$39,KHOAN_KHAC!$G$5:$G$39,B18)) -> 0 | N18: =IF(D18="Khoán",IF(TONG_GIO_KHOAN>0,QUY_CHEN/TONG_GIO_KHOAN*G18,0),0) -> 0 | O18: =IF(D18="Khoán",IF(TONG_GIO_KHOAN>0,-TONG_CONGNHAT/TONG_GIO_KHOAN*G18,0),0) -> 0 | P18: =IF(D18="Công nhật",H18*IFERROR(IF(INDEX(NV_DGCN,MATCH(B18,NV_MA,0))="",DG_CONGNHAT,INDEX(NV_DGCN,MATCH(B18,NV_MA,0))),DG_CONGNHAT),0) -> 0 | Q18: =IF(B18="","",IF(D18="Khoán",ROUNDDOWN(J18+K18+L18+M18+N18+O18,-3),P18+M18)) -> 0 | R18: =IF(B18="","",ROUNDDOWN(TIENAN_CONG*H18,-3)) -> 0 | S18: =IF(B18="","",Q18+R18) -> 0
A19: =IF(B19="","",14) -> 14 | B19: =IF(BCC_KHOAN!B19="","",BCC_KHOAN!B19) -> 046178006439 | C19: =IF(B19="","",IFERROR(INDEX(NV_TEN,MATCH(B19,NV_MA,0)),"MÃ KHÔNG CÓ")) -> Nguyễn Thị Thúy Vân | D19: =IF(B19="","",IFERROR(INDEX(NV_HINHTHUC,MATCH(B19,NV_MA,0)),"")) -> Khoán | E19: =IF(D19="Khoán",IFERROR(INDEX(NV_HESO,MATCH(B19,NV_MA,0)),0),"") -> 1.15 | F19: =IF(D19="Khoán",IFERROR(INDEX(HS_SX!$B$5:$B$30,MATCH(E19,HS_SX!$A$5:$A$30,0)),0),"") -> 7400 | G19: =IF(B19="","",IFERROR(INDEX(BCC_GIO,MATCH(B19,BCC_MA,0)),0)) -> 0 | H19: =IF(B19="","",G19/GIO_CONG) -> 0 | I19: =IF(D19="Khoán",IF(GIO_TB>0,G19/GIO_TB*KL_CHEBIEN,0),0) -> 0 | J19: =IF(D19="Khoán",F19*I19,0) -> 0 | K19: =IF(D19="Khoán",IF(TONG_GIO_KHOAN>0,QUY_HANGING/TONG_GIO_KHOAN*G19,0),0) -> 0 | L19: =IF(D19="Khoán",IF(TONG_GIO_KHOAN>0,QUY_KHAC/TONG_GIO_KHOAN*G19,0),0) -> 0 | M19: =IF(B19="",0,SUMIFS(KHOAN_KHAC!$F$5:$F$39,KHOAN_KHAC!$G$5:$G$39,B19)) -> 0 | N19: =IF(D19="Khoán",IF(TONG_GIO_KHOAN>0,QUY_CHEN/TONG_GIO_KHOAN*G19,0),0) -> 0 | O19: =IF(D19="Khoán",IF(TONG_GIO_KHOAN>0,-TONG_CONGNHAT/TONG_GIO_KHOAN*G19,0),0) -> 0 | P19: =IF(D19="Công nhật",H19*IFERROR(IF(INDEX(NV_DGCN,MATCH(B19,NV_MA,0))="",DG_CONGNHAT,INDEX(NV_DGCN,MATCH(B19,NV_MA,0))),DG_CONGNHAT),0) -> 0 | Q19: =IF(B19="","",IF(D19="Khoán",ROUNDDOWN(J19+K19+L19+M19+N19+O19,-3),P19+M19)) -> 0 | R19: =IF(B19="","",ROUNDDOWN(TIENAN_CONG*H19,-3)) -> 0 | S19: =IF(B19="","",Q19+R19) -> 0
A20: =IF(B20="","",15) -> 15 | B20: =IF(BCC_KHOAN!B20="","",BCC_KHOAN!B20) -> 046172008914 | C20: =IF(B20="","",IFERROR(INDEX(NV_TEN,MATCH(B20,NV_MA,0)),"MÃ KHÔNG CÓ")) -> Trần Thị Thùy | D20: =IF(B20="","",IFERROR(INDEX(NV_HINHTHUC,MATCH(B20,NV_MA,0)),"")) -> Khoán | E20: =IF(D20="Khoán",IFERROR(INDEX(NV_HESO,MATCH(B20,NV_MA,0)),0),"") -> 1.1 | F20: =IF(D20="Khoán",IFERROR(INDEX(HS_SX!$B$5:$B$30,MATCH(E20,HS_SX!$A$5:$A$30,0)),0),"") -> 7100 | G20: =IF(B20="","",IFERROR(INDEX(BCC_GIO,MATCH(B20,BCC_MA,0)),0)) -> 0 | H20: =IF(B20="","",G20/GIO_CONG) -> 0 | I20: =IF(D20="Khoán",IF(GIO_TB>0,G20/GIO_TB*KL_CHEBIEN,0),0) -> 0 | J20: =IF(D20="Khoán",F20*I20,0) -> 0 | K20: =IF(D20="Khoán",IF(TONG_GIO_KHOAN>0,QUY_HANGING/TONG_GIO_KHOAN*G20,0),0) -> 0 | L20: =IF(D20="Khoán",IF(TONG_GIO_KHOAN>0,QUY_KHAC/TONG_GIO_KHOAN*G20,0),0) -> 0 | M20: =IF(B20="",0,SUMIFS(KHOAN_KHAC!$F$5:$F$39,KHOAN_KHAC!$G$5:$G$39,B20)) -> 0 | N20: =IF(D20="Khoán",IF(TONG_GIO_KHOAN>0,QUY_CHEN/TONG_GIO_KHOAN*G20,0),0) -> 0 | O20: =IF(D20="Khoán",IF(TONG_GIO_KHOAN>0,-TONG_CONGNHAT/TONG_GIO_KHOAN*G20,0),0) -> 0 | P20: =IF(D20="Công nhật",H20*IFERROR(IF(INDEX(NV_DGCN,MATCH(B20,NV_MA,0))="",DG_CONGNHAT,INDEX(NV_DGCN,MATCH(B20,NV_MA,0))),DG_CONGNHAT),0) -> 0 | Q20: =IF(B20="","",IF(D20="Khoán",ROUNDDOWN(J20+K20+L20+M20+N20+O20,-3),P20+M20)) -> 0 | R20: =IF(B20="","",ROUNDDOWN(TIENAN_CONG*H20,-3)) -> 0 | S20: =IF(B20="","",Q20+R20) -> 0
A21: =IF(B21="","",16) -> 16 | B21: =IF(BCC_KHOAN!B21="","",BCC_KHOAN!B21) -> 046177011413 | C21: =IF(B21="","",IFERROR(INDEX(NV_TEN,MATCH(B21,NV_MA,0)),"MÃ KHÔNG CÓ")) -> Lê Thị Thơ | D21: =IF(B21="","",IFERROR(INDEX(NV_HINHTHUC,MATCH(B21,NV_MA,0)),"")) -> Khoán | E21: =IF(D21="Khoán",IFERROR(INDEX(NV_HESO,MATCH(B21,NV_MA,0)),0),"") -> 1.1 | F21: =IF(D21="Khoán",IFERROR(INDEX(HS_SX!$B$5:$B$30,MATCH(E21,HS_SX!$A$5:$A$30,0)),0),"") -> 7100 | G21: =IF(B21="","",IFERROR(INDEX(BCC_GIO,MATCH(B21,BCC_MA,0)),0)) -> 0 | H21: =IF(B21="","",G21/GIO_CONG) -> 0 | I21: =IF(D21="Khoán",IF(GIO_TB>0,G21/GIO_TB*KL_CHEBIEN,0),0) -> 0 | J21: =IF(D21="Khoán",F21*I21,0) -> 0 | K21: =IF(D21="Khoán",IF(TONG_GIO_KHOAN>0,QUY_HANGING/TONG_GIO_KHOAN*G21,0),0) -> 0 | L21: =IF(D21="Khoán",IF(TONG_GIO_KHOAN>0,QUY_KHAC/TONG_GIO_KHOAN*G21,0),0) -> 0 | M21: =IF(B21="",0,SUMIFS(KHOAN_KHAC!$F$5:$F$39,KHOAN_KHAC!$G$5:$G$39,B21)) -> 0 | N21: =IF(D21="Khoán",IF(TONG_GIO_KHOAN>0,QUY_CHEN/TONG_GIO_KHOAN*G21,0),0) -> 0 | O21: =IF(D21="Khoán",IF(TONG_GIO_KHOAN>0,-TONG_CONGNHAT/TONG_GIO_KHOAN*G21,0),0) -> 0 | P21: =IF(D21="Công nhật",H21*IFERROR(IF(INDEX(NV_DGCN,MATCH(B21,NV_MA,0))="",DG_CONGNHAT,INDEX(NV_DGCN,MATCH(B21,NV_MA,0))),DG_CONGNHAT),0) -> 0 | Q21: =IF(B21="","",IF(D21="Khoán",ROUNDDOWN(J21+K21+L21+M21+N21+O21,-3),P21+M21)) -> 0 | R21: =IF(B21="","",ROUNDDOWN(TIENAN_CONG*H21,-3)) -> 0 | S21: =IF(B21="","",Q21+R21) -> 0
A22: =IF(B22="","",17) -> 17 | B22: =IF(BCC_KHOAN!B22="","",BCC_KHOAN!B22) -> 046176012012 | C22: =IF(B22="","",IFERROR(INDEX(NV_TEN,MATCH(B22,NV_MA,0)),"MÃ KHÔNG CÓ")) -> Lê Thị Hồng Lan | D22: =IF(B22="","",IFERROR(INDEX(NV_HINHTHUC,MATCH(B22,NV_MA,0)),"")) -> Khoán | E22: =IF(D22="Khoán",IFERROR(INDEX(NV_HESO,MATCH(B22,NV_MA,0)),0),"") -> 1 | F22: =IF(D22="Khoán",IFERROR(INDEX(HS_SX!$B$5:$B$30,MATCH(E22,HS_SX!$A$5:$A$30,0)),0),"") -> 6400 | G22: =IF(B22="","",IFERROR(INDEX(BCC_GIO,MATCH(B22,BCC_MA,0)),0)) -> 0 | H22: =IF(B22="","",G22/GIO_CONG) -> 0 | I22: =IF(D22="Khoán",IF(GIO_TB>0,G22/GIO_TB*KL_CHEBIEN,0),0) -> 0 | J22: =IF(D22="Khoán",F22*I22,0) -> 0 | K22: =IF(D22="Khoán",IF(TONG_GIO_KHOAN>0,QUY_HANGING/TONG_GIO_KHOAN*G22,0),0) -> 0 | L22: =IF(D22="Khoán",IF(TONG_GIO_KHOAN>0,QUY_KHAC/TONG_GIO_KHOAN*G22,0),0) -> 0 | M22: =IF(B22="",0,SUMIFS(KHOAN_KHAC!$F$5:$F$39,KHOAN_KHAC!$G$5:$G$39,B22)) -> 0 | N22: =IF(D22="Khoán",IF(TONG_GIO_KHOAN>0,QUY_CHEN/TONG_GIO_KHOAN*G22,0),0) -> 0 | O22: =IF(D22="Khoán",IF(TONG_GIO_KHOAN>0,-TONG_CONGNHAT/TONG_GIO_KHOAN*G22,0),0) -> 0 | P22: =IF(D22="Công nhật",H22*IFERROR(IF(INDEX(NV_DGCN,MATCH(B22,NV_MA,0))="",DG_CONGNHAT,INDEX(NV_DGCN,MATCH(B22,NV_MA,0))),DG_CONGNHAT),0) -> 0 | Q22: =IF(B22="","",IF(D22="Khoán",ROUNDDOWN(J22+K22+L22+M22+N22+O22,-3),P22+M22)) -> 0 | R22: =IF(B22="","",ROUNDDOWN(TIENAN_CONG*H22,-3)) -> 0 | S22: =IF(B22="","",Q22+R22) -> 0
A23: =IF(B23="","",18) -> 18 | B23: =IF(BCC_KHOAN!B23="","",BCC_KHOAN!B23) -> 046091004633 | C23: =IF(B23="","",IFERROR(INDEX(NV_TEN,MATCH(B23,NV_MA,0)),"MÃ KHÔNG CÓ")) -> Nguyễn Quang Thọ | D23: =IF(B23="","",IFERROR(INDEX(NV_HINHTHUC,MATCH(B23,NV_MA,0)),"")) -> Khoán | E23: =IF(D23="Khoán",IFERROR(INDEX(NV_HESO,MATCH(B23,NV_MA,0)),0),"") -> 0.9 | F23: =IF(D23="Khoán",IFERROR(INDEX(HS_SX!$B$5:$B$30,MATCH(E23,HS_SX!$A$5:$A$30,0)),0),"") -> 5800 | G23: =IF(B23="","",IFERROR(INDEX(BCC_GIO,MATCH(B23,BCC_MA,0)),0)) -> 0 | H23: =IF(B23="","",G23/GIO_CONG) -> 0 | I23: =IF(D23="Khoán",IF(GIO_TB>0,G23/GIO_TB*KL_CHEBIEN,0),0) -> 0 | J23: =IF(D23="Khoán",F23*I23,0) -> 0 | K23: =IF(D23="Khoán",IF(TONG_GIO_KHOAN>0,QUY_HANGING/TONG_GIO_KHOAN*G23,0),0) -> 0 | L23: =IF(D23="Khoán",IF(TONG_GIO_KHOAN>0,QUY_KHAC/TONG_GIO_KHOAN*G23,0),0) -> 0 | M23: =IF(B23="",0,SUMIFS(KHOAN_KHAC!$F$5:$F$39,KHOAN_KHAC!$G$5:$G$39,B23)) -> 0 | N23: =IF(D23="Khoán",IF(TONG_GIO_KHOAN>0,QUY_CHEN/TONG_GIO_KHOAN*G23,0),0) -> 0 | O23: =IF(D23="Khoán",IF(TONG_GIO_KHOAN>0,-TONG_CONGNHAT/TONG_GIO_KHOAN*G23,0),0) -> 0 | P23: =IF(D23="Công nhật",H23*IFERROR(IF(INDEX(NV_DGCN,MATCH(B23,NV_MA,0))="",DG_CONGNHAT,INDEX(NV_DGCN,MATCH(B23,NV_MA,0))),DG_CONGNHAT),0) -> 0 | Q23: =IF(B23="","",IF(D23="Khoán",ROUNDDOWN(J23+K23+L23+M23+N23+O23,-3),P23+M23)) -> 0 | R23: =IF(B23="","",ROUNDDOWN(TIENAN_CONG*H23,-3)) -> 0 | S23: =IF(B23="","",Q23+R23) -> 0
A24: =IF(B24="","",19) -> 19 | B24: =IF(BCC_KHOAN!B24="","",BCC_KHOAN!B24) -> 046074013724 | C24: =IF(B24="","",IFERROR(INDEX(NV_TEN,MATCH(B24,NV_MA,0)),"MÃ KHÔNG CÓ")) -> Nguyễn Ngọc Phương | D24: =IF(B24="","",IFERROR(INDEX(NV_HINHTHUC,MATCH(B24,NV_MA,0)),"")) -> Khoán | E24: =IF(D24="Khoán",IFERROR(INDEX(NV_HESO,MATCH(B24,NV_MA,0)),0),"") -> 1.3 | F24: =IF(D24="Khoán",IFERROR(INDEX(HS_SX!$B$5:$B$30,MATCH(E24,HS_SX!$A$5:$A$30,0)),0),"") -> 8300 | G24: =IF(B24="","",IFERROR(INDEX(BCC_GIO,MATCH(B24,BCC_MA,0)),0)) -> 132 | H24: =IF(B24="","",G24/GIO_CONG) -> 16.5 | I24: =IF(D24="Khoán",IF(GIO_TB>0,G24/GIO_TB*KL_CHEBIEN,0),0) -> 13128.801 | J24: =IF(D24="Khoán",F24*I24,0) -> 1.0896905e+08 | K24: =IF(D24="Khoán",IF(TONG_GIO_KHOAN>0,QUY_HANGING/TONG_GIO_KHOAN*G24,0),0) -> 0 | L24: =IF(D24="Khoán",IF(TONG_GIO_KHOAN>0,QUY_KHAC/TONG_GIO_KHOAN*G24,0),0) -> -6512967 | M24: =IF(B24="",0,SUMIFS(KHOAN_KHAC!$F$5:$F$39,KHOAN_KHAC!$G$5:$G$39,B24)) -> 0 | N24: =IF(D24="Khoán",IF(TONG_GIO_KHOAN>0,QUY_CHEN/TONG_GIO_KHOAN*G24,0),0) -> 4279643.1 | O24: =IF(D24="Khoán",IF(TONG_GIO_KHOAN>0,-TONG_CONGNHAT/TONG_GIO_KHOAN*G24,0),0) -> 0 | P24: =IF(D24="Công nhật",H24*IFERROR(IF(INDEX(NV_DGCN,MATCH(B24,NV_MA,0))="",DG_CONGNHAT,INDEX(NV_DGCN,MATCH(B24,NV_MA,0))),DG_CONGNHAT),0) -> 0 | Q24: =IF(B24="","",IF(D24="Khoán",ROUNDDOWN(J24+K24+L24+M24+N24+O24,-3),P24+M24)) -> 106735000 | R24: =IF(B24="","",ROUNDDOWN(TIENAN_CONG*H24,-3)) -> 6408000 | S24: =IF(B24="","",Q24+R24) -> 113143000
A25: =IF(B25="","",20) -> 20 | B25: =IF(BCC_KHOAN!B25="","",BCC_KHOAN!B25) -> 046099007864 | C25: =IF(B25="","",IFERROR(INDEX(NV_TEN,MATCH(B25,NV_MA,0)),"MÃ KHÔNG CÓ")) -> Lê Lộc | D25: =IF(B25="","",IFERROR(INDEX(NV_HINHTHUC,MATCH(B25,NV_MA,0)),"")) -> Khoán | E25: =IF(D25="Khoán",IFERROR(INDEX(NV_HESO,MATCH(B25,NV_MA,0)),0),"") -> 1.15 | F25: =IF(D25="Khoán",IFERROR(INDEX(HS_SX!$B$5:$B$30,MATCH(E25,HS_SX!$A$5:$A$30,0)),0),"") -> 7400 | G25: =IF(B25="","",IFERROR(INDEX(BCC_GIO,MATCH(B25,BCC_MA,0)),0)) -> 0 | H25: =IF(B25="","",G25/GIO_CONG) -> 0 | I25: =IF(D25="Khoán",IF(GIO_TB>0,G25/GIO_TB*KL_CHEBIEN,0),0) -> 0 | J25: =IF(D25="Khoán",F25*I25,0) -> 0 | K25: =IF(D25="Khoán",IF(TONG_GIO_KHOAN>0,QUY_HANGING/TONG_GIO_KHOAN*G25,0),0) -> 0 | L25: =IF(D25="Khoán",IF(TONG_GIO_KHOAN>0,QUY_KHAC/TONG_GIO_KHOAN*G25,0),0) -> 0 | M25: =IF(B25="",0,SUMIFS(KHOAN_KHAC!$F$5:$F$39,KHOAN_KHAC!$G$5:$G$39,B25)) -> 0 | N25: =IF(D25="Khoán",IF(TONG_GIO_KHOAN>0,QUY_CHEN/TONG_GIO_KHOAN*G25,0),0) -> 0 | O25: =IF(D25="Khoán",IF(TONG_GIO_KHOAN>0,-TONG_CONGNHAT/TONG_GIO_KHOAN*G25,0),0) -> 0 | P25: =IF(D25="Công nhật",H25*IFERROR(IF(INDEX(NV_DGCN,MATCH(B25,NV_MA,0))="",DG_CONGNHAT,INDEX(NV_DGCN,MATCH(B25,NV_MA,0))),DG_CONGNHAT),0) -> 0 | Q25: =IF(B25="","",IF(D25="Khoán",ROUNDDOWN(J25+K25+L25+M25+N25+O25,-3),P25+M25)) -> 0 | R25: =IF(B25="","",ROUNDDOWN(TIENAN_CONG*H25,-3)) -> 0 | S25: =IF(B25="","",Q25+R25) -> 0
A26: =IF(B26="","",21) -> 21 | B26: =IF(BCC_KHOAN!B26="","",BCC_KHOAN!B26) -> 002191001272 | C26: =IF(B26="","",IFERROR(INDEX(NV_TEN,MATCH(B26,NV_MA,0)),"MÃ KHÔNG CÓ")) -> Thèn Thị Giang | D26: =IF(B26="","",IFERROR(INDEX(NV_HINHTHUC,MATCH(B26,NV_MA,0)),"")) -> Khoán | E26: =IF(D26="Khoán",IFERROR(INDEX(NV_HESO,MATCH(B26,NV_MA,0)),0),"") -> 1.15 | F26: =IF(D26="Khoán",IFERROR(INDEX(HS_SX!$B$5:$B$30,MATCH(E26,HS_SX!$A$5:$A$30,0)),0),"") -> 7400 | G26: =IF(B26="","",IFERROR(INDEX(BCC_GIO,MATCH(B26,BCC_MA,0)),0)) -> 0 | H26: =IF(B26="","",G26/GIO_CONG) -> 0 | I26: =IF(D26="Khoán",IF(GIO_TB>0,G26/GIO_TB*KL_CHEBIEN,0),0) -> 0 | J26: =IF(D26="Khoán",F26*I26,0) -> 0 | K26: =IF(D26="Khoán",IF(TONG_GIO_KHOAN>0,QUY_HANGING/TONG_GIO_KHOAN*G26,0),0) -> 0 | L26: =IF(D26="Khoán",IF(TONG_GIO_KHOAN>0,QUY_KHAC/TONG_GIO_KHOAN*G26,0),0) -> 0 | M26: =IF(B26="",0,SUMIFS(KHOAN_KHAC!$F$5:$F$39,KHOAN_KHAC!$G$5:$G$39,B26)) -> 0 | N26: =IF(D26="Khoán",IF(TONG_GIO_KHOAN>0,QUY_CHEN/TONG_GIO_KHOAN*G26,0),0) -> 0 | O26: =IF(D26="Khoán",IF(TONG_GIO_KHOAN>0,-TONG_CONGNHAT/TONG_GIO_KHOAN*G26,0),0) -> 0 | P26: =IF(D26="Công nhật",H26*IFERROR(IF(INDEX(NV_DGCN,MATCH(B26,NV_MA,0))="",DG_CONGNHAT,INDEX(NV_DGCN,MATCH(B26,NV_MA,0))),DG_CONGNHAT),0) -> 0 | Q26: =IF(B26="","",IF(D26="Khoán",ROUNDDOWN(J26+K26+L26+M26+N26+O26,-3),P26+M26)) -> 0 | R26: =IF(B26="","",ROUNDDOWN(TIENAN_CONG*H26,-3)) -> 0 | S26: =IF(B26="","",Q26+R26) -> 0
A27: =IF(B27="","",22) -> 22 | B27: =IF(BCC_KHOAN!B27="","",BCC_KHOAN!B27) -> 046087002473 | C27: =IF(B27="","",IFERROR(INDEX(NV_TEN,MATCH(B27,NV_MA,0)),"MÃ KHÔNG CÓ")) -> Nguyễn Tình | D27: =IF(B27="","",IFERROR(INDEX(NV_HINHTHUC,MATCH(B27,NV_MA,0)),"")) -> Khoán | E27: =IF(D27="Khoán",IFERROR(INDEX(NV_HESO,MATCH(B27,NV_MA,0)),0),"") -> 0.9 | F27: =IF(D27="Khoán",IFERROR(INDEX(HS_SX!$B$5:$B$30,MATCH(E27,HS_SX!$A$5:$A$30,0)),0),"") -> 5800 | G27: =IF(B27="","",IFERROR(INDEX(BCC_GIO,MATCH(B27,BCC_MA,0)),0)) -> 0 | H27: =IF(B27="","",G27/GIO_CONG) -> 0 | I27: =IF(D27="Khoán",IF(GIO_TB>0,G27/GIO_TB*KL_CHEBIEN,0),0) -> 0 | J27: =IF(D27="Khoán",F27*I27,0) -> 0 | K27: =IF(D27="Khoán",IF(TONG_GIO_KHOAN>0,QUY_HANGING/TONG_GIO_KHOAN*G27,0),0) -> 0 | L27: =IF(D27="Khoán",IF(TONG_GIO_KHOAN>0,QUY_KHAC/TONG_GIO_KHOAN*G27,0),0) -> 0 | M27: =IF(B27="",0,SUMIFS(KHOAN_KHAC!$F$5:$F$39,KHOAN_KHAC!$G$5:$G$39,B27)) -> 0 | N27: =IF(D27="Khoán",IF(TONG_GIO_KHOAN>0,QUY_CHEN/TONG_GIO_KHOAN*G27,0),0) -> 0 | O27: =IF(D27="Khoán",IF(TONG_GIO_KHOAN>0,-TONG_CONGNHAT/TONG_GIO_KHOAN*G27,0),0) -> 0 | P27: =IF(D27="Công nhật",H27*IFERROR(IF(INDEX(NV_DGCN,MATCH(B27,NV_MA,0))="",DG_CONGNHAT,INDEX(NV_DGCN,MATCH(B27,NV_MA,0))),DG_CONGNHAT),0) -> 0 | Q27: =IF(B27="","",IF(D27="Khoán",ROUNDDOWN(J27+K27+L27+M27+N27+O27,-3),P27+M27)) -> 0 | R27: =IF(B27="","",ROUNDDOWN(TIENAN_CONG*H27,-3)) -> 0 | S27: =IF(B27="","",Q27+R27) -> 0
A28: =IF(B28="","",23) -> 23 | B28: =IF(BCC_KHOAN!B28="","",BCC_KHOAN!B28) -> 046178010147 | C28: =IF(B28="","",IFERROR(INDEX(NV_TEN,MATCH(B28,NV_MA,0)),"MÃ KHÔNG CÓ")) -> Đặng Thị Huế | D28: =IF(B28="","",IFERROR(INDEX(NV_HINHTHUC,MATCH(B28,NV_MA,0)),"")) -> Khoán | E28: =IF(D28="Khoán",IFERROR(INDEX(NV_HESO,MATCH(B28,NV_MA,0)),0),"") -> 1.1 | F28: =IF(D28="Khoán",IFERROR(INDEX(HS_SX!$B$5:$B$30,MATCH(E28,HS_SX!$A$5:$A$30,0)),0),"") -> 7100 | G28: =IF(B28="","",IFERROR(INDEX(BCC_GIO,MATCH(B28,BCC_MA,0)),0)) -> 0 | H28: =IF(B28="","",G28/GIO_CONG) -> 0 | I28: =IF(D28="Khoán",IF(GIO_TB>0,G28/GIO_TB*KL_CHEBIEN,0),0) -> 0 | J28: =IF(D28="Khoán",F28*I28,0) -> 0 | K28: =IF(D28="Khoán",IF(TONG_GIO_KHOAN>0,QUY_HANGING/TONG_GIO_KHOAN*G28,0),0) -> 0 | L28: =IF(D28="Khoán",IF(TONG_GIO_KHOAN>0,QUY_KHAC/TONG_GIO_KHOAN*G28,0),0) -> 0 | M28: =IF(B28="",0,SUMIFS(KHOAN_KHAC!$F$5:$F$39,KHOAN_KHAC!$G$5:$G$39,B28)) -> 0 | N28: =IF(D28="Khoán",IF(TONG_GIO_KHOAN>0,QUY_CHEN/TONG_GIO_KHOAN*G28,0),0) -> 0 | O28: =IF(D28="Khoán",IF(TONG_GIO_KHOAN>0,-TONG_CONGNHAT/TONG_GIO_KHOAN*G28,0),0) -> 0 | P28: =IF(D28="Công nhật",H28*IFERROR(IF(INDEX(NV_DGCN,MATCH(B28,NV_MA,0))="",DG_CONGNHAT,INDEX(NV_DGCN,MATCH(B28,NV_MA,0))),DG_CONGNHAT),0) -> 0 | Q28: =IF(B28="","",IF(D28="Khoán",ROUNDDOWN(J28+K28+L28+M28+N28+O28,-3),P28+M28)) -> 0 | R28: =IF(B28="","",ROUNDDOWN(TIENAN_CONG*H28,-3)) -> 0 | S28: =IF(B28="","",Q28+R28) -> 0
A29: =IF(B29="","",24) -> 24 | B29: =IF(BCC_KHOAN!B29="","",BCC_KHOAN!B29) -> 046089009803 | C29: =IF(B29="","",IFERROR(INDEX(NV_TEN,MATCH(B29,NV_MA,0)),"MÃ KHÔNG CÓ")) -> Trần Văn Trình | D29: =IF(B29="","",IFERROR(INDEX(NV_HINHTHUC,MATCH(B29,NV_MA,0)),"")) -> Khoán | E29: =IF(D29="Khoán",IFERROR(INDEX(NV_HESO,MATCH(B29,NV_MA,0)),0),"") -> 0.9 | F29: =IF(D29="Khoán",IFERROR(INDEX(HS_SX!$B$5:$B$30,MATCH(E29,HS_SX!$A$5:$A$30,0)),0),"") -> 5800 | G29: =IF(B29="","",IFERROR(INDEX(BCC_GIO,MATCH(B29,BCC_MA,0)),0)) -> 0 | H29: =IF(B29="","",G29/GIO_CONG) -> 0 | I29: =IF(D29="Khoán",IF(GIO_TB>0,G29/GIO_TB*KL_CHEBIEN,0),0) -> 0 | J29: =IF(D29="Khoán",F29*I29,0) -> 0 | K29: =IF(D29="Khoán",IF(TONG_GIO_KHOAN>0,QUY_HANGING/TONG_GIO_KHOAN*G29,0),0) -> 0 | L29: =IF(D29="Khoán",IF(TONG_GIO_KHOAN>0,QUY_KHAC/TONG_GIO_KHOAN*G29,0),0) -> 0 | M29: =IF(B29="",0,SUMIFS(KHOAN_KHAC!$F$5:$F$39,KHOAN_KHAC!$G$5:$G$39,B29)) -> 0 | N29: =IF(D29="Khoán",IF(TONG_GIO_KHOAN>0,QUY_CHEN/TONG_GIO_KHOAN*G29,0),0) -> 0 | O29: =IF(D29="Khoán",IF(TONG_GIO_KHOAN>0,-TONG_CONGNHAT/TONG_GIO_KHOAN*G29,0),0) -> 0 | P29: =IF(D29="Công nhật",H29*IFERROR(IF(INDEX(NV_DGCN,MATCH(B29,NV_MA,0))="",DG_CONGNHAT,INDEX(NV_DGCN,MATCH(B29,NV_MA,0))),DG_CONGNHAT),0) -> 0 | Q29: =IF(B29="","",IF(D29="Khoán",ROUNDDOWN(J29+K29+L29+M29+N29+O29,-3),P29+M29)) -> 0 | R29: =IF(B29="","",ROUNDDOWN(TIENAN_CONG*H29,-3)) -> 0 | S29: =IF(B29="","",Q29+R29) -> 0
A30: =IF(B30="","",25) -> 25 | B30: =IF(BCC_KHOAN!B30="","",BCC_KHOAN!B30) -> 046084009142 | C30: =IF(B30="","",IFERROR(INDEX(NV_TEN,MATCH(B30,NV_MA,0)),"MÃ KHÔNG CÓ")) -> Trần Văn Hiền | D30: =IF(B30="","",IFERROR(INDEX(NV_HINHTHUC,MATCH(B30,NV_MA,0)),"")) -> Khoán | E30: =IF(D30="Khoán",IFERROR(INDEX(NV_HESO,MATCH(B30,NV_MA,0)),0),"") -> 1.5 | F30: =IF(D30="Khoán",IFERROR(INDEX(HS_SX!$B$5:$B$30,MATCH(E30,HS_SX!$A$5:$A$30,0)),0),"") -> 9600 | G30: =IF(B30="","",IFERROR(INDEX(BCC_GIO,MATCH(B30,BCC_MA,0)),0)) -> 0 | H30: =IF(B30="","",G30/GIO_CONG) -> 0 | I30: =IF(D30="Khoán",IF(GIO_TB>0,G30/GIO_TB*KL_CHEBIEN,0),0) -> 0 | J30: =IF(D30="Khoán",F30*I30,0) -> 0 | K30: =IF(D30="Khoán",IF(TONG_GIO_KHOAN>0,QUY_HANGING/TONG_GIO_KHOAN*G30,0),0) -> 0 | L30: =IF(D30="Khoán",IF(TONG_GIO_KHOAN>0,QUY_KHAC/TONG_GIO_KHOAN*G30,0),0) -> 0 | M30: =IF(B30="",0,SUMIFS(KHOAN_KHAC!$F$5:$F$39,KHOAN_KHAC!$G$5:$G$39,B30)) -> 200000 | N30: =IF(D30="Khoán",IF(TONG_GIO_KHOAN>0,QUY_CHEN/TONG_GIO_KHOAN*G30,0),0) -> 0 | O30: =IF(D30="Khoán",IF(TONG_GIO_KHOAN>0,-TONG_CONGNHAT/TONG_GIO_KHOAN*G30,0),0) -> 0 | P30: =IF(D30="Công nhật",H30*IFERROR(IF(INDEX(NV_DGCN,MATCH(B30,NV_MA,0))="",DG_CONGNHAT,INDEX(NV_DGCN,MATCH(B30,NV_MA,0))),DG_CONGNHAT),0) -> 0 | Q30: =IF(B30="","",IF(D30="Khoán",ROUNDDOWN(J30+K30+L30+M30+N30+O30,-3),P30+M30)) -> 200000 | R30: =IF(B30="","",ROUNDDOWN(TIENAN_CONG*H30,-3)) -> 0 | S30: =IF(B30="","",Q30+R30) -> 200000
A31: =IF(B31="","",26) -> 26 | B31: =IF(BCC_KHOAN!B31="","",BCC_KHOAN!B31) -> 046207415351 | C31: =IF(B31="","",IFERROR(INDEX(NV_TEN,MATCH(B31,NV_MA,0)),"MÃ KHÔNG CÓ")) -> Trần Văn Tâm | D31: =IF(B31="","",IFERROR(INDEX(NV_HINHTHUC,MATCH(B31,NV_MA,0)),"")) -> Khoán | E31: =IF(D31="Khoán",IFERROR(INDEX(NV_HESO,MATCH(B31,NV_MA,0)),0),"") -> 1.15 | F31: =IF(D31="Khoán",IFERROR(INDEX(HS_SX!$B$5:$B$30,MATCH(E31,HS_SX!$A$5:$A$30,0)),0),"") -> 7400 | G31: =IF(B31="","",IFERROR(INDEX(BCC_GIO,MATCH(B31,BCC_MA,0)),0)) -> 123 | H31: =IF(B31="","",G31/GIO_CONG) -> 15.375 | I31: =IF(D31="Khoán",IF(GIO_TB>0,G31/GIO_TB*KL_CHEBIEN,0),0) -> 12233.656 | J31: =IF(D31="Khoán",F31*I31,0) -> 90529052 | K31: =IF(D31="Khoán",IF(TONG_GIO_KHOAN>0,QUY_HANGING/TONG_GIO_KHOAN*G31,0),0) -> 0 | L31: =IF(D31="Khoán",IF(TONG_GIO_KHOAN>0,QUY_KHAC/TONG_GIO_KHOAN*G31,0),0) -> -6068901.1 | M31: =IF(B31="",0,SUMIFS(KHOAN_KHAC!$F$5:$F$39,KHOAN_KHAC!$G$5:$G$39,B31)) -> 0 | N31: =IF(D31="Khoán",IF(TONG_GIO_KHOAN>0,QUY_CHEN/TONG_GIO_KHOAN*G31,0),0) -> 3987849.2 | O31: =IF(D31="Khoán",IF(TONG_GIO_KHOAN>0,-TONG_CONGNHAT/TONG_GIO_KHOAN*G31,0),0) -> 0 | P31: =IF(D31="Công nhật",H31*IFERROR(IF(INDEX(NV_DGCN,MATCH(B31,NV_MA,0))="",DG_CONGNHAT,INDEX(NV_DGCN,MATCH(B31,NV_MA,0))),DG_CONGNHAT),0) -> 0 | Q31: =IF(B31="","",IF(D31="Khoán",ROUNDDOWN(J31+K31+L31+M31+N31+O31,-3),P31+M31)) -> 88448000 | R31: =IF(B31="","",ROUNDDOWN(TIENAN_CONG*H31,-3)) -> 5971000 | S31: =IF(B31="","",Q31+R31) -> 94419000
A32: =IF(B32="","",27) -> 27 | B32: =IF(BCC_KHOAN!B32="","",BCC_KHOAN!B32) -> NV_DINHHAI | C32: =IF(B32="","",IFERROR(INDEX(NV_TEN,MATCH(B32,NV_MA,0)),"MÃ KHÔNG CÓ")) -> Trần Đình Hải | D32: =IF(B32="","",IFERROR(INDEX(NV_HINHTHUC,MATCH(B32,NV_MA,0)),"")) -> Khoán | E32: =IF(D32="Khoán",IFERROR(INDEX(NV_HESO,MATCH(B32,NV_MA,0)),0),"") -> 1.2 | F32: =IF(D32="Khoán",IFERROR(INDEX(HS_SX!$B$5:$B$30,MATCH(E32,HS_SX!$A$5:$A$30,0)),0),"") -> 7700 | G32: =IF(B32="","",IFERROR(INDEX(BCC_GIO,MATCH(B32,BCC_MA,0)),0)) -> 0 | H32: =IF(B32="","",G32/GIO_CONG) -> 0 | I32: =IF(D32="Khoán",IF(GIO_TB>0,G32/GIO_TB*KL_CHEBIEN,0),0) -> 0 | J32: =IF(D32="Khoán",F32*I32,0) -> 0 | K32: =IF(D32="Khoán",IF(TONG_GIO_KHOAN>0,QUY_HANGING/TONG_GIO_KHOAN*G32,0),0) -> 0 | L32: =IF(D32="Khoán",IF(TONG_GIO_KHOAN>0,QUY_KHAC/TONG_GIO_KHOAN*G32,0),0) -> 0 | M32: =IF(B32="",0,SUMIFS(KHOAN_KHAC!$F$5:$F$39,KHOAN_KHAC!$G$5:$G$39,B32)) -> 0 | N32: =IF(D32="Khoán",IF(TONG_GIO_KHOAN>0,QUY_CHEN/TONG_GIO_KHOAN*G32,0),0) -> 0 | O32: =IF(D32="Khoán",IF(TONG_GIO_KHOAN>0,-TONG_CONGNHAT/TONG_GIO_KHOAN*G32,0),0) -> 0 | P32: =IF(D32="Công nhật",H32*IFERROR(IF(INDEX(NV_DGCN,MATCH(B32,NV_MA,0))="",DG_CONGNHAT,INDEX(NV_DGCN,MATCH(B32,NV_MA,0))),DG_CONGNHAT),0) -> 0 | Q32: =IF(B32="","",IF(D32="Khoán",ROUNDDOWN(J32+K32+L32+M32+N32+O32,-3),P32+M32)) -> 0 | R32: =IF(B32="","",ROUNDDOWN(TIENAN_CONG*H32,-3)) -> 0 | S32: =IF(B32="","",Q32+R32) -> 0
A33: =IF(B33="","",28) -> 28 | B33: =IF(BCC_KHOAN!B33="","",BCC_KHOAN!B33) -> 046064009756 | C33: =IF(B33="","",IFERROR(INDEX(NV_TEN,MATCH(B33,NV_MA,0)),"MÃ KHÔNG CÓ")) -> Hoàng Lự | D33: =IF(B33="","",IFERROR(INDEX(NV_HINHTHUC,MATCH(B33,NV_MA,0)),"")) -> Khoán | E33: =IF(D33="Khoán",IFERROR(INDEX(NV_HESO,MATCH(B33,NV_MA,0)),0),"") -> 1.1 | F33: =IF(D33="Khoán",IFERROR(INDEX(HS_SX!$B$5:$B$30,MATCH(E33,HS_SX!$A$5:$A$30,0)),0),"") -> 7100 | G33: =IF(B33="","",IFERROR(INDEX(BCC_GIO,MATCH(B33,BCC_MA,0)),0)) -> 0 | H33: =IF(B33="","",G33/GIO_CONG) -> 0 | I33: =IF(D33="Khoán",IF(GIO_TB>0,G33/GIO_TB*KL_CHEBIEN,0),0) -> 0 | J33: =IF(D33="Khoán",F33*I33,0) -> 0 | K33: =IF(D33="Khoán",IF(TONG_GIO_KHOAN>0,QUY_HANGING/TONG_GIO_KHOAN*G33,0),0) -> 0 | L33: =IF(D33="Khoán",IF(TONG_GIO_KHOAN>0,QUY_KHAC/TONG_GIO_KHOAN*G33,0),0) -> 0 | M33: =IF(B33="",0,SUMIFS(KHOAN_KHAC!$F$5:$F$39,KHOAN_KHAC!$G$5:$G$39,B33)) -> 0 | N33: =IF(D33="Khoán",IF(TONG_GIO_KHOAN>0,QUY_CHEN/TONG_GIO_KHOAN*G33,0),0) -> 0 | O33: =IF(D33="Khoán",IF(TONG_GIO_KHOAN>0,-TONG_CONGNHAT/TONG_GIO_KHOAN*G33,0),0) -> 0 | P33: =IF(D33="Công nhật",H33*IFERROR(IF(INDEX(NV_DGCN,MATCH(B33,NV_MA,0))="",DG_CONGNHAT,INDEX(NV_DGCN,MATCH(B33,NV_MA,0))),DG_CONGNHAT),0) -> 0 | Q33: =IF(B33="","",IF(D33="Khoán",ROUNDDOWN(J33+K33+L33+M33+N33+O33,-3),P33+M33)) -> 0 | R33: =IF(B33="","",ROUNDDOWN(TIENAN_CONG*H33,-3)) -> 0 | S33: =IF(B33="","",Q33+R33) -> 0
A34: =IF(B34="","",29) -> 29 | B34: =IF(BCC_KHOAN!B34="","",BCC_KHOAN!B34) -> 046172013307 | C34: =IF(B34="","",IFERROR(INDEX(NV_TEN,MATCH(B34,NV_MA,0)),"MÃ KHÔNG CÓ")) -> Ngô Thị Thủy | D34: =IF(B34="","",IFERROR(INDEX(NV_HINHTHUC,MATCH(B34,NV_MA,0)),"")) -> Khoán | E34: =IF(D34="Khoán",IFERROR(INDEX(NV_HESO,MATCH(B34,NV_MA,0)),0),"") -> 1.1 | F34: =IF(D34="Khoán",IFERROR(INDEX(HS_SX!$B$5:$B$30,MATCH(E34,HS_SX!$A$5:$A$30,0)),0),"") -> 7100 | G34: =IF(B34="","",IFERROR(INDEX(BCC_GIO,MATCH(B34,BCC_MA,0)),0)) -> 0 | H34: =IF(B34="","",G34/GIO_CONG) -> 0 | I34: =IF(D34="Khoán",IF(GIO_TB>0,G34/GIO_TB*KL_CHEBIEN,0),0) -> 0 | J34: =IF(D34="Khoán",F34*I34,0) -> 0 | K34: =IF(D34="Khoán",IF(TONG_GIO_KHOAN>0,QUY_HANGING/TONG_GIO_KHOAN*G34,0),0) -> 0 | L34: =IF(D34="Khoán",IF(TONG_GIO_KHOAN>0,QUY_KHAC/TONG_GIO_KHOAN*G34,0),0) -> 0 | M34: =IF(B34="",0,SUMIFS(KHOAN_KHAC!$F$5:$F$39,KHOAN_KHAC!$G$5:$G$39,B34)) -> 0 | N34: =IF(D34="Khoán",IF(TONG_GIO_KHOAN>0,QUY_CHEN/TONG_GIO_KHOAN*G34,0),0) -> 0 | O34: =IF(D34="Khoán",IF(TONG_GIO_KHOAN>0,-TONG_CONGNHAT/TONG_GIO_KHOAN*G34,0),0) -> 0 | P34: =IF(D34="Công nhật",H34*IFERROR(IF(INDEX(NV_DGCN,MATCH(B34,NV_MA,0))="",DG_CONGNHAT,INDEX(NV_DGCN,MATCH(B34,NV_MA,0))),DG_CONGNHAT),0) -> 0 | Q34: =IF(B34="","",IF(D34="Khoán",ROUNDDOWN(J34+K34+L34+M34+N34+O34,-3),P34+M34)) -> 0 | R34: =IF(B34="","",ROUNDDOWN(TIENAN_CONG*H34,-3)) -> 0 | S34: =IF(B34="","",Q34+R34) -> 0
A35: =IF(B35="","",30) -> 30 | B35: =IF(BCC_KHOAN!B35="","",BCC_KHOAN!B35) -> 046165007228 | C35: =IF(B35="","",IFERROR(INDEX(NV_TEN,MATCH(B35,NV_MA,0)),"MÃ KHÔNG CÓ")) -> Lê Thị Hương | D35: =IF(B35="","",IFERROR(INDEX(NV_HINHTHUC,MATCH(B35,NV_MA,0)),"")) -> Khoán | E35: =IF(D35="Khoán",IFERROR(INDEX(NV_HESO,MATCH(B35,NV_MA,0)),0),"") -> 1 | F35: =IF(D35="Khoán",IFERROR(INDEX(HS_SX!$B$5:$B$30,MATCH(E35,HS_SX!$A$5:$A$30,0)),0),"") -> 6400 | G35: =IF(B35="","",IFERROR(INDEX(BCC_GIO,MATCH(B35,BCC_MA,0)),0)) -> 0 | H35: =IF(B35="","",G35/GIO_CONG) -> 0 | I35: =IF(D35="Khoán",IF(GIO_TB>0,G35/GIO_TB*KL_CHEBIEN,0),0) -> 0 | J35: =IF(D35="Khoán",F35*I35,0) -> 0 | K35: =IF(D35="Khoán",IF(TONG_GIO_KHOAN>0,QUY_HANGING/TONG_GIO_KHOAN*G35,0),0) -> 0 | L35: =IF(D35="Khoán",IF(TONG_GIO_KHOAN>0,QUY_KHAC/TONG_GIO_KHOAN*G35,0),0) -> 0 | M35: =IF(B35="",0,SUMIFS(KHOAN_KHAC!$F$5:$F$39,KHOAN_KHAC!$G$5:$G$39,B35)) -> 0 | N35: =IF(D35="Khoán",IF(TONG_GIO_KHOAN>0,QUY_CHEN/TONG_GIO_KHOAN*G35,0),0) -> 0 | O35: =IF(D35="Khoán",IF(TONG_GIO_KHOAN>0,-TONG_CONGNHAT/TONG_GIO_KHOAN*G35,0),0) -> 0 | P35: =IF(D35="Công nhật",H35*IFERROR(IF(INDEX(NV_DGCN,MATCH(B35,NV_MA,0))="",DG_CONGNHAT,INDEX(NV_DGCN,MATCH(B35,NV_MA,0))),DG_CONGNHAT),0) -> 0 | Q35: =IF(B35="","",IF(D35="Khoán",ROUNDDOWN(J35+K35+L35+M35+N35+O35,-3),P35+M35)) -> 0 | R35: =IF(B35="","",ROUNDDOWN(TIENAN_CONG*H35,-3)) -> 0 | S35: =IF(B35="","",Q35+R35) -> 0
A36: =IF(B36="","",31) -> 31 | B36: =IF(BCC_KHOAN!B36="","",BCC_KHOAN!B36) -> 046181009164 | C36: =IF(B36="","",IFERROR(INDEX(NV_TEN,MATCH(B36,NV_MA,0)),"MÃ KHÔNG CÓ")) -> Hoàng Thị Nhung | D36: =IF(B36="","",IFERROR(INDEX(NV_HINHTHUC,MATCH(B36,NV_MA,0)),"")) -> Khoán | E36: =IF(D36="Khoán",IFERROR(INDEX(NV_HESO,MATCH(B36,NV_MA,0)),0),"") -> 1.15 | F36: =IF(D36="Khoán",IFERROR(INDEX(HS_SX!$B$5:$B$30,MATCH(E36,HS_SX!$A$5:$A$30,0)),0),"") -> 7400 | G36: =IF(B36="","",IFERROR(INDEX(BCC_GIO,MATCH(B36,BCC_MA,0)),0)) -> 0 | H36: =IF(B36="","",G36/GIO_CONG) -> 0 | I36: =IF(D36="Khoán",IF(GIO_TB>0,G36/GIO_TB*KL_CHEBIEN,0),0) -> 0 | J36: =IF(D36="Khoán",F36*I36,0) -> 0 | K36: =IF(D36="Khoán",IF(TONG_GIO_KHOAN>0,QUY_HANGING/TONG_GIO_KHOAN*G36,0),0) -> 0 | L36: =IF(D36="Khoán",IF(TONG_GIO_KHOAN>0,QUY_KHAC/TONG_GIO_KHOAN*G36,0),0) -> 0 | M36: =IF(B36="",0,SUMIFS(KHOAN_KHAC!$F$5:$F$39,KHOAN_KHAC!$G$5:$G$39,B36)) -> 0 | N36: =IF(D36="Khoán",IF(TONG_GIO_KHOAN>0,QUY_CHEN/TONG_GIO_KHOAN*G36,0),0) -> 0 | O36: =IF(D36="Khoán",IF(TONG_GIO_KHOAN>0,-TONG_CONGNHAT/TONG_GIO_KHOAN*G36,0),0) -> 0 | P36: =IF(D36="Công nhật",H36*IFERROR(IF(INDEX(NV_DGCN,MATCH(B36,NV_MA,0))="",DG_CONGNHAT,INDEX(NV_DGCN,MATCH(B36,NV_MA,0))),DG_CONGNHAT),0) -> 0 | Q36: =IF(B36="","",IF(D36="Khoán",ROUNDDOWN(J36+K36+L36+M36+N36+O36,-3),P36+M36)) -> 0 | R36: =IF(B36="","",ROUNDDOWN(TIENAN_CONG*H36,-3)) -> 0 | S36: =IF(B36="","",Q36+R36) -> 0
A37: =IF(B37="","",32) -> 32 | B37: =IF(BCC_KHOAN!B37="","",BCC_KHOAN!B37) -> 046173005614 | C37: =IF(B37="","",IFERROR(INDEX(NV_TEN,MATCH(B37,NV_MA,0)),"MÃ KHÔNG CÓ")) -> Trần Thị Thu Thủy | D37: =IF(B37="","",IFERROR(INDEX(NV_HINHTHUC,MATCH(B37,NV_MA,0)),"")) -> Khoán | E37: =IF(D37="Khoán",IFERROR(INDEX(NV_HESO,MATCH(B37,NV_MA,0)),0),"") -> 1.1 | F37: =IF(D37="Khoán",IFERROR(INDEX(HS_SX!$B$5:$B$30,MATCH(E37,HS_SX!$A$5:$A$30,0)),0),"") -> 7100 | G37: =IF(B37="","",IFERROR(INDEX(BCC_GIO,MATCH(B37,BCC_MA,0)),0)) -> 0 | H37: =IF(B37="","",G37/GIO_CONG) -> 0 | I37: =IF(D37="Khoán",IF(GIO_TB>0,G37/GIO_TB*KL_CHEBIEN,0),0) -> 0 | J37: =IF(D37="Khoán",F37*I37,0) -> 0 | K37: =IF(D37="Khoán",IF(TONG_GIO_KHOAN>0,QUY_HANGING/TONG_GIO_KHOAN*G37,0),0) -> 0 | L37: =IF(D37="Khoán",IF(TONG_GIO_KHOAN>0,QUY_KHAC/TONG_GIO_KHOAN*G37,0),0) -> 0 | M37: =IF(B37="",0,SUMIFS(KHOAN_KHAC!$F$5:$F$39,KHOAN_KHAC!$G$5:$G$39,B37)) -> 0 | N37: =IF(D37="Khoán",IF(TONG_GIO_KHOAN>0,QUY_CHEN/TONG_GIO_KHOAN*G37,0),0) -> 0 | O37: =IF(D37="Khoán",IF(TONG_GIO_KHOAN>0,-TONG_CONGNHAT/TONG_GIO_KHOAN*G37,0),0) -> 0 | P37: =IF(D37="Công nhật",H37*IFERROR(IF(INDEX(NV_DGCN,MATCH(B37,NV_MA,0))="",DG_CONGNHAT,INDEX(NV_DGCN,MATCH(B37,NV_MA,0))),DG_CONGNHAT),0) -> 0 | Q37: =IF(B37="","",IF(D37="Khoán",ROUNDDOWN(J37+K37+L37+M37+N37+O37,-3),P37+M37)) -> 0 | R37: =IF(B37="","",ROUNDDOWN(TIENAN_CONG*H37,-3)) -> 0 | S37: =IF(B37="","",Q37+R37) -> 0
A38: =IF(B38="","",33) -> 33 | B38: =IF(BCC_KHOAN!B38="","",BCC_KHOAN!B38) -> 046180005626 | C38: =IF(B38="","",IFERROR(INDEX(NV_TEN,MATCH(B38,NV_MA,0)),"MÃ KHÔNG CÓ")) -> Trần Thị Cẩm Hà | D38: =IF(B38="","",IFERROR(INDEX(NV_HINHTHUC,MATCH(B38,NV_MA,0)),"")) -> Khoán | E38: =IF(D38="Khoán",IFERROR(INDEX(NV_HESO,MATCH(B38,NV_MA,0)),0),"") -> 1.15 | F38: =IF(D38="Khoán",IFERROR(INDEX(HS_SX!$B$5:$B$30,MATCH(E38,HS_SX!$A$5:$A$30,0)),0),"") -> 7400 | G38: =IF(B38="","",IFERROR(INDEX(BCC_GIO,MATCH(B38,BCC_MA,0)),0)) -> 0 | H38: =IF(B38="","",G38/GIO_CONG) -> 0 | I38: =IF(D38="Khoán",IF(GIO_TB>0,G38/GIO_TB*KL_CHEBIEN,0),0) -> 0 | J38: =IF(D38="Khoán",F38*I38,0) -> 0 | K38: =IF(D38="Khoán",IF(TONG_GIO_KHOAN>0,QUY_HANGING/TONG_GIO_KHOAN*G38,0),0) -> 0 | L38: =IF(D38="Khoán",IF(TONG_GIO_KHOAN>0,QUY_KHAC/TONG_GIO_KHOAN*G38,0),0) -> 0 | M38: =IF(B38="",0,SUMIFS(KHOAN_KHAC!$F$5:$F$39,KHOAN_KHAC!$G$5:$G$39,B38)) -> 0 | N38: =IF(D38="Khoán",IF(TONG_GIO_KHOAN>0,QUY_CHEN/TONG_GIO_KHOAN*G38,0),0) -> 0 | O38: =IF(D38="Khoán",IF(TONG_GIO_KHOAN>0,-TONG_CONGNHAT/TONG_GIO_KHOAN*G38,0),0) -> 0 | P38: =IF(D38="Công nhật",H38*IFERROR(IF(INDEX(NV_DGCN,MATCH(B38,NV_MA,0))="",DG_CONGNHAT,INDEX(NV_DGCN,MATCH(B38,NV_MA,0))),DG_CONGNHAT),0) -> 0 | Q38: =IF(B38="","",IF(D38="Khoán",ROUNDDOWN(J38+K38+L38+M38+N38+O38,-3),P38+M38)) -> 0 | R38: =IF(B38="","",ROUNDDOWN(TIENAN_CONG*H38,-3)) -> 0 | S38: =IF(B38="","",Q38+R38) -> 0
A39: =IF(B39="","",34) -> 34 | B39: =IF(BCC_KHOAN!B39="","",BCC_KHOAN!B39) -> 046177004568 | C39: =IF(B39="","",IFERROR(INDEX(NV_TEN,MATCH(B39,NV_MA,0)),"MÃ KHÔNG CÓ")) -> Nguyễn Thị Kim Tin | D39: =IF(B39="","",IFERROR(INDEX(NV_HINHTHUC,MATCH(B39,NV_MA,0)),"")) -> Khoán | E39: =IF(D39="Khoán",IFERROR(INDEX(NV_HESO,MATCH(B39,NV_MA,0)),0),"") -> 1.15 | F39: =IF(D39="Khoán",IFERROR(INDEX(HS_SX!$B$5:$B$30,MATCH(E39,HS_SX!$A$5:$A$30,0)),0),"") -> 7400 | G39: =IF(B39="","",IFERROR(INDEX(BCC_GIO,MATCH(B39,BCC_MA,0)),0)) -> 0 | H39: =IF(B39="","",G39/GIO_CONG) -> 0 | I39: =IF(D39="Khoán",IF(GIO_TB>0,G39/GIO_TB*KL_CHEBIEN,0),0) -> 0 | J39: =IF(D39="Khoán",F39*I39,0) -> 0 | K39: =IF(D39="Khoán",IF(TONG_GIO_KHOAN>0,QUY_HANGING/TONG_GIO_KHOAN*G39,0),0) -> 0 | L39: =IF(D39="Khoán",IF(TONG_GIO_KHOAN>0,QUY_KHAC/TONG_GIO_KHOAN*G39,0),0) -> 0 | M39: =IF(B39="",0,SUMIFS(KHOAN_KHAC!$F$5:$F$39,KHOAN_KHAC!$G$5:$G$39,B39)) -> 0 | N39: =IF(D39="Khoán",IF(TONG_GIO_KHOAN>0,QUY_CHEN/TONG_GIO_KHOAN*G39,0),0) -> 0 | O39: =IF(D39="Khoán",IF(TONG_GIO_KHOAN>0,-TONG_CONGNHAT/TONG_GIO_KHOAN*G39,0),0) -> 0 | P39: =IF(D39="Công nhật",H39*IFERROR(IF(INDEX(NV_DGCN,MATCH(B39,NV_MA,0))="",DG_CONGNHAT,INDEX(NV_DGCN,MATCH(B39,NV_MA,0))),DG_CONGNHAT),0) -> 0 | Q39: =IF(B39="","",IF(D39="Khoán",ROUNDDOWN(J39+K39+L39+M39+N39+O39,-3),P39+M39)) -> 0 | R39: =IF(B39="","",ROUNDDOWN(TIENAN_CONG*H39,-3)) -> 0 | S39: =IF(B39="","",Q39+R39) -> 0
A40: =IF(B40="","",35) -> 35 | B40: =IF(BCC_KHOAN!B40="","",BCC_KHOAN!B40) -> 046176012968 | C40: =IF(B40="","",IFERROR(INDEX(NV_TEN,MATCH(B40,NV_MA,0)),"MÃ KHÔNG CÓ")) -> Nguyễn Thị Loan | D40: =IF(B40="","",IFERROR(INDEX(NV_HINHTHUC,MATCH(B40,NV_MA,0)),"")) -> Khoán | E40: =IF(D40="Khoán",IFERROR(INDEX(NV_HESO,MATCH(B40,NV_MA,0)),0),"") -> 1.1 | F40: =IF(D40="Khoán",IFERROR(INDEX(HS_SX!$B$5:$B$30,MATCH(E40,HS_SX!$A$5:$A$30,0)),0),"") -> 7100 | G40: =IF(B40="","",IFERROR(INDEX(BCC_GIO,MATCH(B40,BCC_MA,0)),0)) -> 0 | H40: =IF(B40="","",G40/GIO_CONG) -> 0 | I40: =IF(D40="Khoán",IF(GIO_TB>0,G40/GIO_TB*KL_CHEBIEN,0),0) -> 0 | J40: =IF(D40="Khoán",F40*I40,0) -> 0 | K40: =IF(D40="Khoán",IF(TONG_GIO_KHOAN>0,QUY_HANGING/TONG_GIO_KHOAN*G40,0),0) -> 0 | L40: =IF(D40="Khoán",IF(TONG_GIO_KHOAN>0,QUY_KHAC/TONG_GIO_KHOAN*G40,0),0) -> 0 | M40: =IF(B40="",0,SUMIFS(KHOAN_KHAC!$F$5:$F$39,KHOAN_KHAC!$G$5:$G$39,B40)) -> 0 | N40: =IF(D40="Khoán",IF(TONG_GIO_KHOAN>0,QUY_CHEN/TONG_GIO_KHOAN*G40,0),0) -> 0 | O40: =IF(D40="Khoán",IF(TONG_GIO_KHOAN>0,-TONG_CONGNHAT/TONG_GIO_KHOAN*G40,0),0) -> 0 | P40: =IF(D40="Công nhật",H40*IFERROR(IF(INDEX(NV_DGCN,MATCH(B40,NV_MA,0))="",DG_CONGNHAT,INDEX(NV_DGCN,MATCH(B40,NV_MA,0))),DG_CONGNHAT),0) -> 0 | Q40: =IF(B40="","",IF(D40="Khoán",ROUNDDOWN(J40+K40+L40+M40+N40+O40,-3),P40+M40)) -> 0 | R40: =IF(B40="","",ROUNDDOWN(TIENAN_CONG*H40,-3)) -> 0 | S40: =IF(B40="","",Q40+R40) -> 0
A41: =IF(B41="","",36) -> 36 | B41: =IF(BCC_KHOAN!B41="","",BCC_KHOAN!B41) -> 046183006914 | C41: =IF(B41="","",IFERROR(INDEX(NV_TEN,MATCH(B41,NV_MA,0)),"MÃ KHÔNG CÓ")) -> Nguyễn Thị Thu Hà | D41: =IF(B41="","",IFERROR(INDEX(NV_HINHTHUC,MATCH(B41,NV_MA,0)),"")) -> Khoán | E41: =IF(D41="Khoán",IFERROR(INDEX(NV_HESO,MATCH(B41,NV_MA,0)),0),"") -> 1.1 | F41: =IF(D41="Khoán",IFERROR(INDEX(HS_SX!$B$5:$B$30,MATCH(E41,HS_SX!$A$5:$A$30,0)),0),"") -> 7100 | G41: =IF(B41="","",IFERROR(INDEX(BCC_GIO,MATCH(B41,BCC_MA,0)),0)) -> 0 | H41: =IF(B41="","",G41/GIO_CONG) -> 0 | I41: =IF(D41="Khoán",IF(GIO_TB>0,G41/GIO_TB*KL_CHEBIEN,0),0) -> 0 | J41: =IF(D41="Khoán",F41*I41,0) -> 0 | K41: =IF(D41="Khoán",IF(TONG_GIO_KHOAN>0,QUY_HANGING/TONG_GIO_KHOAN*G41,0),0) -> 0 | L41: =IF(D41="Khoán",IF(TONG_GIO_KHOAN>0,QUY_KHAC/TONG_GIO_KHOAN*G41,0),0) -> 0 | M41: =IF(B41="",0,SUMIFS(KHOAN_KHAC!$F$5:$F$39,KHOAN_KHAC!$G$5:$G$39,B41)) -> 0 | N41: =IF(D41="Khoán",IF(TONG_GIO_KHOAN>0,QUY_CHEN/TONG_GIO_KHOAN*G41,0),0) -> 0 | O41: =IF(D41="Khoán",IF(TONG_GIO_KHOAN>0,-TONG_CONGNHAT/TONG_GIO_KHOAN*G41,0),0) -> 0 | P41: =IF(D41="Công nhật",H41*IFERROR(IF(INDEX(NV_DGCN,MATCH(B41,NV_MA,0))="",DG_CONGNHAT,INDEX(NV_DGCN,MATCH(B41,NV_MA,0))),DG_CONGNHAT),0) -> 0 | Q41: =IF(B41="","",IF(D41="Khoán",ROUNDDOWN(J41+K41+L41+M41+N41+O41,-3),P41+M41)) -> 0 | R41: =IF(B41="","",ROUNDDOWN(TIENAN_CONG*H41,-3)) -> 0 | S41: =IF(B41="","",Q41+R41) -> 0
A42: =IF(B42="","",37) -> 37 | B42: =IF(BCC_KHOAN!B42="","",BCC_KHOAN!B42) -> 046077008985 | C42: =IF(B42="","",IFERROR(INDEX(NV_TEN,MATCH(B42,NV_MA,0)),"MÃ KHÔNG CÓ")) -> Ngô Văn Đính | D42: =IF(B42="","",IFERROR(INDEX(NV_HINHTHUC,MATCH(B42,NV_MA,0)),"")) -> Khoán | E42: =IF(D42="Khoán",IFERROR(INDEX(NV_HESO,MATCH(B42,NV_MA,0)),0),"") -> 1.25 | F42: =IF(D42="Khoán",IFERROR(INDEX(HS_SX!$B$5:$B$30,MATCH(E42,HS_SX!$A$5:$A$30,0)),0),"") -> 8000 | G42: =IF(B42="","",IFERROR(INDEX(BCC_GIO,MATCH(B42,BCC_MA,0)),0)) -> 0 | H42: =IF(B42="","",G42/GIO_CONG) -> 0 | I42: =IF(D42="Khoán",IF(GIO_TB>0,G42/GIO_TB*KL_CHEBIEN,0),0) -> 0 | J42: =IF(D42="Khoán",F42*I42,0) -> 0 | K42: =IF(D42="Khoán",IF(TONG_GIO_KHOAN>0,QUY_HANGING/TONG_GIO_KHOAN*G42,0),0) -> 0 | L42: =IF(D42="Khoán",IF(TONG_GIO_KHOAN>0,QUY_KHAC/TONG_GIO_KHOAN*G42,0),0) -> 0 | M42: =IF(B42="",0,SUMIFS(KHOAN_KHAC!$F$5:$F$39,KHOAN_KHAC!$G$5:$G$39,B42)) -> 0 | N42: =IF(D42="Khoán",IF(TONG_GIO_KHOAN>0,QUY_CHEN/TONG_GIO_KHOAN*G42,0),0) -> 0 | O42: =IF(D42="Khoán",IF(TONG_GIO_KHOAN>0,-TONG_CONGNHAT/TONG_GIO_KHOAN*G42,0),0) -> 0 | P42: =IF(D42="Công nhật",H42*IFERROR(IF(INDEX(NV_DGCN,MATCH(B42,NV_MA,0))="",DG_CONGNHAT,INDEX(NV_DGCN,MATCH(B42,NV_MA,0))),DG_CONGNHAT),0) -> 0 | Q42: =IF(B42="","",IF(D42="Khoán",ROUNDDOWN(J42+K42+L42+M42+N42+O42,-3),P42+M42)) -> 0 | R42: =IF(B42="","",ROUNDDOWN(TIENAN_CONG*H42,-3)) -> 0 | S42: =IF(B42="","",Q42+R42) -> 0
A43: =IF(B43="","",38) -> 38 | B43: =IF(BCC_KHOAN!B43="","",BCC_KHOAN!B43) -> 046180009217 | C43: =IF(B43="","",IFERROR(INDEX(NV_TEN,MATCH(B43,NV_MA,0)),"MÃ KHÔNG CÓ")) -> Ngô Thị Quý | D43: =IF(B43="","",IFERROR(INDEX(NV_HINHTHUC,MATCH(B43,NV_MA,0)),"")) -> Khoán | E43: =IF(D43="Khoán",IFERROR(INDEX(NV_HESO,MATCH(B43,NV_MA,0)),0),"") -> 1.15 | F43: =IF(D43="Khoán",IFERROR(INDEX(HS_SX!$B$5:$B$30,MATCH(E43,HS_SX!$A$5:$A$30,0)),0),"") -> 7400 | G43: =IF(B43="","",IFERROR(INDEX(BCC_GIO,MATCH(B43,BCC_MA,0)),0)) -> 0 | H43: =IF(B43="","",G43/GIO_CONG) -> 0 | I43: =IF(D43="Khoán",IF(GIO_TB>0,G43/GIO_TB*KL_CHEBIEN,0),0) -> 0 | J43: =IF(D43="Khoán",F43*I43,0) -> 0 | K43: =IF(D43="Khoán",IF(TONG_GIO_KHOAN>0,QUY_HANGING/TONG_GIO_KHOAN*G43,0),0) -> 0 | L43: =IF(D43="Khoán",IF(TONG_GIO_KHOAN>0,QUY_KHAC/TONG_GIO_KHOAN*G43,0),0) -> 0 | M43: =IF(B43="",0,SUMIFS(KHOAN_KHAC!$F$5:$F$39,KHOAN_KHAC!$G$5:$G$39,B43)) -> 0 | N43: =IF(D43="Khoán",IF(TONG_GIO_KHOAN>0,QUY_CHEN/TONG_GIO_KHOAN*G43,0),0) -> 0 | O43: =IF(D43="Khoán",IF(TONG_GIO_KHOAN>0,-TONG_CONGNHAT/TONG_GIO_KHOAN*G43,0),0) -> 0 | P43: =IF(D43="Công nhật",H43*IFERROR(IF(INDEX(NV_DGCN,MATCH(B43,NV_MA,0))="",DG_CONGNHAT,INDEX(NV_DGCN,MATCH(B43,NV_MA,0))),DG_CONGNHAT),0) -> 0 | Q43: =IF(B43="","",IF(D43="Khoán",ROUNDDOWN(J43+K43+L43+M43+N43+O43,-3),P43+M43)) -> 0 | R43: =IF(B43="","",ROUNDDOWN(TIENAN_CONG*H43,-3)) -> 0 | S43: =IF(B43="","",Q43+R43) -> 0
A44: =IF(B44="","",39) -> 39 | B44: =IF(BCC_KHOAN!B44="","",BCC_KHOAN!B44) -> 046075012004 | C44: =IF(B44="","",IFERROR(INDEX(NV_TEN,MATCH(B44,NV_MA,0)),"MÃ KHÔNG CÓ")) -> Ngô Văn Tịnh | D44: =IF(B44="","",IFERROR(INDEX(NV_HINHTHUC,MATCH(B44,NV_MA,0)),"")) -> Khoán | E44: =IF(D44="Khoán",IFERROR(INDEX(NV_HESO,MATCH(B44,NV_MA,0)),0),"") -> 1.1 | F44: =IF(D44="Khoán",IFERROR(INDEX(HS_SX!$B$5:$B$30,MATCH(E44,HS_SX!$A$5:$A$30,0)),0),"") -> 7100 | G44: =IF(B44="","",IFERROR(INDEX(BCC_GIO,MATCH(B44,BCC_MA,0)),0)) -> 0 | H44: =IF(B44="","",G44/GIO_CONG) -> 0 | I44: =IF(D44="Khoán",IF(GIO_TB>0,G44/GIO_TB*KL_CHEBIEN,0),0) -> 0 | J44: =IF(D44="Khoán",F44*I44,0) -> 0 | K44: =IF(D44="Khoán",IF(TONG_GIO_KHOAN>0,QUY_HANGING/TONG_GIO_KHOAN*G44,0),0) -> 0 | L44: =IF(D44="Khoán",IF(TONG_GIO_KHOAN>0,QUY_KHAC/TONG_GIO_KHOAN*G44,0),0) -> 0 | M44: =IF(B44="",0,SUMIFS(KHOAN_KHAC!$F$5:$F$39,KHOAN_KHAC!$G$5:$G$39,B44)) -> 0 | N44: =IF(D44="Khoán",IF(TONG_GIO_KHOAN>0,QUY_CHEN/TONG_GIO_KHOAN*G44,0),0) -> 0 | O44: =IF(D44="Khoán",IF(TONG_GIO_KHOAN>0,-TONG_CONGNHAT/TONG_GIO_KHOAN*G44,0),0) -> 0 | P44: =IF(D44="Công nhật",H44*IFERROR(IF(INDEX(NV_DGCN,MATCH(B44,NV_MA,0))="",DG_CONGNHAT,INDEX(NV_DGCN,MATCH(B44,NV_MA,0))),DG_CONGNHAT),0) -> 0 | Q44: =IF(B44="","",IF(D44="Khoán",ROUNDDOWN(J44+K44+L44+M44+N44+O44,-3),P44+M44)) -> 0 | R44: =IF(B44="","",ROUNDDOWN(TIENAN_CONG*H44,-3)) -> 0 | S44: =IF(B44="","",Q44+R44) -> 0
A45: =IF(B45="","",40) -> 40 | B45: =IF(BCC_KHOAN!B45="","",BCC_KHOAN!B45) -> 046181010233 | C45: =IF(B45="","",IFERROR(INDEX(NV_TEN,MATCH(B45,NV_MA,0)),"MÃ KHÔNG CÓ")) -> Đỗ Thị Hoài | D45: =IF(B45="","",IFERROR(INDEX(NV_HINHTHUC,MATCH(B45,NV_MA,0)),"")) -> Khoán | E45: =IF(D45="Khoán",IFERROR(INDEX(NV_HESO,MATCH(B45,NV_MA,0)),0),"") -> 1.1 | F45: =IF(D45="Khoán",IFERROR(INDEX(HS_SX!$B$5:$B$30,MATCH(E45,HS_SX!$A$5:$A$30,0)),0),"") -> 7100 | G45: =IF(B45="","",IFERROR(INDEX(BCC_GIO,MATCH(B45,BCC_MA,0)),0)) -> 0 | H45: =IF(B45="","",G45/GIO_CONG) -> 0 | I45: =IF(D45="Khoán",IF(GIO_TB>0,G45/GIO_TB*KL_CHEBIEN,0),0) -> 0 | J45: =IF(D45="Khoán",F45*I45,0) -> 0 | K45: =IF(D45="Khoán",IF(TONG_GIO_KHOAN>0,QUY_HANGING/TONG_GIO_KHOAN*G45,0),0) -> 0 | L45: =IF(D45="Khoán",IF(TONG_GIO_KHOAN>0,QUY_KHAC/TONG_GIO_KHOAN*G45,0),0) -> 0 | M45: =IF(B45="",0,SUMIFS(KHOAN_KHAC!$F$5:$F$39,KHOAN_KHAC!$G$5:$G$39,B45)) -> 0 | N45: =IF(D45="Khoán",IF(TONG_GIO_KHOAN>0,QUY_CHEN/TONG_GIO_KHOAN*G45,0),0) -> 0 | O45: =IF(D45="Khoán",IF(TONG_GIO_KHOAN>0,-TONG_CONGNHAT/TONG_GIO_KHOAN*G45,0),0) -> 0 | P45: =IF(D45="Công nhật",H45*IFERROR(IF(INDEX(NV_DGCN,MATCH(B45,NV_MA,0))="",DG_CONGNHAT,INDEX(NV_DGCN,MATCH(B45,NV_MA,0))),DG_CONGNHAT),0) -> 0 | Q45: =IF(B45="","",IF(D45="Khoán",ROUNDDOWN(J45+K45+L45+M45+N45+O45,-3),P45+M45)) -> 0 | R45: =IF(B45="","",ROUNDDOWN(TIENAN_CONG*H45,-3)) -> 0 | S45: =IF(B45="","",Q45+R45) -> 0
A46: =IF(B46="","",41) -> 41 | B46: =IF(BCC_KHOAN!B46="","",BCC_KHOAN!B46) -> 046180005929 | C46: =IF(B46="","",IFERROR(INDEX(NV_TEN,MATCH(B46,NV_MA,0)),"MÃ KHÔNG CÓ")) -> Nguyễn Thị Lợi | D46: =IF(B46="","",IFERROR(INDEX(NV_HINHTHUC,MATCH(B46,NV_MA,0)),"")) -> Khoán | E46: =IF(D46="Khoán",IFERROR(INDEX(NV_HESO,MATCH(B46,NV_MA,0)),0),"") -> 1.1 | F46: =IF(D46="Khoán",IFERROR(INDEX(HS_SX!$B$5:$B$30,MATCH(E46,HS_SX!$A$5:$A$30,0)),0),"") -> 7100 | G46: =IF(B46="","",IFERROR(INDEX(BCC_GIO,MATCH(B46,BCC_MA,0)),0)) -> 0 | H46: =IF(B46="","",G46/GIO_CONG) -> 0 | I46: =IF(D46="Khoán",IF(GIO_TB>0,G46/GIO_TB*KL_CHEBIEN,0),0) -> 0 | J46: =IF(D46="Khoán",F46*I46,0) -> 0 | K46: =IF(D46="Khoán",IF(TONG_GIO_KHOAN>0,QUY_HANGING/TONG_GIO_KHOAN*G46,0),0) -> 0 | L46: =IF(D46="Khoán",IF(TONG_GIO_KHOAN>0,QUY_KHAC/TONG_GIO_KHOAN*G46,0),0) -> 0 | M46: =IF(B46="",0,SUMIFS(KHOAN_KHAC!$F$5:$F$39,KHOAN_KHAC!$G$5:$G$39,B46)) -> 0 | N46: =IF(D46="Khoán",IF(TONG_GIO_KHOAN>0,QUY_CHEN/TONG_GIO_KHOAN*G46,0),0) -> 0 | O46: =IF(D46="Khoán",IF(TONG_GIO_KHOAN>0,-TONG_CONGNHAT/TONG_GIO_KHOAN*G46,0),0) -> 0 | P46: =IF(D46="Công nhật",H46*IFERROR(IF(INDEX(NV_DGCN,MATCH(B46,NV_MA,0))="",DG_CONGNHAT,INDEX(NV_DGCN,MATCH(B46,NV_MA,0))),DG_CONGNHAT),0) -> 0 | Q46: =IF(B46="","",IF(D46="Khoán",ROUNDDOWN(J46+K46+L46+M46+N46+O46,-3),P46+M46)) -> 0 | R46: =IF(B46="","",ROUNDDOWN(TIENAN_CONG*H46,-3)) -> 0 | S46: =IF(B46="","",Q46+R46) -> 0
A47: =IF(B47="","",42) -> 42 | B47: =IF(BCC_KHOAN!B47="","",BCC_KHOAN!B47) -> 046095008572 | C47: =IF(B47="","",IFERROR(INDEX(NV_TEN,MATCH(B47,NV_MA,0)),"MÃ KHÔNG CÓ")) -> Trần Văn Tấn | D47: =IF(B47="","",IFERROR(INDEX(NV_HINHTHUC,MATCH(B47,NV_MA,0)),"")) -> Khoán | E47: =IF(D47="Khoán",IFERROR(INDEX(NV_HESO,MATCH(B47,NV_MA,0)),0),"") -> 1.1 | F47: =IF(D47="Khoán",IFERROR(INDEX(HS_SX!$B$5:$B$30,MATCH(E47,HS_SX!$A$5:$A$30,0)),0),"") -> 7100 | G47: =IF(B47="","",IFERROR(INDEX(BCC_GIO,MATCH(B47,BCC_MA,0)),0)) -> 0 | H47: =IF(B47="","",G47/GIO_CONG) -> 0 | I47: =IF(D47="Khoán",IF(GIO_TB>0,G47/GIO_TB*KL_CHEBIEN,0),0) -> 0 | J47: =IF(D47="Khoán",F47*I47,0) -> 0 | K47: =IF(D47="Khoán",IF(TONG_GIO_KHOAN>0,QUY_HANGING/TONG_GIO_KHOAN*G47,0),0) -> 0 | L47: =IF(D47="Khoán",IF(TONG_GIO_KHOAN>0,QUY_KHAC/TONG_GIO_KHOAN*G47,0),0) -> 0 | M47: =IF(B47="",0,SUMIFS(KHOAN_KHAC!$F$5:$F$39,KHOAN_KHAC!$G$5:$G$39,B47)) -> 0 | N47: =IF(D47="Khoán",IF(TONG_GIO_KHOAN>0,QUY_CHEN/TONG_GIO_KHOAN*G47,0),0) -> 0 | O47: =IF(D47="Khoán",IF(TONG_GIO_KHOAN>0,-TONG_CONGNHAT/TONG_GIO_KHOAN*G47,0),0) -> 0 | P47: =IF(D47="Công nhật",H47*IFERROR(IF(INDEX(NV_DGCN,MATCH(B47,NV_MA,0))="",DG_CONGNHAT,INDEX(NV_DGCN,MATCH(B47,NV_MA,0))),DG_CONGNHAT),0) -> 0 | Q47: =IF(B47="","",IF(D47="Khoán",ROUNDDOWN(J47+K47+L47+M47+N47+O47,-3),P47+M47)) -> 0 | R47: =IF(B47="","",ROUNDDOWN(TIENAN_CONG*H47,-3)) -> 0 | S47: =IF(B47="","",Q47+R47) -> 0
A48: =IF(B48="","",43) -> 43 | B48: =IF(BCC_KHOAN!B48="","",BCC_KHOAN!B48) -> 045200002742 | C48: =IF(B48="","",IFERROR(INDEX(NV_TEN,MATCH(B48,NV_MA,0)),"MÃ KHÔNG CÓ")) -> Hoàng Văn Anh | D48: =IF(B48="","",IFERROR(INDEX(NV_HINHTHUC,MATCH(B48,NV_MA,0)),"")) -> Khoán | E48: =IF(D48="Khoán",IFERROR(INDEX(NV_HESO,MATCH(B48,NV_MA,0)),0),"") -> 1.1 | F48: =IF(D48="Khoán",IFERROR(INDEX(HS_SX!$B$5:$B$30,MATCH(E48,HS_SX!$A$5:$A$30,0)),0),"") -> 7100 | G48: =IF(B48="","",IFERROR(INDEX(BCC_GIO,MATCH(B48,BCC_MA,0)),0)) -> 200 | H48: =IF(B48="","",G48/GIO_CONG) -> 25 | I48: =IF(D48="Khoán",IF(GIO_TB>0,G48/GIO_TB*KL_CHEBIEN,0),0) -> 19892.123 | J48: =IF(D48="Khoán",F48*I48,0) -> 1.4123407e+08 | K48: =IF(D48="Khoán",IF(TONG_GIO_KHOAN>0,QUY_HANGING/TONG_GIO_KHOAN*G48,0),0) -> 0 | L48: =IF(D48="Khoán",IF(TONG_GIO_KHOAN>0,QUY_KHAC/TONG_GIO_KHOAN*G48,0),0) -> -9868131.9 | M48: =IF(B48="",0,SUMIFS(KHOAN_KHAC!$F$5:$F$39,KHOAN_KHAC!$G$5:$G$39,B48)) -> 0 | N48: =IF(D48="Khoán",IF(TONG_GIO_KHOAN>0,QUY_CHEN/TONG_GIO_KHOAN*G48,0),0) -> 6484307.7 | O48: =IF(D48="Khoán",IF(TONG_GIO_KHOAN>0,-TONG_CONGNHAT/TONG_GIO_KHOAN*G48,0),0) -> 0 | P48: =IF(D48="Công nhật",H48*IFERROR(IF(INDEX(NV_DGCN,MATCH(B48,NV_MA,0))="",DG_CONGNHAT,INDEX(NV_DGCN,MATCH(B48,NV_MA,0))),DG_CONGNHAT),0) -> 0 | Q48: =IF(B48="","",IF(D48="Khoán",ROUNDDOWN(J48+K48+L48+M48+N48+O48,-3),P48+M48)) -> 137850000 | R48: =IF(B48="","",ROUNDDOWN(TIENAN_CONG*H48,-3)) -> 9709000 | S48: =IF(B48="","",Q48+R48) -> 147559000
A49: =IF(B49="","",44) -> 44 | B49: =IF(BCC_KHOAN!B49="","",BCC_KHOAN!B49) -> CN_MAU_01 | C49: =IF(B49="","",IFERROR(INDEX(NV_TEN,MATCH(B49,NV_MA,0)),"MÃ KHÔNG CÓ")) -> (Ví dụ) Nguyễn Văn A | D49: =IF(B49="","",IFERROR(INDEX(NV_HINHTHUC,MATCH(B49,NV_MA,0)),"")) -> Công nhật | E49: =IF(D49="Khoán",IFERROR(INDEX(NV_HESO,MATCH(B49,NV_MA,0)),0),"") | F49: =IF(D49="Khoán",IFERROR(INDEX(HS_SX!$B$5:$B$30,MATCH(E49,HS_SX!$A$5:$A$30,0)),0),"") | G49: =IF(B49="","",IFERROR(INDEX(BCC_GIO,MATCH(B49,BCC_MA,0)),0)) -> 0 | H49: =IF(B49="","",G49/GIO_CONG) -> 0 | I49: =IF(D49="Khoán",IF(GIO_TB>0,G49/GIO_TB*KL_CHEBIEN,0),0) -> 0 | J49: =IF(D49="Khoán",F49*I49,0) -> 0 | K49: =IF(D49="Khoán",IF(TONG_GIO_KHOAN>0,QUY_HANGING/TONG_GIO_KHOAN*G49,0),0) -> 0 | L49: =IF(D49="Khoán",IF(TONG_GIO_KHOAN>0,QUY_KHAC/TONG_GIO_KHOAN*G49,0),0) -> 0 | M49: =IF(B49="",0,SUMIFS(KHOAN_KHAC!$F$5:$F$39,KHOAN_KHAC!$G$5:$G$39,B49)) -> 0 | N49: =IF(D49="Khoán",IF(TONG_GIO_KHOAN>0,QUY_CHEN/TONG_GIO_KHOAN*G49,0),0) -> 0 | O49: =IF(D49="Khoán",IF(TONG_GIO_KHOAN>0,-TONG_CONGNHAT/TONG_GIO_KHOAN*G49,0),0) -> 0 | P49: =IF(D49="Công nhật",H49*IFERROR(IF(INDEX(NV_DGCN,MATCH(B49,NV_MA,0))="",DG_CONGNHAT,INDEX(NV_DGCN,MATCH(B49,NV_MA,0))),DG_CONGNHAT),0) -> 0 | Q49: =IF(B49="","",IF(D49="Khoán",ROUNDDOWN(J49+K49+L49+M49+N49+O49,-3),P49+M49)) -> 0 | R49: =IF(B49="","",ROUNDDOWN(TIENAN_CONG*H49,-3)) -> 0 | S49: =IF(B49="","",Q49+R49) -> 0
A50: =IF(B50="","",45) | B50: =IF(BCC_KHOAN!B50="","",BCC_KHOAN!B50) | C50: =IF(B50="","",IFERROR(INDEX(NV_TEN,MATCH(B50,NV_MA,0)),"MÃ KHÔNG CÓ")) | D50: =IF(B50="","",IFERROR(INDEX(NV_HINHTHUC,MATCH(B50,NV_MA,0)),"")) | E50: =IF(D50="Khoán",IFERROR(INDEX(NV_HESO,MATCH(B50,NV_MA,0)),0),"") | F50: =IF(D50="Khoán",IFERROR(INDEX(HS_SX!$B$5:$B$30,MATCH(E50,HS_SX!$A$5:$A$30,0)),0),"") | G50: =IF(B50="","",IFERROR(INDEX(BCC_GIO,MATCH(B50,BCC_MA,0)),0)) | H50: =IF(B50="","",G50/GIO_CONG) | I50: =IF(D50="Khoán",IF(GIO_TB>0,G50/GIO_TB*KL_CHEBIEN,0),0) -> 0 | J50: =IF(D50="Khoán",F50*I50,0) -> 0 | K50: =IF(D50="Khoán",IF(TONG_GIO_KHOAN>0,QUY_HANGING/TONG_GIO_KHOAN*G50,0),0) -> 0 | L50: =IF(D50="Khoán",IF(TONG_GIO_KHOAN>0,QUY_KHAC/TONG_GIO_KHOAN*G50,0),0) -> 0 | M50: =IF(B50="",0,SUMIFS(KHOAN_KHAC!$F$5:$F$39,KHOAN_KHAC!$G$5:$G$39,B50)) -> 0 | N50: =IF(D50="Khoán",IF(TONG_GIO_KHOAN>0,QUY_CHEN/TONG_GIO_KHOAN*G50,0),0) -> 0 | O50: =IF(D50="Khoán",IF(TONG_GIO_KHOAN>0,-TONG_CONGNHAT/TONG_GIO_KHOAN*G50,0),0) -> 0 | P50: =IF(D50="Công nhật",H50*IFERROR(IF(INDEX(NV_DGCN,MATCH(B50,NV_MA,0))="",DG_CONGNHAT,INDEX(NV_DGCN,MATCH(B50,NV_MA,0))),DG_CONGNHAT),0) -> 0 | Q50: =IF(B50="","",IF(D50="Khoán",ROUNDDOWN(J50+K50+L50+M50+N50+O50,-3),P50+M50)) | R50: =IF(B50="","",ROUNDDOWN(TIENAN_CONG*H50,-3)) | S50: =IF(B50="","",Q50+R50)
A51: =IF(B51="","",46) | B51: =IF(BCC_KHOAN!B51="","",BCC_KHOAN!B51) | C51: =IF(B51="","",IFERROR(INDEX(NV_TEN,MATCH(B51,NV_MA,0)),"MÃ KHÔNG CÓ")) | D51: =IF(B51="","",IFERROR(INDEX(NV_HINHTHUC,MATCH(B51,NV_MA,0)),"")) | E51: =IF(D51="Khoán",IFERROR(INDEX(NV_HESO,MATCH(B51,NV_MA,0)),0),"") | F51: =IF(D51="Khoán",IFERROR(INDEX(HS_SX!$B$5:$B$30,MATCH(E51,HS_SX!$A$5:$A$30,0)),0),"") | G51: =IF(B51="","",IFERROR(INDEX(BCC_GIO,MATCH(B51,BCC_MA,0)),0)) | H51: =IF(B51="","",G51/GIO_CONG) | I51: =IF(D51="Khoán",IF(GIO_TB>0,G51/GIO_TB*KL_CHEBIEN,0),0) -> 0 | J51: =IF(D51="Khoán",F51*I51,0) -> 0 | K51: =IF(D51="Khoán",IF(TONG_GIO_KHOAN>0,QUY_HANGING/TONG_GIO_KHOAN*G51,0),0) -> 0 | L51: =IF(D51="Khoán",IF(TONG_GIO_KHOAN>0,QUY_KHAC/TONG_GIO_KHOAN*G51,0),0) -> 0 | M51: =IF(B51="",0,SUMIFS(KHOAN_KHAC!$F$5:$F$39,KHOAN_KHAC!$G$5:$G$39,B51)) -> 0 | N51: =IF(D51="Khoán",IF(TONG_GIO_KHOAN>0,QUY_CHEN/TONG_GIO_KHOAN*G51,0),0) -> 0 | O51: =IF(D51="Khoán",IF(TONG_GIO_KHOAN>0,-TONG_CONGNHAT/TONG_GIO_KHOAN*G51,0),0) -> 0 | P51: =IF(D51="Công nhật",H51*IFERROR(IF(INDEX(NV_DGCN,MATCH(B51,NV_MA,0))="",DG_CONGNHAT,INDEX(NV_DGCN,MATCH(B51,NV_MA,0))),DG_CONGNHAT),0) -> 0 | Q51: =IF(B51="","",IF(D51="Khoán",ROUNDDOWN(J51+K51+L51+M51+N51+O51,-3),P51+M51)) | R51: =IF(B51="","",ROUNDDOWN(TIENAN_CONG*H51,-3)) | S51: =IF(B51="","",Q51+R51)
A52: =IF(B52="","",47) | B52: =IF(BCC_KHOAN!B52="","",BCC_KHOAN!B52) | C52: =IF(B52="","",IFERROR(INDEX(NV_TEN,MATCH(B52,NV_MA,0)),"MÃ KHÔNG CÓ")) | D52: =IF(B52="","",IFERROR(INDEX(NV_HINHTHUC,MATCH(B52,NV_MA,0)),"")) | E52: =IF(D52="Khoán",IFERROR(INDEX(NV_HESO,MATCH(B52,NV_MA,0)),0),"") | F52: =IF(D52="Khoán",IFERROR(INDEX(HS_SX!$B$5:$B$30,MATCH(E52,HS_SX!$A$5:$A$30,0)),0),"") | G52: =IF(B52="","",IFERROR(INDEX(BCC_GIO,MATCH(B52,BCC_MA,0)),0)) | H52: =IF(B52="","",G52/GIO_CONG) | I52: =IF(D52="Khoán",IF(GIO_TB>0,G52/GIO_TB*KL_CHEBIEN,0),0) -> 0 | J52: =IF(D52="Khoán",F52*I52,0) -> 0 | K52: =IF(D52="Khoán",IF(TONG_GIO_KHOAN>0,QUY_HANGING/TONG_GIO_KHOAN*G52,0),0) -> 0 | L52: =IF(D52="Khoán",IF(TONG_GIO_KHOAN>0,QUY_KHAC/TONG_GIO_KHOAN*G52,0),0) -> 0 | M52: =IF(B52="",0,SUMIFS(KHOAN_KHAC!$F$5:$F$39,KHOAN_KHAC!$G$5:$G$39,B52)) -> 0 | N52: =IF(D52="Khoán",IF(TONG_GIO_KHOAN>0,QUY_CHEN/TONG_GIO_KHOAN*G52,0),0) -> 0 | O52: =IF(D52="Khoán",IF(TONG_GIO_KHOAN>0,-TONG_CONGNHAT/TONG_GIO_KHOAN*G52,0),0) -> 0 | P52: =IF(D52="Công nhật",H52*IFERROR(IF(INDEX(NV_DGCN,MATCH(B52,NV_MA,0))="",DG_CONGNHAT,INDEX(NV_DGCN,MATCH(B52,NV_MA,0))),DG_CONGNHAT),0) -> 0 | Q52: =IF(B52="","",IF(D52="Khoán",ROUNDDOWN(J52+K52+L52+M52+N52+O52,-3),P52+M52)) | R52: =IF(B52="","",ROUNDDOWN(TIENAN_CONG*H52,-3)) | S52: =IF(B52="","",Q52+R52)
A53: =IF(B53="","",48) | B53: =IF(BCC_KHOAN!B53="","",BCC_KHOAN!B53) | C53: =IF(B53="","",IFERROR(INDEX(NV_TEN,MATCH(B53,NV_MA,0)),"MÃ KHÔNG CÓ")) | D53: =IF(B53="","",IFERROR(INDEX(NV_HINHTHUC,MATCH(B53,NV_MA,0)),"")) | E53: =IF(D53="Khoán",IFERROR(INDEX(NV_HESO,MATCH(B53,NV_MA,0)),0),"") | F53: =IF(D53="Khoán",IFERROR(INDEX(HS_SX!$B$5:$B$30,MATCH(E53,HS_SX!$A$5:$A$30,0)),0),"") | G53: =IF(B53="","",IFERROR(INDEX(BCC_GIO,MATCH(B53,BCC_MA,0)),0)) | H53: =IF(B53="","",G53/GIO_CONG) | I53: =IF(D53="Khoán",IF(GIO_TB>0,G53/GIO_TB*KL_CHEBIEN,0),0) -> 0 | J53: =IF(D53="Khoán",F53*I53,0) -> 0 | K53: =IF(D53="Khoán",IF(TONG_GIO_KHOAN>0,QUY_HANGING/TONG_GIO_KHOAN*G53,0),0) -> 0 | L53: =IF(D53="Khoán",IF(TONG_GIO_KHOAN>0,QUY_KHAC/TONG_GIO_KHOAN*G53,0),0) -> 0 | M53: =IF(B53="",0,SUMIFS(KHOAN_KHAC!$F$5:$F$39,KHOAN_KHAC!$G$5:$G$39,B53)) -> 0 | N53: =IF(D53="Khoán",IF(TONG_GIO_KHOAN>0,QUY_CHEN/TONG_GIO_KHOAN*G53,0),0) -> 0 | O53: =IF(D53="Khoán",IF(TONG_GIO_KHOAN>0,-TONG_CONGNHAT/TONG_GIO_KHOAN*G53,0),0) -> 0 | P53: =IF(D53="Công nhật",H53*IFERROR(IF(INDEX(NV_DGCN,MATCH(B53,NV_MA,0))="",DG_CONGNHAT,INDEX(NV_DGCN,MATCH(B53,NV_MA,0))),DG_CONGNHAT),0) -> 0 | Q53: =IF(B53="","",IF(D53="Khoán",ROUNDDOWN(J53+K53+L53+M53+N53+O53,-3),P53+M53)) | R53: =IF(B53="","",ROUNDDOWN(TIENAN_CONG*H53,-3)) | S53: =IF(B53="","",Q53+R53)
A54: =IF(B54="","",49) | B54: =IF(BCC_KHOAN!B54="","",BCC_KHOAN!B54) | C54: =IF(B54="","",IFERROR(INDEX(NV_TEN,MATCH(B54,NV_MA,0)),"MÃ KHÔNG CÓ")) | D54: =IF(B54="","",IFERROR(INDEX(NV_HINHTHUC,MATCH(B54,NV_MA,0)),"")) | E54: =IF(D54="Khoán",IFERROR(INDEX(NV_HESO,MATCH(B54,NV_MA,0)),0),"") | F54: =IF(D54="Khoán",IFERROR(INDEX(HS_SX!$B$5:$B$30,MATCH(E54,HS_SX!$A$5:$A$30,0)),0),"") | G54: =IF(B54="","",IFERROR(INDEX(BCC_GIO,MATCH(B54,BCC_MA,0)),0)) | H54: =IF(B54="","",G54/GIO_CONG) | I54: =IF(D54="Khoán",IF(GIO_TB>0,G54/GIO_TB*KL_CHEBIEN,0),0) -> 0 | J54: =IF(D54="Khoán",F54*I54,0) -> 0 | K54: =IF(D54="Khoán",IF(TONG_GIO_KHOAN>0,QUY_HANGING/TONG_GIO_KHOAN*G54,0),0) -> 0 | L54: =IF(D54="Khoán",IF(TONG_GIO_KHOAN>0,QUY_KHAC/TONG_GIO_KHOAN*G54,0),0) -> 0 | M54: =IF(B54="",0,SUMIFS(KHOAN_KHAC!$F$5:$F$39,KHOAN_KHAC!$G$5:$G$39,B54)) -> 0 | N54: =IF(D54="Khoán",IF(TONG_GIO_KHOAN>0,QUY_CHEN/TONG_GIO_KHOAN*G54,0),0) -> 0 | O54: =IF(D54="Khoán",IF(TONG_GIO_KHOAN>0,-TONG_CONGNHAT/TONG_GIO_KHOAN*G54,0),0) -> 0 | P54: =IF(D54="Công nhật",H54*IFERROR(IF(INDEX(NV_DGCN,MATCH(B54,NV_MA,0))="",DG_CONGNHAT,INDEX(NV_DGCN,MATCH(B54,NV_MA,0))),DG_CONGNHAT),0) -> 0 | Q54: =IF(B54="","",IF(D54="Khoán",ROUNDDOWN(J54+K54+L54+M54+N54+O54,-3),P54+M54)) | R54: =IF(B54="","",ROUNDDOWN(TIENAN_CONG*H54,-3)) | S54: =IF(B54="","",Q54+R54)
A55: =IF(B55="","",50) | B55: =IF(BCC_KHOAN!B55="","",BCC_KHOAN!B55) | C55: =IF(B55="","",IFERROR(INDEX(NV_TEN,MATCH(B55,NV_MA,0)),"MÃ KHÔNG CÓ")) | D55: =IF(B55="","",IFERROR(INDEX(NV_HINHTHUC,MATCH(B55,NV_MA,0)),"")) | E55: =IF(D55="Khoán",IFERROR(INDEX(NV_HESO,MATCH(B55,NV_MA,0)),0),"") | F55: =IF(D55="Khoán",IFERROR(INDEX(HS_SX!$B$5:$B$30,MATCH(E55,HS_SX!$A$5:$A$30,0)),0),"") | G55: =IF(B55="","",IFERROR(INDEX(BCC_GIO,MATCH(B55,BCC_MA,0)),0)) | H55: =IF(B55="","",G55/GIO_CONG) | I55: =IF(D55="Khoán",IF(GIO_TB>0,G55/GIO_TB*KL_CHEBIEN,0),0) -> 0 | J55: =IF(D55="Khoán",F55*I55,0) -> 0 | K55: =IF(D55="Khoán",IF(TONG_GIO_KHOAN>0,QUY_HANGING/TONG_GIO_KHOAN*G55,0),0) -> 0 | L55: =IF(D55="Khoán",IF(TONG_GIO_KHOAN>0,QUY_KHAC/TONG_GIO_KHOAN*G55,0),0) -> 0 | M55: =IF(B55="",0,SUMIFS(KHOAN_KHAC!$F$5:$F$39,KHOAN_KHAC!$G$5:$G$39,B55)) -> 0 | N55: =IF(D55="Khoán",IF(TONG_GIO_KHOAN>0,QUY_CHEN/TONG_GIO_KHOAN*G55,0),0) -> 0 | O55: =IF(D55="Khoán",IF(TONG_GIO_KHOAN>0,-TONG_CONGNHAT/TONG_GIO_KHOAN*G55,0),0) -> 0 | P55: =IF(D55="Công nhật",H55*IFERROR(IF(INDEX(NV_DGCN,MATCH(B55,NV_MA,0))="",DG_CONGNHAT,INDEX(NV_DGCN,MATCH(B55,NV_MA,0))),DG_CONGNHAT),0) -> 0 | Q55: =IF(B55="","",IF(D55="Khoán",ROUNDDOWN(J55+K55+L55+M55+N55+O55,-3),P55+M55)) | R55: =IF(B55="","",ROUNDDOWN(TIENAN_CONG*H55,-3)) | S55: =IF(B55="","",Q55+R55)
A56: =IF(B56="","",51) | B56: =IF(BCC_KHOAN!B56="","",BCC_KHOAN!B56) | C56: =IF(B56="","",IFERROR(INDEX(NV_TEN,MATCH(B56,NV_MA,0)),"MÃ KHÔNG CÓ")) | D56: =IF(B56="","",IFERROR(INDEX(NV_HINHTHUC,MATCH(B56,NV_MA,0)),"")) | E56: =IF(D56="Khoán",IFERROR(INDEX(NV_HESO,MATCH(B56,NV_MA,0)),0),"") | F56: =IF(D56="Khoán",IFERROR(INDEX(HS_SX!$B$5:$B$30,MATCH(E56,HS_SX!$A$5:$A$30,0)),0),"") | G56: =IF(B56="","",IFERROR(INDEX(BCC_GIO,MATCH(B56,BCC_MA,0)),0)) | H56: =IF(B56="","",G56/GIO_CONG) | I56: =IF(D56="Khoán",IF(GIO_TB>0,G56/GIO_TB*KL_CHEBIEN,0),0) -> 0 | J56: =IF(D56="Khoán",F56*I56,0) -> 0 | K56: =IF(D56="Khoán",IF(TONG_GIO_KHOAN>0,QUY_HANGING/TONG_GIO_KHOAN*G56,0),0) -> 0 | L56: =IF(D56="Khoán",IF(TONG_GIO_KHOAN>0,QUY_KHAC/TONG_GIO_KHOAN*G56,0),0) -> 0 | M56: =IF(B56="",0,SUMIFS(KHOAN_KHAC!$F$5:$F$39,KHOAN_KHAC!$G$5:$G$39,B56)) -> 0 | N56: =IF(D56="Khoán",IF(TONG_GIO_KHOAN>0,QUY_CHEN/TONG_GIO_KHOAN*G56,0),0) -> 0 | O56: =IF(D56="Khoán",IF(TONG_GIO_KHOAN>0,-TONG_CONGNHAT/TONG_GIO_KHOAN*G56,0),0) -> 0 | P56: =IF(D56="Công nhật",H56*IFERROR(IF(INDEX(NV_DGCN,MATCH(B56,NV_MA,0))="",DG_CONGNHAT,INDEX(NV_DGCN,MATCH(B56,NV_MA,0))),DG_CONGNHAT),0) -> 0 | Q56: =IF(B56="","",IF(D56="Khoán",ROUNDDOWN(J56+K56+L56+M56+N56+O56,-3),P56+M56)) | R56: =IF(B56="","",ROUNDDOWN(TIENAN_CONG*H56,-3)) | S56: =IF(B56="","",Q56+R56)
A57: =IF(B57="","",52) | B57: =IF(BCC_KHOAN!B57="","",BCC_KHOAN!B57) | C57: =IF(B57="","",IFERROR(INDEX(NV_TEN,MATCH(B57,NV_MA,0)),"MÃ KHÔNG CÓ")) | D57: =IF(B57="","",IFERROR(INDEX(NV_HINHTHUC,MATCH(B57,NV_MA,0)),"")) | E57: =IF(D57="Khoán",IFERROR(INDEX(NV_HESO,MATCH(B57,NV_MA,0)),0),"") | F57: =IF(D57="Khoán",IFERROR(INDEX(HS_SX!$B$5:$B$30,MATCH(E57,HS_SX!$A$5:$A$30,0)),0),"") | G57: =IF(B57="","",IFERROR(INDEX(BCC_GIO,MATCH(B57,BCC_MA,0)),0)) | H57: =IF(B57="","",G57/GIO_CONG) | I57: =IF(D57="Khoán",IF(GIO_TB>0,G57/GIO_TB*KL_CHEBIEN,0),0) -> 0 | J57: =IF(D57="Khoán",F57*I57,0) -> 0 | K57: =IF(D57="Khoán",IF(TONG_GIO_KHOAN>0,QUY_HANGING/TONG_GIO_KHOAN*G57,0),0) -> 0 | L57: =IF(D57="Khoán",IF(TONG_GIO_KHOAN>0,QUY_KHAC/TONG_GIO_KHOAN*G57,0),0) -> 0 | M57: =IF(B57="",0,SUMIFS(KHOAN_KHAC!$F$5:$F$39,KHOAN_KHAC!$G$5:$G$39,B57)) -> 0 | N57: =IF(D57="Khoán",IF(TONG_GIO_KHOAN>0,QUY_CHEN/TONG_GIO_KHOAN*G57,0),0) -> 0 | O57: =IF(D57="Khoán",IF(TONG_GIO_KHOAN>0,-TONG_CONGNHAT/TONG_GIO_KHOAN*G57,0),0) -> 0 | P57: =IF(D57="Công nhật",H57*IFERROR(IF(INDEX(NV_DGCN,MATCH(B57,NV_MA,0))="",DG_CONGNHAT,INDEX(NV_DGCN,MATCH(B57,NV_MA,0))),DG_CONGNHAT),0) -> 0 | Q57: =IF(B57="","",IF(D57="Khoán",ROUNDDOWN(J57+K57+L57+M57+N57+O57,-3),P57+M57)) | R57: =IF(B57="","",ROUNDDOWN(TIENAN_CONG*H57,-3)) | S57: =IF(B57="","",Q57+R57)
A58: =IF(B58="","",53) | B58: =IF(BCC_KHOAN!B58="","",BCC_KHOAN!B58) | C58: =IF(B58="","",IFERROR(INDEX(NV_TEN,MATCH(B58,NV_MA,0)),"MÃ KHÔNG CÓ")) | D58: =IF(B58="","",IFERROR(INDEX(NV_HINHTHUC,MATCH(B58,NV_MA,0)),"")) | E58: =IF(D58="Khoán",IFERROR(INDEX(NV_HESO,MATCH(B58,NV_MA,0)),0),"") | F58: =IF(D58="Khoán",IFERROR(INDEX(HS_SX!$B$5:$B$30,MATCH(E58,HS_SX!$A$5:$A$30,0)),0),"") | G58: =IF(B58="","",IFERROR(INDEX(BCC_GIO,MATCH(B58,BCC_MA,0)),0)) | H58: =IF(B58="","",G58/GIO_CONG) | I58: =IF(D58="Khoán",IF(GIO_TB>0,G58/GIO_TB*KL_CHEBIEN,0),0) -> 0 | J58: =IF(D58="Khoán",F58*I58,0) -> 0 | K58: =IF(D58="Khoán",IF(TONG_GIO_KHOAN>0,QUY_HANGING/TONG_GIO_KHOAN*G58,0),0) -> 0 | L58: =IF(D58="Khoán",IF(TONG_GIO_KHOAN>0,QUY_KHAC/TONG_GIO_KHOAN*G58,0),0) -> 0 | M58: =IF(B58="",0,SUMIFS(KHOAN_KHAC!$F$5:$F$39,KHOAN_KHAC!$G$5:$G$39,B58)) -> 0 | N58: =IF(D58="Khoán",IF(TONG_GIO_KHOAN>0,QUY_CHEN/TONG_GIO_KHOAN*G58,0),0) -> 0 | O58: =IF(D58="Khoán",IF(TONG_GIO_KHOAN>0,-TONG_CONGNHAT/TONG_GIO_KHOAN*G58,0),0) -> 0 | P58: =IF(D58="Công nhật",H58*IFERROR(IF(INDEX(NV_DGCN,MATCH(B58,NV_MA,0))="",DG_CONGNHAT,INDEX(NV_DGCN,MATCH(B58,NV_MA,0))),DG_CONGNHAT),0) -> 0 | Q58: =IF(B58="","",IF(D58="Khoán",ROUNDDOWN(J58+K58+L58+M58+N58+O58,-3),P58+M58)) | R58: =IF(B58="","",ROUNDDOWN(TIENAN_CONG*H58,-3)) | S58: =IF(B58="","",Q58+R58)
A59: =IF(B59="","",54) | B59: =IF(BCC_KHOAN!B59="","",BCC_KHOAN!B59) | C59: =IF(B59="","",IFERROR(INDEX(NV_TEN,MATCH(B59,NV_MA,0)),"MÃ KHÔNG CÓ")) | D59: =IF(B59="","",IFERROR(INDEX(NV_HINHTHUC,MATCH(B59,NV_MA,0)),"")) | E59: =IF(D59="Khoán",IFERROR(INDEX(NV_HESO,MATCH(B59,NV_MA,0)),0),"") | F59: =IF(D59="Khoán",IFERROR(INDEX(HS_SX!$B$5:$B$30,MATCH(E59,HS_SX!$A$5:$A$30,0)),0),"") | G59: =IF(B59="","",IFERROR(INDEX(BCC_GIO,MATCH(B59,BCC_MA,0)),0)) | H59: =IF(B59="","",G59/GIO_CONG) | I59: =IF(D59="Khoán",IF(GIO_TB>0,G59/GIO_TB*KL_CHEBIEN,0),0) -> 0 | J59: =IF(D59="Khoán",F59*I59,0) -> 0 | K59: =IF(D59="Khoán",IF(TONG_GIO_KHOAN>0,QUY_HANGING/TONG_GIO_KHOAN*G59,0),0) -> 0 | L59: =IF(D59="Khoán",IF(TONG_GIO_KHOAN>0,QUY_KHAC/TONG_GIO_KHOAN*G59,0),0) -> 0 | M59: =IF(B59="",0,SUMIFS(KHOAN_KHAC!$F$5:$F$39,KHOAN_KHAC!$G$5:$G$39,B59)) -> 0 | N59: =IF(D59="Khoán",IF(TONG_GIO_KHOAN>0,QUY_CHEN/TONG_GIO_KHOAN*G59,0),0) -> 0 | O59: =IF(D59="Khoán",IF(TONG_GIO_KHOAN>0,-TONG_CONGNHAT/TONG_GIO_KHOAN*G59,0),0) -> 0 | P59: =IF(D59="Công nhật",H59*IFERROR(IF(INDEX(NV_DGCN,MATCH(B59,NV_MA,0))="",DG_CONGNHAT,INDEX(NV_DGCN,MATCH(B59,NV_MA,0))),DG_CONGNHAT),0) -> 0 | Q59: =IF(B59="","",IF(D59="Khoán",ROUNDDOWN(J59+K59+L59+M59+N59+O59,-3),P59+M59)) | R59: =IF(B59="","",ROUNDDOWN(TIENAN_CONG*H59,-3)) | S59: =IF(B59="","",Q59+R59)
A60: =IF(B60="","",55) | B60: =IF(BCC_KHOAN!B60="","",BCC_KHOAN!B60) | C60: =IF(B60="","",IFERROR(INDEX(NV_TEN,MATCH(B60,NV_MA,0)),"MÃ KHÔNG CÓ")) | D60: =IF(B60="","",IFERROR(INDEX(NV_HINHTHUC,MATCH(B60,NV_MA,0)),"")) | E60: =IF(D60="Khoán",IFERROR(INDEX(NV_HESO,MATCH(B60,NV_MA,0)),0),"") | F60: =IF(D60="Khoán",IFERROR(INDEX(HS_SX!$B$5:$B$30,MATCH(E60,HS_SX!$A$5:$A$30,0)),0),"") | G60: =IF(B60="","",IFERROR(INDEX(BCC_GIO,MATCH(B60,BCC_MA,0)),0)) | H60: =IF(B60="","",G60/GIO_CONG) | I60: =IF(D60="Khoán",IF(GIO_TB>0,G60/GIO_TB*KL_CHEBIEN,0),0) -> 0 | J60: =IF(D60="Khoán",F60*I60,0) -> 0 | K60: =IF(D60="Khoán",IF(TONG_GIO_KHOAN>0,QUY_HANGING/TONG_GIO_KHOAN*G60,0),0) -> 0 | L60: =IF(D60="Khoán",IF(TONG_GIO_KHOAN>0,QUY_KHAC/TONG_GIO_KHOAN*G60,0),0) -> 0 | M60: =IF(B60="",0,SUMIFS(KHOAN_KHAC!$F$5:$F$39,KHOAN_KHAC!$G$5:$G$39,B60)) -> 0 | N60: =IF(D60="Khoán",IF(TONG_GIO_KHOAN>0,QUY_CHEN/TONG_GIO_KHOAN*G60,0),0) -> 0 | O60: =IF(D60="Khoán",IF(TONG_GIO_KHOAN>0,-TONG_CONGNHAT/TONG_GIO_KHOAN*G60,0),0) -> 0 | P60: =IF(D60="Công nhật",H60*IFERROR(IF(INDEX(NV_DGCN,MATCH(B60,NV_MA,0))="",DG_CONGNHAT,INDEX(NV_DGCN,MATCH(B60,NV_MA,0))),DG_CONGNHAT),0) -> 0 | Q60: =IF(B60="","",IF(D60="Khoán",ROUNDDOWN(J60+K60+L60+M60+N60+O60,-3),P60+M60)) | R60: =IF(B60="","",ROUNDDOWN(TIENAN_CONG*H60,-3)) | S60: =IF(B60="","",Q60+R60)
A61: =IF(B61="","",56) | B61: =IF(BCC_KHOAN!B61="","",BCC_KHOAN!B61) | C61: =IF(B61="","",IFERROR(INDEX(NV_TEN,MATCH(B61,NV_MA,0)),"MÃ KHÔNG CÓ")) | D61: =IF(B61="","",IFERROR(INDEX(NV_HINHTHUC,MATCH(B61,NV_MA,0)),"")) | E61: =IF(D61="Khoán",IFERROR(INDEX(NV_HESO,MATCH(B61,NV_MA,0)),0),"") | F61: =IF(D61="Khoán",IFERROR(INDEX(HS_SX!$B$5:$B$30,MATCH(E61,HS_SX!$A$5:$A$30,0)),0),"") | G61: =IF(B61="","",IFERROR(INDEX(BCC_GIO,MATCH(B61,BCC_MA,0)),0)) | H61: =IF(B61="","",G61/GIO_CONG) | I61: =IF(D61="Khoán",IF(GIO_TB>0,G61/GIO_TB*KL_CHEBIEN,0),0) -> 0 | J61: =IF(D61="Khoán",F61*I61,0) -> 0 | K61: =IF(D61="Khoán",IF(TONG_GIO_KHOAN>0,QUY_HANGING/TONG_GIO_KHOAN*G61,0),0) -> 0 | L61: =IF(D61="Khoán",IF(TONG_GIO_KHOAN>0,QUY_KHAC/TONG_GIO_KHOAN*G61,0),0) -> 0 | M61: =IF(B61="",0,SUMIFS(KHOAN_KHAC!$F$5:$F$39,KHOAN_KHAC!$G$5:$G$39,B61)) -> 0 | N61: =IF(D61="Khoán",IF(TONG_GIO_KHOAN>0,QUY_CHEN/TONG_GIO_KHOAN*G61,0),0) -> 0 | O61: =IF(D61="Khoán",IF(TONG_GIO_KHOAN>0,-TONG_CONGNHAT/TONG_GIO_KHOAN*G61,0),0) -> 0 | P61: =IF(D61="Công nhật",H61*IFERROR(IF(INDEX(NV_DGCN,MATCH(B61,NV_MA,0))="",DG_CONGNHAT,INDEX(NV_DGCN,MATCH(B61,NV_MA,0))),DG_CONGNHAT),0) -> 0 | Q61: =IF(B61="","",IF(D61="Khoán",ROUNDDOWN(J61+K61+L61+M61+N61+O61,-3),P61+M61)) | R61: =IF(B61="","",ROUNDDOWN(TIENAN_CONG*H61,-3)) | S61: =IF(B61="","",Q61+R61)
A62: =IF(B62="","",57) | B62: =IF(BCC_KHOAN!B62="","",BCC_KHOAN!B62) | C62: =IF(B62="","",IFERROR(INDEX(NV_TEN,MATCH(B62,NV_MA,0)),"MÃ KHÔNG CÓ")) | D62: =IF(B62="","",IFERROR(INDEX(NV_HINHTHUC,MATCH(B62,NV_MA,0)),"")) | E62: =IF(D62="Khoán",IFERROR(INDEX(NV_HESO,MATCH(B62,NV_MA,0)),0),"") | F62: =IF(D62="Khoán",IFERROR(INDEX(HS_SX!$B$5:$B$30,MATCH(E62,HS_SX!$A$5:$A$30,0)),0),"") | G62: =IF(B62="","",IFERROR(INDEX(BCC_GIO,MATCH(B62,BCC_MA,0)),0)) | H62: =IF(B62="","",G62/GIO_CONG) | I62: =IF(D62="Khoán",IF(GIO_TB>0,G62/GIO_TB*KL_CHEBIEN,0),0) -> 0 | J62: =IF(D62="Khoán",F62*I62,0) -> 0 | K62: =IF(D62="Khoán",IF(TONG_GIO_KHOAN>0,QUY_HANGING/TONG_GIO_KHOAN*G62,0),0) -> 0 | L62: =IF(D62="Khoán",IF(TONG_GIO_KHOAN>0,QUY_KHAC/TONG_GIO_KHOAN*G62,0),0) -> 0 | M62: =IF(B62="",0,SUMIFS(KHOAN_KHAC!$F$5:$F$39,KHOAN_KHAC!$G$5:$G$39,B62)) -> 0 | N62: =IF(D62="Khoán",IF(TONG_GIO_KHOAN>0,QUY_CHEN/TONG_GIO_KHOAN*G62,0),0) -> 0 | O62: =IF(D62="Khoán",IF(TONG_GIO_KHOAN>0,-TONG_CONGNHAT/TONG_GIO_KHOAN*G62,0),0) -> 0 | P62: =IF(D62="Công nhật",H62*IFERROR(IF(INDEX(NV_DGCN,MATCH(B62,NV_MA,0))="",DG_CONGNHAT,INDEX(NV_DGCN,MATCH(B62,NV_MA,0))),DG_CONGNHAT),0) -> 0 | Q62: =IF(B62="","",IF(D62="Khoán",ROUNDDOWN(J62+K62+L62+M62+N62+O62,-3),P62+M62)) | R62: =IF(B62="","",ROUNDDOWN(TIENAN_CONG*H62,-3)) | S62: =IF(B62="","",Q62+R62)
A63: =IF(B63="","",58) | B63: =IF(BCC_KHOAN!B63="","",BCC_KHOAN!B63) | C63: =IF(B63="","",IFERROR(INDEX(NV_TEN,MATCH(B63,NV_MA,0)),"MÃ KHÔNG CÓ")) | D63: =IF(B63="","",IFERROR(INDEX(NV_HINHTHUC,MATCH(B63,NV_MA,0)),"")) | E63: =IF(D63="Khoán",IFERROR(INDEX(NV_HESO,MATCH(B63,NV_MA,0)),0),"") | F63: =IF(D63="Khoán",IFERROR(INDEX(HS_SX!$B$5:$B$30,MATCH(E63,HS_SX!$A$5:$A$30,0)),0),"") | G63: =IF(B63="","",IFERROR(INDEX(BCC_GIO,MATCH(B63,BCC_MA,0)),0)) | H63: =IF(B63="","",G63/GIO_CONG) | I63: =IF(D63="Khoán",IF(GIO_TB>0,G63/GIO_TB*KL_CHEBIEN,0),0) -> 0 | J63: =IF(D63="Khoán",F63*I63,0) -> 0 | K63: =IF(D63="Khoán",IF(TONG_GIO_KHOAN>0,QUY_HANGING/TONG_GIO_KHOAN*G63,0),0) -> 0 | L63: =IF(D63="Khoán",IF(TONG_GIO_KHOAN>0,QUY_KHAC/TONG_GIO_KHOAN*G63,0),0) -> 0 | M63: =IF(B63="",0,SUMIFS(KHOAN_KHAC!$F$5:$F$39,KHOAN_KHAC!$G$5:$G$39,B63)) -> 0 | N63: =IF(D63="Khoán",IF(TONG_GIO_KHOAN>0,QUY_CHEN/TONG_GIO_KHOAN*G63,0),0) -> 0 | O63: =IF(D63="Khoán",IF(TONG_GIO_KHOAN>0,-TONG_CONGNHAT/TONG_GIO_KHOAN*G63,0),0) -> 0 | P63: =IF(D63="Công nhật",H63*IFERROR(IF(INDEX(NV_DGCN,MATCH(B63,NV_MA,0))="",DG_CONGNHAT,INDEX(NV_DGCN,MATCH(B63,NV_MA,0))),DG_CONGNHAT),0) -> 0 | Q63: =IF(B63="","",IF(D63="Khoán",ROUNDDOWN(J63+K63+L63+M63+N63+O63,-3),P63+M63)) | R63: =IF(B63="","",ROUNDDOWN(TIENAN_CONG*H63,-3)) | S63: =IF(B63="","",Q63+R63)
A64: =IF(B64="","",59) | B64: =IF(BCC_KHOAN!B64="","",BCC_KHOAN!B64) | C64: =IF(B64="","",IFERROR(INDEX(NV_TEN,MATCH(B64,NV_MA,0)),"MÃ KHÔNG CÓ")) | D64: =IF(B64="","",IFERROR(INDEX(NV_HINHTHUC,MATCH(B64,NV_MA,0)),"")) | E64: =IF(D64="Khoán",IFERROR(INDEX(NV_HESO,MATCH(B64,NV_MA,0)),0),"") | F64: =IF(D64="Khoán",IFERROR(INDEX(HS_SX!$B$5:$B$30,MATCH(E64,HS_SX!$A$5:$A$30,0)),0),"") | G64: =IF(B64="","",IFERROR(INDEX(BCC_GIO,MATCH(B64,BCC_MA,0)),0)) | H64: =IF(B64="","",G64/GIO_CONG) | I64: =IF(D64="Khoán",IF(GIO_TB>0,G64/GIO_TB*KL_CHEBIEN,0),0) -> 0 | J64: =IF(D64="Khoán",F64*I64,0) -> 0 | K64: =IF(D64="Khoán",IF(TONG_GIO_KHOAN>0,QUY_HANGING/TONG_GIO_KHOAN*G64,0),0) -> 0 | L64: =IF(D64="Khoán",IF(TONG_GIO_KHOAN>0,QUY_KHAC/TONG_GIO_KHOAN*G64,0),0) -> 0 | M64: =IF(B64="",0,SUMIFS(KHOAN_KHAC!$F$5:$F$39,KHOAN_KHAC!$G$5:$G$39,B64)) -> 0 | N64: =IF(D64="Khoán",IF(TONG_GIO_KHOAN>0,QUY_CHEN/TONG_GIO_KHOAN*G64,0),0) -> 0 | O64: =IF(D64="Khoán",IF(TONG_GIO_KHOAN>0,-TONG_CONGNHAT/TONG_GIO_KHOAN*G64,0),0) -> 0 | P64: =IF(D64="Công nhật",H64*IFERROR(IF(INDEX(NV_DGCN,MATCH(B64,NV_MA,0))="",DG_CONGNHAT,INDEX(NV_DGCN,MATCH(B64,NV_MA,0))),DG_CONGNHAT),0) -> 0 | Q64: =IF(B64="","",IF(D64="Khoán",ROUNDDOWN(J64+K64+L64+M64+N64+O64,-3),P64+M64)) | R64: =IF(B64="","",ROUNDDOWN(TIENAN_CONG*H64,-3)) | S64: =IF(B64="","",Q64+R64)
A65: =IF(B65="","",60) | B65: =IF(BCC_KHOAN!B65="","",BCC_KHOAN!B65) | C65: =IF(B65="","",IFERROR(INDEX(NV_TEN,MATCH(B65,NV_MA,0)),"MÃ KHÔNG CÓ")) | D65: =IF(B65="","",IFERROR(INDEX(NV_HINHTHUC,MATCH(B65,NV_MA,0)),"")) | E65: =IF(D65="Khoán",IFERROR(INDEX(NV_HESO,MATCH(B65,NV_MA,0)),0),"") | F65: =IF(D65="Khoán",IFERROR(INDEX(HS_SX!$B$5:$B$30,MATCH(E65,HS_SX!$A$5:$A$30,0)),0),"") | G65: =IF(B65="","",IFERROR(INDEX(BCC_GIO,MATCH(B65,BCC_MA,0)),0)) | H65: =IF(B65="","",G65/GIO_CONG) | I65: =IF(D65="Khoán",IF(GIO_TB>0,G65/GIO_TB*KL_CHEBIEN,0),0) -> 0 | J65: =IF(D65="Khoán",F65*I65,0) -> 0 | K65: =IF(D65="Khoán",IF(TONG_GIO_KHOAN>0,QUY_HANGING/TONG_GIO_KHOAN*G65,0),0) -> 0 | L65: =IF(D65="Khoán",IF(TONG_GIO_KHOAN>0,QUY_KHAC/TONG_GIO_KHOAN*G65,0),0) -> 0 | M65: =IF(B65="",0,SUMIFS(KHOAN_KHAC!$F$5:$F$39,KHOAN_KHAC!$G$5:$G$39,B65)) -> 0 | N65: =IF(D65="Khoán",IF(TONG_GIO_KHOAN>0,QUY_CHEN/TONG_GIO_KHOAN*G65,0),0) -> 0 | O65: =IF(D65="Khoán",IF(TONG_GIO_KHOAN>0,-TONG_CONGNHAT/TONG_GIO_KHOAN*G65,0),0) -> 0 | P65: =IF(D65="Công nhật",H65*IFERROR(IF(INDEX(NV_DGCN,MATCH(B65,NV_MA,0))="",DG_CONGNHAT,INDEX(NV_DGCN,MATCH(B65,NV_MA,0))),DG_CONGNHAT),0) -> 0 | Q65: =IF(B65="","",IF(D65="Khoán",ROUNDDOWN(J65+K65+L65+M65+N65+O65,-3),P65+M65)) | R65: =IF(B65="","",ROUNDDOWN(TIENAN_CONG*H65,-3)) | S65: =IF(B65="","",Q65+R65)
A66: =IF(B66="","",61) | B66: =IF(BCC_KHOAN!B66="","",BCC_KHOAN!B66) | C66: =IF(B66="","",IFERROR(INDEX(NV_TEN,MATCH(B66,NV_MA,0)),"MÃ KHÔNG CÓ")) | D66: =IF(B66="","",IFERROR(INDEX(NV_HINHTHUC,MATCH(B66,NV_MA,0)),"")) | E66: =IF(D66="Khoán",IFERROR(INDEX(NV_HESO,MATCH(B66,NV_MA,0)),0),"") | F66: =IF(D66="Khoán",IFERROR(INDEX(HS_SX!$B$5:$B$30,MATCH(E66,HS_SX!$A$5:$A$30,0)),0),"") | G66: =IF(B66="","",IFERROR(INDEX(BCC_GIO,MATCH(B66,BCC_MA,0)),0)) | H66: =IF(B66="","",G66/GIO_CONG) | I66: =IF(D66="Khoán",IF(GIO_TB>0,G66/GIO_TB*KL_CHEBIEN,0),0) -> 0 | J66: =IF(D66="Khoán",F66*I66,0) -> 0 | K66: =IF(D66="Khoán",IF(TONG_GIO_KHOAN>0,QUY_HANGING/TONG_GIO_KHOAN*G66,0),0) -> 0 | L66: =IF(D66="Khoán",IF(TONG_GIO_KHOAN>0,QUY_KHAC/TONG_GIO_KHOAN*G66,0),0) -> 0 | M66: =IF(B66="",0,SUMIFS(KHOAN_KHAC!$F$5:$F$39,KHOAN_KHAC!$G$5:$G$39,B66)) -> 0 | N66: =IF(D66="Khoán",IF(TONG_GIO_KHOAN>0,QUY_CHEN/TONG_GIO_KHOAN*G66,0),0) -> 0 | O66: =IF(D66="Khoán",IF(TONG_GIO_KHOAN>0,-TONG_CONGNHAT/TONG_GIO_KHOAN*G66,0),0) -> 0 | P66: =IF(D66="Công nhật",H66*IFERROR(IF(INDEX(NV_DGCN,MATCH(B66,NV_MA,0))="",DG_CONGNHAT,INDEX(NV_DGCN,MATCH(B66,NV_MA,0))),DG_CONGNHAT),0) -> 0 | Q66: =IF(B66="","",IF(D66="Khoán",ROUNDDOWN(J66+K66+L66+M66+N66+O66,-3),P66+M66)) | R66: =IF(B66="","",ROUNDDOWN(TIENAN_CONG*H66,-3)) | S66: =IF(B66="","",Q66+R66)
A67: =IF(B67="","",62) | B67: =IF(BCC_KHOAN!B67="","",BCC_KHOAN!B67) | C67: =IF(B67="","",IFERROR(INDEX(NV_TEN,MATCH(B67,NV_MA,0)),"MÃ KHÔNG CÓ")) | D67: =IF(B67="","",IFERROR(INDEX(NV_HINHTHUC,MATCH(B67,NV_MA,0)),"")) | E67: =IF(D67="Khoán",IFERROR(INDEX(NV_HESO,MATCH(B67,NV_MA,0)),0),"") | F67: =IF(D67="Khoán",IFERROR(INDEX(HS_SX!$B$5:$B$30,MATCH(E67,HS_SX!$A$5:$A$30,0)),0),"") | G67: =IF(B67="","",IFERROR(INDEX(BCC_GIO,MATCH(B67,BCC_MA,0)),0)) | H67: =IF(B67="","",G67/GIO_CONG) | I67: =IF(D67="Khoán",IF(GIO_TB>0,G67/GIO_TB*KL_CHEBIEN,0),0) -> 0 | J67: =IF(D67="Khoán",F67*I67,0) -> 0 | K67: =IF(D67="Khoán",IF(TONG_GIO_KHOAN>0,QUY_HANGING/TONG_GIO_KHOAN*G67,0),0) -> 0 | L67: =IF(D67="Khoán",IF(TONG_GIO_KHOAN>0,QUY_KHAC/TONG_GIO_KHOAN*G67,0),0) -> 0 | M67: =IF(B67="",0,SUMIFS(KHOAN_KHAC!$F$5:$F$39,KHOAN_KHAC!$G$5:$G$39,B67)) -> 0 | N67: =IF(D67="Khoán",IF(TONG_GIO_KHOAN>0,QUY_CHEN/TONG_GIO_KHOAN*G67,0),0) -> 0 | O67: =IF(D67="Khoán",IF(TONG_GIO_KHOAN>0,-TONG_CONGNHAT/TONG_GIO_KHOAN*G67,0),0) -> 0 | P67: =IF(D67="Công nhật",H67*IFERROR(IF(INDEX(NV_DGCN,MATCH(B67,NV_MA,0))="",DG_CONGNHAT,INDEX(NV_DGCN,MATCH(B67,NV_MA,0))),DG_CONGNHAT),0) -> 0 | Q67: =IF(B67="","",IF(D67="Khoán",ROUNDDOWN(J67+K67+L67+M67+N67+O67,-3),P67+M67)) | R67: =IF(B67="","",ROUNDDOWN(TIENAN_CONG*H67,-3)) | S67: =IF(B67="","",Q67+R67)
A68: =IF(B68="","",63) | B68: =IF(BCC_KHOAN!B68="","",BCC_KHOAN!B68) | C68: =IF(B68="","",IFERROR(INDEX(NV_TEN,MATCH(B68,NV_MA,0)),"MÃ KHÔNG CÓ")) | D68: =IF(B68="","",IFERROR(INDEX(NV_HINHTHUC,MATCH(B68,NV_MA,0)),"")) | E68: =IF(D68="Khoán",IFERROR(INDEX(NV_HESO,MATCH(B68,NV_MA,0)),0),"") | F68: =IF(D68="Khoán",IFERROR(INDEX(HS_SX!$B$5:$B$30,MATCH(E68,HS_SX!$A$5:$A$30,0)),0),"") | G68: =IF(B68="","",IFERROR(INDEX(BCC_GIO,MATCH(B68,BCC_MA,0)),0)) | H68: =IF(B68="","",G68/GIO_CONG) | I68: =IF(D68="Khoán",IF(GIO_TB>0,G68/GIO_TB*KL_CHEBIEN,0),0) -> 0 | J68: =IF(D68="Khoán",F68*I68,0) -> 0 | K68: =IF(D68="Khoán",IF(TONG_GIO_KHOAN>0,QUY_HANGING/TONG_GIO_KHOAN*G68,0),0) -> 0 | L68: =IF(D68="Khoán",IF(TONG_GIO_KHOAN>0,QUY_KHAC/TONG_GIO_KHOAN*G68,0),0) -> 0 | M68: =IF(B68="",0,SUMIFS(KHOAN_KHAC!$F$5:$F$39,KHOAN_KHAC!$G$5:$G$39,B68)) -> 0 | N68: =IF(D68="Khoán",IF(TONG_GIO_KHOAN>0,QUY_CHEN/TONG_GIO_KHOAN*G68,0),0) -> 0 | O68: =IF(D68="Khoán",IF(TONG_GIO_KHOAN>0,-TONG_CONGNHAT/TONG_GIO_KHOAN*G68,0),0) -> 0 | P68: =IF(D68="Công nhật",H68*IFERROR(IF(INDEX(NV_DGCN,MATCH(B68,NV_MA,0))="",DG_CONGNHAT,INDEX(NV_DGCN,MATCH(B68,NV_MA,0))),DG_CONGNHAT),0) -> 0 | Q68: =IF(B68="","",IF(D68="Khoán",ROUNDDOWN(J68+K68+L68+M68+N68+O68,-3),P68+M68)) | R68: =IF(B68="","",ROUNDDOWN(TIENAN_CONG*H68,-3)) | S68: =IF(B68="","",Q68+R68)
A69: =IF(B69="","",64) | B69: =IF(BCC_KHOAN!B69="","",BCC_KHOAN!B69) | C69: =IF(B69="","",IFERROR(INDEX(NV_TEN,MATCH(B69,NV_MA,0)),"MÃ KHÔNG CÓ")) | D69: =IF(B69="","",IFERROR(INDEX(NV_HINHTHUC,MATCH(B69,NV_MA,0)),"")) | E69: =IF(D69="Khoán",IFERROR(INDEX(NV_HESO,MATCH(B69,NV_MA,0)),0),"") | F69: =IF(D69="Khoán",IFERROR(INDEX(HS_SX!$B$5:$B$30,MATCH(E69,HS_SX!$A$5:$A$30,0)),0),"") | G69: =IF(B69="","",IFERROR(INDEX(BCC_GIO,MATCH(B69,BCC_MA,0)),0)) | H69: =IF(B69="","",G69/GIO_CONG) | I69: =IF(D69="Khoán",IF(GIO_TB>0,G69/GIO_TB*KL_CHEBIEN,0),0) -> 0 | J69: =IF(D69="Khoán",F69*I69,0) -> 0 | K69: =IF(D69="Khoán",IF(TONG_GIO_KHOAN>0,QUY_HANGING/TONG_GIO_KHOAN*G69,0),0) -> 0 | L69: =IF(D69="Khoán",IF(TONG_GIO_KHOAN>0,QUY_KHAC/TONG_GIO_KHOAN*G69,0),0) -> 0 | M69: =IF(B69="",0,SUMIFS(KHOAN_KHAC!$F$5:$F$39,KHOAN_KHAC!$G$5:$G$39,B69)) -> 0 | N69: =IF(D69="Khoán",IF(TONG_GIO_KHOAN>0,QUY_CHEN/TONG_GIO_KHOAN*G69,0),0) -> 0 | O69: =IF(D69="Khoán",IF(TONG_GIO_KHOAN>0,-TONG_CONGNHAT/TONG_GIO_KHOAN*G69,0),0) -> 0 | P69: =IF(D69="Công nhật",H69*IFERROR(IF(INDEX(NV_DGCN,MATCH(B69,NV_MA,0))="",DG_CONGNHAT,INDEX(NV_DGCN,MATCH(B69,NV_MA,0))),DG_CONGNHAT),0) -> 0 | Q69: =IF(B69="","",IF(D69="Khoán",ROUNDDOWN(J69+K69+L69+M69+N69+O69,-3),P69+M69)) | R69: =IF(B69="","",ROUNDDOWN(TIENAN_CONG*H69,-3)) | S69: =IF(B69="","",Q69+R69)
A70: =IF(B70="","",65) | B70: =IF(BCC_KHOAN!B70="","",BCC_KHOAN!B70) | C70: =IF(B70="","",IFERROR(INDEX(NV_TEN,MATCH(B70,NV_MA,0)),"MÃ KHÔNG CÓ")) | D70: =IF(B70="","",IFERROR(INDEX(NV_HINHTHUC,MATCH(B70,NV_MA,0)),"")) | E70: =IF(D70="Khoán",IFERROR(INDEX(NV_HESO,MATCH(B70,NV_MA,0)),0),"") | F70: =IF(D70="Khoán",IFERROR(INDEX(HS_SX!$B$5:$B$30,MATCH(E70,HS_SX!$A$5:$A$30,0)),0),"") | G70: =IF(B70="","",IFERROR(INDEX(BCC_GIO,MATCH(B70,BCC_MA,0)),0)) | H70: =IF(B70="","",G70/GIO_CONG) | I70: =IF(D70="Khoán",IF(GIO_TB>0,G70/GIO_TB*KL_CHEBIEN,0),0) -> 0 | J70: =IF(D70="Khoán",F70*I70,0) -> 0 | K70: =IF(D70="Khoán",IF(TONG_GIO_KHOAN>0,QUY_HANGING/TONG_GIO_KHOAN*G70,0),0) -> 0 | L70: =IF(D70="Khoán",IF(TONG_GIO_KHOAN>0,QUY_KHAC/TONG_GIO_KHOAN*G70,0),0) -> 0 | M70: =IF(B70="",0,SUMIFS(KHOAN_KHAC!$F$5:$F$39,KHOAN_KHAC!$G$5:$G$39,B70)) -> 0 | N70: =IF(D70="Khoán",IF(TONG_GIO_KHOAN>0,QUY_CHEN/TONG_GIO_KHOAN*G70,0),0) -> 0 | O70: =IF(D70="Khoán",IF(TONG_GIO_KHOAN>0,-TONG_CONGNHAT/TONG_GIO_KHOAN*G70,0),0) -> 0 | P70: =IF(D70="Công nhật",H70*IFERROR(IF(INDEX(NV_DGCN,MATCH(B70,NV_MA,0))="",DG_CONGNHAT,INDEX(NV_DGCN,MATCH(B70,NV_MA,0))),DG_CONGNHAT),0) -> 0 | Q70: =IF(B70="","",IF(D70="Khoán",ROUNDDOWN(J70+K70+L70+M70+N70+O70,-3),P70+M70)) | R70: =IF(B70="","",ROUNDDOWN(TIENAN_CONG*H70,-3)) | S70: =IF(B70="","",Q70+R70)
A71: =IF(B71="","",66) | B71: =IF(BCC_KHOAN!B71="","",BCC_KHOAN!B71) | C71: =IF(B71="","",IFERROR(INDEX(NV_TEN,MATCH(B71,NV_MA,0)),"MÃ KHÔNG CÓ")) | D71: =IF(B71="","",IFERROR(INDEX(NV_HINHTHUC,MATCH(B71,NV_MA,0)),"")) | E71: =IF(D71="Khoán",IFERROR(INDEX(NV_HESO,MATCH(B71,NV_MA,0)),0),"") | F71: =IF(D71="Khoán",IFERROR(INDEX(HS_SX!$B$5:$B$30,MATCH(E71,HS_SX!$A$5:$A$30,0)),0),"") | G71: =IF(B71="","",IFERROR(INDEX(BCC_GIO,MATCH(B71,BCC_MA,0)),0)) | H71: =IF(B71="","",G71/GIO_CONG) | I71: =IF(D71="Khoán",IF(GIO_TB>0,G71/GIO_TB*KL_CHEBIEN,0),0) -> 0 | J71: =IF(D71="Khoán",F71*I71,0) -> 0 | K71: =IF(D71="Khoán",IF(TONG_GIO_KHOAN>0,QUY_HANGING/TONG_GIO_KHOAN*G71,0),0) -> 0 | L71: =IF(D71="Khoán",IF(TONG_GIO_KHOAN>0,QUY_KHAC/TONG_GIO_KHOAN*G71,0),0) -> 0 | M71: =IF(B71="",0,SUMIFS(KHOAN_KHAC!$F$5:$F$39,KHOAN_KHAC!$G$5:$G$39,B71)) -> 0 | N71: =IF(D71="Khoán",IF(TONG_GIO_KHOAN>0,QUY_CHEN/TONG_GIO_KHOAN*G71,0),0) -> 0 | O71: =IF(D71="Khoán",IF(TONG_GIO_KHOAN>0,-TONG_CONGNHAT/TONG_GIO_KHOAN*G71,0),0) -> 0 | P71: =IF(D71="Công nhật",H71*IFERROR(IF(INDEX(NV_DGCN,MATCH(B71,NV_MA,0))="",DG_CONGNHAT,INDEX(NV_DGCN,MATCH(B71,NV_MA,0))),DG_CONGNHAT),0) -> 0 | Q71: =IF(B71="","",IF(D71="Khoán",ROUNDDOWN(J71+K71+L71+M71+N71+O71,-3),P71+M71)) | R71: =IF(B71="","",ROUNDDOWN(TIENAN_CONG*H71,-3)) | S71: =IF(B71="","",Q71+R71)
A72: =IF(B72="","",67) | B72: =IF(BCC_KHOAN!B72="","",BCC_KHOAN!B72) | C72: =IF(B72="","",IFERROR(INDEX(NV_TEN,MATCH(B72,NV_MA,0)),"MÃ KHÔNG CÓ")) | D72: =IF(B72="","",IFERROR(INDEX(NV_HINHTHUC,MATCH(B72,NV_MA,0)),"")) | E72: =IF(D72="Khoán",IFERROR(INDEX(NV_HESO,MATCH(B72,NV_MA,0)),0),"") | F72: =IF(D72="Khoán",IFERROR(INDEX(HS_SX!$B$5:$B$30,MATCH(E72,HS_SX!$A$5:$A$30,0)),0),"") | G72: =IF(B72="","",IFERROR(INDEX(BCC_GIO,MATCH(B72,BCC_MA,0)),0)) | H72: =IF(B72="","",G72/GIO_CONG) | I72: =IF(D72="Khoán",IF(GIO_TB>0,G72/GIO_TB*KL_CHEBIEN,0),0) -> 0 | J72: =IF(D72="Khoán",F72*I72,0) -> 0 | K72: =IF(D72="Khoán",IF(TONG_GIO_KHOAN>0,QUY_HANGING/TONG_GIO_KHOAN*G72,0),0) -> 0 | L72: =IF(D72="Khoán",IF(TONG_GIO_KHOAN>0,QUY_KHAC/TONG_GIO_KHOAN*G72,0),0) -> 0 | M72: =IF(B72="",0,SUMIFS(KHOAN_KHAC!$F$5:$F$39,KHOAN_KHAC!$G$5:$G$39,B72)) -> 0 | N72: =IF(D72="Khoán",IF(TONG_GIO_KHOAN>0,QUY_CHEN/TONG_GIO_KHOAN*G72,0),0) -> 0 | O72: =IF(D72="Khoán",IF(TONG_GIO_KHOAN>0,-TONG_CONGNHAT/TONG_GIO_KHOAN*G72,0),0) -> 0 | P72: =IF(D72="Công nhật",H72*IFERROR(IF(INDEX(NV_DGCN,MATCH(B72,NV_MA,0))="",DG_CONGNHAT,INDEX(NV_DGCN,MATCH(B72,NV_MA,0))),DG_CONGNHAT),0) -> 0 | Q72: =IF(B72="","",IF(D72="Khoán",ROUNDDOWN(J72+K72+L72+M72+N72+O72,-3),P72+M72)) | R72: =IF(B72="","",ROUNDDOWN(TIENAN_CONG*H72,-3)) | S72: =IF(B72="","",Q72+R72)
A73: =IF(B73="","",68) | B73: =IF(BCC_KHOAN!B73="","",BCC_KHOAN!B73) | C73: =IF(B73="","",IFERROR(INDEX(NV_TEN,MATCH(B73,NV_MA,0)),"MÃ KHÔNG CÓ")) | D73: =IF(B73="","",IFERROR(INDEX(NV_HINHTHUC,MATCH(B73,NV_MA,0)),"")) | E73: =IF(D73="Khoán",IFERROR(INDEX(NV_HESO,MATCH(B73,NV_MA,0)),0),"") | F73: =IF(D73="Khoán",IFERROR(INDEX(HS_SX!$B$5:$B$30,MATCH(E73,HS_SX!$A$5:$A$30,0)),0),"") | G73: =IF(B73="","",IFERROR(INDEX(BCC_GIO,MATCH(B73,BCC_MA,0)),0)) | H73: =IF(B73="","",G73/GIO_CONG) | I73: =IF(D73="Khoán",IF(GIO_TB>0,G73/GIO_TB*KL_CHEBIEN,0),0) -> 0 | J73: =IF(D73="Khoán",F73*I73,0) -> 0 | K73: =IF(D73="Khoán",IF(TONG_GIO_KHOAN>0,QUY_HANGING/TONG_GIO_KHOAN*G73,0),0) -> 0 | L73: =IF(D73="Khoán",IF(TONG_GIO_KHOAN>0,QUY_KHAC/TONG_GIO_KHOAN*G73,0),0) -> 0 | M73: =IF(B73="",0,SUMIFS(KHOAN_KHAC!$F$5:$F$39,KHOAN_KHAC!$G$5:$G$39,B73)) -> 0 | N73: =IF(D73="Khoán",IF(TONG_GIO_KHOAN>0,QUY_CHEN/TONG_GIO_KHOAN*G73,0),0) -> 0 | O73: =IF(D73="Khoán",IF(TONG_GIO_KHOAN>0,-TONG_CONGNHAT/TONG_GIO_KHOAN*G73,0),0) -> 0 | P73: =IF(D73="Công nhật",H73*IFERROR(IF(INDEX(NV_DGCN,MATCH(B73,NV_MA,0))="",DG_CONGNHAT,INDEX(NV_DGCN,MATCH(B73,NV_MA,0))),DG_CONGNHAT),0) -> 0 | Q73: =IF(B73="","",IF(D73="Khoán",ROUNDDOWN(J73+K73+L73+M73+N73+O73,-3),P73+M73)) | R73: =IF(B73="","",ROUNDDOWN(TIENAN_CONG*H73,-3)) | S73: =IF(B73="","",Q73+R73)
A74: =IF(B74="","",69) | B74: =IF(BCC_KHOAN!B74="","",BCC_KHOAN!B74) | C74: =IF(B74="","",IFERROR(INDEX(NV_TEN,MATCH(B74,NV_MA,0)),"MÃ KHÔNG CÓ")) | D74: =IF(B74="","",IFERROR(INDEX(NV_HINHTHUC,MATCH(B74,NV_MA,0)),"")) | E74: =IF(D74="Khoán",IFERROR(INDEX(NV_HESO,MATCH(B74,NV_MA,0)),0),"") | F74: =IF(D74="Khoán",IFERROR(INDEX(HS_SX!$B$5:$B$30,MATCH(E74,HS_SX!$A$5:$A$30,0)),0),"") | G74: =IF(B74="","",IFERROR(INDEX(BCC_GIO,MATCH(B74,BCC_MA,0)),0)) | H74: =IF(B74="","",G74/GIO_CONG) | I74: =IF(D74="Khoán",IF(GIO_TB>0,G74/GIO_TB*KL_CHEBIEN,0),0) -> 0 | J74: =IF(D74="Khoán",F74*I74,0) -> 0 | K74: =IF(D74="Khoán",IF(TONG_GIO_KHOAN>0,QUY_HANGING/TONG_GIO_KHOAN*G74,0),0) -> 0 | L74: =IF(D74="Khoán",IF(TONG_GIO_KHOAN>0,QUY_KHAC/TONG_GIO_KHOAN*G74,0),0) -> 0 | M74: =IF(B74="",0,SUMIFS(KHOAN_KHAC!$F$5:$F$39,KHOAN_KHAC!$G$5:$G$39,B74)) -> 0 | N74: =IF(D74="Khoán",IF(TONG_GIO_KHOAN>0,QUY_CHEN/TONG_GIO_KHOAN*G74,0),0) -> 0 | O74: =IF(D74="Khoán",IF(TONG_GIO_KHOAN>0,-TONG_CONGNHAT/TONG_GIO_KHOAN*G74,0),0) -> 0 | P74: =IF(D74="Công nhật",H74*IFERROR(IF(INDEX(NV_DGCN,MATCH(B74,NV_MA,0))="",DG_CONGNHAT,INDEX(NV_DGCN,MATCH(B74,NV_MA,0))),DG_CONGNHAT),0) -> 0 | Q74: =IF(B74="","",IF(D74="Khoán",ROUNDDOWN(J74+K74+L74+M74+N74+O74,-3),P74+M74)) | R74: =IF(B74="","",ROUNDDOWN(TIENAN_CONG*H74,-3)) | S74: =IF(B74="","",Q74+R74)
A75: =IF(B75="","",70) | B75: =IF(BCC_KHOAN!B75="","",BCC_KHOAN!B75) | C75: =IF(B75="","",IFERROR(INDEX(NV_TEN,MATCH(B75,NV_MA,0)),"MÃ KHÔNG CÓ")) | D75: =IF(B75="","",IFERROR(INDEX(NV_HINHTHUC,MATCH(B75,NV_MA,0)),"")) | E75: =IF(D75="Khoán",IFERROR(INDEX(NV_HESO,MATCH(B75,NV_MA,0)),0),"") | F75: =IF(D75="Khoán",IFERROR(INDEX(HS_SX!$B$5:$B$30,MATCH(E75,HS_SX!$A$5:$A$30,0)),0),"") | G75: =IF(B75="","",IFERROR(INDEX(BCC_GIO,MATCH(B75,BCC_MA,0)),0)) | H75: =IF(B75="","",G75/GIO_CONG) | I75: =IF(D75="Khoán",IF(GIO_TB>0,G75/GIO_TB*KL_CHEBIEN,0),0) -> 0 | J75: =IF(D75="Khoán",F75*I75,0) -> 0 | K75: =IF(D75="Khoán",IF(TONG_GIO_KHOAN>0,QUY_HANGING/TONG_GIO_KHOAN*G75,0),0) -> 0 | L75: =IF(D75="Khoán",IF(TONG_GIO_KHOAN>0,QUY_KHAC/TONG_GIO_KHOAN*G75,0),0) -> 0 | M75: =IF(B75="",0,SUMIFS(KHOAN_KHAC!$F$5:$F$39,KHOAN_KHAC!$G$5:$G$39,B75)) -> 0 | N75: =IF(D75="Khoán",IF(TONG_GIO_KHOAN>0,QUY_CHEN/TONG_GIO_KHOAN*G75,0),0) -> 0 | O75: =IF(D75="Khoán",IF(TONG_GIO_KHOAN>0,-TONG_CONGNHAT/TONG_GIO_KHOAN*G75,0),0) -> 0 | P75: =IF(D75="Công nhật",H75*IFERROR(IF(INDEX(NV_DGCN,MATCH(B75,NV_MA,0))="",DG_CONGNHAT,INDEX(NV_DGCN,MATCH(B75,NV_MA,0))),DG_CONGNHAT),0) -> 0 | Q75: =IF(B75="","",IF(D75="Khoán",ROUNDDOWN(J75+K75+L75+M75+N75+O75,-3),P75+M75)) | R75: =IF(B75="","",ROUNDDOWN(TIENAN_CONG*H75,-3)) | S75: =IF(B75="","",Q75+R75)
A76: =IF(B76="","",71) | B76: =IF(BCC_KHOAN!B76="","",BCC_KHOAN!B76) | C76: =IF(B76="","",IFERROR(INDEX(NV_TEN,MATCH(B76,NV_MA,0)),"MÃ KHÔNG CÓ")) | D76: =IF(B76="","",IFERROR(INDEX(NV_HINHTHUC,MATCH(B76,NV_MA,0)),"")) | E76: =IF(D76="Khoán",IFERROR(INDEX(NV_HESO,MATCH(B76,NV_MA,0)),0),"") | F76: =IF(D76="Khoán",IFERROR(INDEX(HS_SX!$B$5:$B$30,MATCH(E76,HS_SX!$A$5:$A$30,0)),0),"") | G76: =IF(B76="","",IFERROR(INDEX(BCC_GIO,MATCH(B76,BCC_MA,0)),0)) | H76: =IF(B76="","",G76/GIO_CONG) | I76: =IF(D76="Khoán",IF(GIO_TB>0,G76/GIO_TB*KL_CHEBIEN,0),0) -> 0 | J76: =IF(D76="Khoán",F76*I76,0) -> 0 | K76: =IF(D76="Khoán",IF(TONG_GIO_KHOAN>0,QUY_HANGING/TONG_GIO_KHOAN*G76,0),0) -> 0 | L76: =IF(D76="Khoán",IF(TONG_GIO_KHOAN>0,QUY_KHAC/TONG_GIO_KHOAN*G76,0),0) -> 0 | M76: =IF(B76="",0,SUMIFS(KHOAN_KHAC!$F$5:$F$39,KHOAN_KHAC!$G$5:$G$39,B76)) -> 0 | N76: =IF(D76="Khoán",IF(TONG_GIO_KHOAN>0,QUY_CHEN/TONG_GIO_KHOAN*G76,0),0) -> 0 | O76: =IF(D76="Khoán",IF(TONG_GIO_KHOAN>0,-TONG_CONGNHAT/TONG_GIO_KHOAN*G76,0),0) -> 0 | P76: =IF(D76="Công nhật",H76*IFERROR(IF(INDEX(NV_DGCN,MATCH(B76,NV_MA,0))="",DG_CONGNHAT,INDEX(NV_DGCN,MATCH(B76,NV_MA,0))),DG_CONGNHAT),0) -> 0 | Q76: =IF(B76="","",IF(D76="Khoán",ROUNDDOWN(J76+K76+L76+M76+N76+O76,-3),P76+M76)) | R76: =IF(B76="","",ROUNDDOWN(TIENAN_CONG*H76,-3)) | S76: =IF(B76="","",Q76+R76)
A77: =IF(B77="","",72) | B77: =IF(BCC_KHOAN!B77="","",BCC_KHOAN!B77) | C77: =IF(B77="","",IFERROR(INDEX(NV_TEN,MATCH(B77,NV_MA,0)),"MÃ KHÔNG CÓ")) | D77: =IF(B77="","",IFERROR(INDEX(NV_HINHTHUC,MATCH(B77,NV_MA,0)),"")) | E77: =IF(D77="Khoán",IFERROR(INDEX(NV_HESO,MATCH(B77,NV_MA,0)),0),"") | F77: =IF(D77="Khoán",IFERROR(INDEX(HS_SX!$B$5:$B$30,MATCH(E77,HS_SX!$A$5:$A$30,0)),0),"") | G77: =IF(B77="","",IFERROR(INDEX(BCC_GIO,MATCH(B77,BCC_MA,0)),0)) | H77: =IF(B77="","",G77/GIO_CONG) | I77: =IF(D77="Khoán",IF(GIO_TB>0,G77/GIO_TB*KL_CHEBIEN,0),0) -> 0 | J77: =IF(D77="Khoán",F77*I77,0) -> 0 | K77: =IF(D77="Khoán",IF(TONG_GIO_KHOAN>0,QUY_HANGING/TONG_GIO_KHOAN*G77,0),0) -> 0 | L77: =IF(D77="Khoán",IF(TONG_GIO_KHOAN>0,QUY_KHAC/TONG_GIO_KHOAN*G77,0),0) -> 0 | M77: =IF(B77="",0,SUMIFS(KHOAN_KHAC!$F$5:$F$39,KHOAN_KHAC!$G$5:$G$39,B77)) -> 0 | N77: =IF(D77="Khoán",IF(TONG_GIO_KHOAN>0,QUY_CHEN/TONG_GIO_KHOAN*G77,0),0) -> 0 | O77: =IF(D77="Khoán",IF(TONG_GIO_KHOAN>0,-TONG_CONGNHAT/TONG_GIO_KHOAN*G77,0),0) -> 0 | P77: =IF(D77="Công nhật",H77*IFERROR(IF(INDEX(NV_DGCN,MATCH(B77,NV_MA,0))="",DG_CONGNHAT,INDEX(NV_DGCN,MATCH(B77,NV_MA,0))),DG_CONGNHAT),0) -> 0 | Q77: =IF(B77="","",IF(D77="Khoán",ROUNDDOWN(J77+K77+L77+M77+N77+O77,-3),P77+M77)) | R77: =IF(B77="","",ROUNDDOWN(TIENAN_CONG*H77,-3)) | S77: =IF(B77="","",Q77+R77)
A78: =IF(B78="","",73) | B78: =IF(BCC_KHOAN!B78="","",BCC_KHOAN!B78) | C78: =IF(B78="","",IFERROR(INDEX(NV_TEN,MATCH(B78,NV_MA,0)),"MÃ KHÔNG CÓ")) | D78: =IF(B78="","",IFERROR(INDEX(NV_HINHTHUC,MATCH(B78,NV_MA,0)),"")) | E78: =IF(D78="Khoán",IFERROR(INDEX(NV_HESO,MATCH(B78,NV_MA,0)),0),"") | F78: =IF(D78="Khoán",IFERROR(INDEX(HS_SX!$B$5:$B$30,MATCH(E78,HS_SX!$A$5:$A$30,0)),0),"") | G78: =IF(B78="","",IFERROR(INDEX(BCC_GIO,MATCH(B78,BCC_MA,0)),0)) | H78: =IF(B78="","",G78/GIO_CONG) | I78: =IF(D78="Khoán",IF(GIO_TB>0,G78/GIO_TB*KL_CHEBIEN,0),0) -> 0 | J78: =IF(D78="Khoán",F78*I78,0) -> 0 | K78: =IF(D78="Khoán",IF(TONG_GIO_KHOAN>0,QUY_HANGING/TONG_GIO_KHOAN*G78,0),0) -> 0 | L78: =IF(D78="Khoán",IF(TONG_GIO_KHOAN>0,QUY_KHAC/TONG_GIO_KHOAN*G78,0),0) -> 0 | M78: =IF(B78="",0,SUMIFS(KHOAN_KHAC!$F$5:$F$39,KHOAN_KHAC!$G$5:$G$39,B78)) -> 0 | N78: =IF(D78="Khoán",IF(TONG_GIO_KHOAN>0,QUY_CHEN/TONG_GIO_KHOAN*G78,0),0) -> 0 | O78: =IF(D78="Khoán",IF(TONG_GIO_KHOAN>0,-TONG_CONGNHAT/TONG_GIO_KHOAN*G78,0),0) -> 0 | P78: =IF(D78="Công nhật",H78*IFERROR(IF(INDEX(NV_DGCN,MATCH(B78,NV_MA,0))="",DG_CONGNHAT,INDEX(NV_DGCN,MATCH(B78,NV_MA,0))),DG_CONGNHAT),0) -> 0 | Q78: =IF(B78="","",IF(D78="Khoán",ROUNDDOWN(J78+K78+L78+M78+N78+O78,-3),P78+M78)) | R78: =IF(B78="","",ROUNDDOWN(TIENAN_CONG*H78,-3)) | S78: =IF(B78="","",Q78+R78)
A79: =IF(B79="","",74) | B79: =IF(BCC_KHOAN!B79="","",BCC_KHOAN!B79) | C79: =IF(B79="","",IFERROR(INDEX(NV_TEN,MATCH(B79,NV_MA,0)),"MÃ KHÔNG CÓ")) | D79: =IF(B79="","",IFERROR(INDEX(NV_HINHTHUC,MATCH(B79,NV_MA,0)),"")) | E79: =IF(D79="Khoán",IFERROR(INDEX(NV_HESO,MATCH(B79,NV_MA,0)),0),"") | F79: =IF(D79="Khoán",IFERROR(INDEX(HS_SX!$B$5:$B$30,MATCH(E79,HS_SX!$A$5:$A$30,0)),0),"") | G79: =IF(B79="","",IFERROR(INDEX(BCC_GIO,MATCH(B79,BCC_MA,0)),0)) | H79: =IF(B79="","",G79/GIO_CONG) | I79: =IF(D79="Khoán",IF(GIO_TB>0,G79/GIO_TB*KL_CHEBIEN,0),0) -> 0 | J79: =IF(D79="Khoán",F79*I79,0) -> 0 | K79: =IF(D79="Khoán",IF(TONG_GIO_KHOAN>0,QUY_HANGING/TONG_GIO_KHOAN*G79,0),0) -> 0 | L79: =IF(D79="Khoán",IF(TONG_GIO_KHOAN>0,QUY_KHAC/TONG_GIO_KHOAN*G79,0),0) -> 0 | M79: =IF(B79="",0,SUMIFS(KHOAN_KHAC!$F$5:$F$39,KHOAN_KHAC!$G$5:$G$39,B79)) -> 0 | N79: =IF(D79="Khoán",IF(TONG_GIO_KHOAN>0,QUY_CHEN/TONG_GIO_KHOAN*G79,0),0) -> 0 | O79: =IF(D79="Khoán",IF(TONG_GIO_KHOAN>0,-TONG_CONGNHAT/TONG_GIO_KHOAN*G79,0),0) -> 0 | P79: =IF(D79="Công nhật",H79*IFERROR(IF(INDEX(NV_DGCN,MATCH(B79,NV_MA,0))="",DG_CONGNHAT,INDEX(NV_DGCN,MATCH(B79,NV_MA,0))),DG_CONGNHAT),0) -> 0 | Q79: =IF(B79="","",IF(D79="Khoán",ROUNDDOWN(J79+K79+L79+M79+N79+O79,-3),P79+M79)) | R79: =IF(B79="","",ROUNDDOWN(TIENAN_CONG*H79,-3)) | S79: =IF(B79="","",Q79+R79)
A80: =IF(B80="","",75) | B80: =IF(BCC_KHOAN!B80="","",BCC_KHOAN!B80) | C80: =IF(B80="","",IFERROR(INDEX(NV_TEN,MATCH(B80,NV_MA,0)),"MÃ KHÔNG CÓ")) | D80: =IF(B80="","",IFERROR(INDEX(NV_HINHTHUC,MATCH(B80,NV_MA,0)),"")) | E80: =IF(D80="Khoán",IFERROR(INDEX(NV_HESO,MATCH(B80,NV_MA,0)),0),"") | F80: =IF(D80="Khoán",IFERROR(INDEX(HS_SX!$B$5:$B$30,MATCH(E80,HS_SX!$A$5:$A$30,0)),0),"") | G80: =IF(B80="","",IFERROR(INDEX(BCC_GIO,MATCH(B80,BCC_MA,0)),0)) | H80: =IF(B80="","",G80/GIO_CONG) | I80: =IF(D80="Khoán",IF(GIO_TB>0,G80/GIO_TB*KL_CHEBIEN,0),0) -> 0 | J80: =IF(D80="Khoán",F80*I80,0) -> 0 | K80: =IF(D80="Khoán",IF(TONG_GIO_KHOAN>0,QUY_HANGING/TONG_GIO_KHOAN*G80,0),0) -> 0 | L80: =IF(D80="Khoán",IF(TONG_GIO_KHOAN>0,QUY_KHAC/TONG_GIO_KHOAN*G80,0),0) -> 0 | M80: =IF(B80="",0,SUMIFS(KHOAN_KHAC!$F$5:$F$39,KHOAN_KHAC!$G$5:$G$39,B80)) -> 0 | N80: =IF(D80="Khoán",IF(TONG_GIO_KHOAN>0,QUY_CHEN/TONG_GIO_KHOAN*G80,0),0) -> 0 | O80: =IF(D80="Khoán",IF(TONG_GIO_KHOAN>0,-TONG_CONGNHAT/TONG_GIO_KHOAN*G80,0),0) -> 0 | P80: =IF(D80="Công nhật",H80*IFERROR(IF(INDEX(NV_DGCN,MATCH(B80,NV_MA,0))="",DG_CONGNHAT,INDEX(NV_DGCN,MATCH(B80,NV_MA,0))),DG_CONGNHAT),0) -> 0 | Q80: =IF(B80="","",IF(D80="Khoán",ROUNDDOWN(J80+K80+L80+M80+N80+O80,-3),P80+M80)) | R80: =IF(B80="","",ROUNDDOWN(TIENAN_CONG*H80,-3)) | S80: =IF(B80="","",Q80+R80)
A81: =IF(B81="","",76) | B81: =IF(BCC_KHOAN!B81="","",BCC_KHOAN!B81) | C81: =IF(B81="","",IFERROR(INDEX(NV_TEN,MATCH(B81,NV_MA,0)),"MÃ KHÔNG CÓ")) | D81: =IF(B81="","",IFERROR(INDEX(NV_HINHTHUC,MATCH(B81,NV_MA,0)),"")) | E81: =IF(D81="Khoán",IFERROR(INDEX(NV_HESO,MATCH(B81,NV_MA,0)),0),"") | F81: =IF(D81="Khoán",IFERROR(INDEX(HS_SX!$B$5:$B$30,MATCH(E81,HS_SX!$A$5:$A$30,0)),0),"") | G81: =IF(B81="","",IFERROR(INDEX(BCC_GIO,MATCH(B81,BCC_MA,0)),0)) | H81: =IF(B81="","",G81/GIO_CONG) | I81: =IF(D81="Khoán",IF(GIO_TB>0,G81/GIO_TB*KL_CHEBIEN,0),0) -> 0 | J81: =IF(D81="Khoán",F81*I81,0) -> 0 | K81: =IF(D81="Khoán",IF(TONG_GIO_KHOAN>0,QUY_HANGING/TONG_GIO_KHOAN*G81,0),0) -> 0 | L81: =IF(D81="Khoán",IF(TONG_GIO_KHOAN>0,QUY_KHAC/TONG_GIO_KHOAN*G81,0),0) -> 0 | M81: =IF(B81="",0,SUMIFS(KHOAN_KHAC!$F$5:$F$39,KHOAN_KHAC!$G$5:$G$39,B81)) -> 0 | N81: =IF(D81="Khoán",IF(TONG_GIO_KHOAN>0,QUY_CHEN/TONG_GIO_KHOAN*G81,0),0) -> 0 | O81: =IF(D81="Khoán",IF(TONG_GIO_KHOAN>0,-TONG_CONGNHAT/TONG_GIO_KHOAN*G81,0),0) -> 0 | P81: =IF(D81="Công nhật",H81*IFERROR(IF(INDEX(NV_DGCN,MATCH(B81,NV_MA,0))="",DG_CONGNHAT,INDEX(NV_DGCN,MATCH(B81,NV_MA,0))),DG_CONGNHAT),0) -> 0 | Q81: =IF(B81="","",IF(D81="Khoán",ROUNDDOWN(J81+K81+L81+M81+N81+O81,-3),P81+M81)) | R81: =IF(B81="","",ROUNDDOWN(TIENAN_CONG*H81,-3)) | S81: =IF(B81="","",Q81+R81)
A82: =IF(B82="","",77) | B82: =IF(BCC_KHOAN!B82="","",BCC_KHOAN!B82) | C82: =IF(B82="","",IFERROR(INDEX(NV_TEN,MATCH(B82,NV_MA,0)),"MÃ KHÔNG CÓ")) | D82: =IF(B82="","",IFERROR(INDEX(NV_HINHTHUC,MATCH(B82,NV_MA,0)),"")) | E82: =IF(D82="Khoán",IFERROR(INDEX(NV_HESO,MATCH(B82,NV_MA,0)),0),"") | F82: =IF(D82="Khoán",IFERROR(INDEX(HS_SX!$B$5:$B$30,MATCH(E82,HS_SX!$A$5:$A$30,0)),0),"") | G82: =IF(B82="","",IFERROR(INDEX(BCC_GIO,MATCH(B82,BCC_MA,0)),0)) | H82: =IF(B82="","",G82/GIO_CONG) | I82: =IF(D82="Khoán",IF(GIO_TB>0,G82/GIO_TB*KL_CHEBIEN,0),0) -> 0 | J82: =IF(D82="Khoán",F82*I82,0) -> 0 | K82: =IF(D82="Khoán",IF(TONG_GIO_KHOAN>0,QUY_HANGING/TONG_GIO_KHOAN*G82,0),0) -> 0 | L82: =IF(D82="Khoán",IF(TONG_GIO_KHOAN>0,QUY_KHAC/TONG_GIO_KHOAN*G82,0),0) -> 0 | M82: =IF(B82="",0,SUMIFS(KHOAN_KHAC!$F$5:$F$39,KHOAN_KHAC!$G$5:$G$39,B82)) -> 0 | N82: =IF(D82="Khoán",IF(TONG_GIO_KHOAN>0,QUY_CHEN/TONG_GIO_KHOAN*G82,0),0) -> 0 | O82: =IF(D82="Khoán",IF(TONG_GIO_KHOAN>0,-TONG_CONGNHAT/TONG_GIO_KHOAN*G82,0),0) -> 0 | P82: =IF(D82="Công nhật",H82*IFERROR(IF(INDEX(NV_DGCN,MATCH(B82,NV_MA,0))="",DG_CONGNHAT,INDEX(NV_DGCN,MATCH(B82,NV_MA,0))),DG_CONGNHAT),0) -> 0 | Q82: =IF(B82="","",IF(D82="Khoán",ROUNDDOWN(J82+K82+L82+M82+N82+O82,-3),P82+M82)) | R82: =IF(B82="","",ROUNDDOWN(TIENAN_CONG*H82,-3)) | S82: =IF(B82="","",Q82+R82)
A83: =IF(B83="","",78) | B83: =IF(BCC_KHOAN!B83="","",BCC_KHOAN!B83) | C83: =IF(B83="","",IFERROR(INDEX(NV_TEN,MATCH(B83,NV_MA,0)),"MÃ KHÔNG CÓ")) | D83: =IF(B83="","",IFERROR(INDEX(NV_HINHTHUC,MATCH(B83,NV_MA,0)),"")) | E83: =IF(D83="Khoán",IFERROR(INDEX(NV_HESO,MATCH(B83,NV_MA,0)),0),"") | F83: =IF(D83="Khoán",IFERROR(INDEX(HS_SX!$B$5:$B$30,MATCH(E83,HS_SX!$A$5:$A$30,0)),0),"") | G83: =IF(B83="","",IFERROR(INDEX(BCC_GIO,MATCH(B83,BCC_MA,0)),0)) | H83: =IF(B83="","",G83/GIO_CONG) | I83: =IF(D83="Khoán",IF(GIO_TB>0,G83/GIO_TB*KL_CHEBIEN,0),0) -> 0 | J83: =IF(D83="Khoán",F83*I83,0) -> 0 | K83: =IF(D83="Khoán",IF(TONG_GIO_KHOAN>0,QUY_HANGING/TONG_GIO_KHOAN*G83,0),0) -> 0 | L83: =IF(D83="Khoán",IF(TONG_GIO_KHOAN>0,QUY_KHAC/TONG_GIO_KHOAN*G83,0),0) -> 0 | M83: =IF(B83="",0,SUMIFS(KHOAN_KHAC!$F$5:$F$39,KHOAN_KHAC!$G$5:$G$39,B83)) -> 0 | N83: =IF(D83="Khoán",IF(TONG_GIO_KHOAN>0,QUY_CHEN/TONG_GIO_KHOAN*G83,0),0) -> 0 | O83: =IF(D83="Khoán",IF(TONG_GIO_KHOAN>0,-TONG_CONGNHAT/TONG_GIO_KHOAN*G83,0),0) -> 0 | P83: =IF(D83="Công nhật",H83*IFERROR(IF(INDEX(NV_DGCN,MATCH(B83,NV_MA,0))="",DG_CONGNHAT,INDEX(NV_DGCN,MATCH(B83,NV_MA,0))),DG_CONGNHAT),0) -> 0 | Q83: =IF(B83="","",IF(D83="Khoán",ROUNDDOWN(J83+K83+L83+M83+N83+O83,-3),P83+M83)) | R83: =IF(B83="","",ROUNDDOWN(TIENAN_CONG*H83,-3)) | S83: =IF(B83="","",Q83+R83)
A84: =IF(B84="","",79) | B84: =IF(BCC_KHOAN!B84="","",BCC_KHOAN!B84) | C84: =IF(B84="","",IFERROR(INDEX(NV_TEN,MATCH(B84,NV_MA,0)),"MÃ KHÔNG CÓ")) | D84: =IF(B84="","",IFERROR(INDEX(NV_HINHTHUC,MATCH(B84,NV_MA,0)),"")) | E84: =IF(D84="Khoán",IFERROR(INDEX(NV_HESO,MATCH(B84,NV_MA,0)),0),"") | F84: =IF(D84="Khoán",IFERROR(INDEX(HS_SX!$B$5:$B$30,MATCH(E84,HS_SX!$A$5:$A$30,0)),0),"") | G84: =IF(B84="","",IFERROR(INDEX(BCC_GIO,MATCH(B84,BCC_MA,0)),0)) | H84: =IF(B84="","",G84/GIO_CONG) | I84: =IF(D84="Khoán",IF(GIO_TB>0,G84/GIO_TB*KL_CHEBIEN,0),0) -> 0 | J84: =IF(D84="Khoán",F84*I84,0) -> 0 | K84: =IF(D84="Khoán",IF(TONG_GIO_KHOAN>0,QUY_HANGING/TONG_GIO_KHOAN*G84,0),0) -> 0 | L84: =IF(D84="Khoán",IF(TONG_GIO_KHOAN>0,QUY_KHAC/TONG_GIO_KHOAN*G84,0),0) -> 0 | M84: =IF(B84="",0,SUMIFS(KHOAN_KHAC!$F$5:$F$39,KHOAN_KHAC!$G$5:$G$39,B84)) -> 0 | N84: =IF(D84="Khoán",IF(TONG_GIO_KHOAN>0,QUY_CHEN/TONG_GIO_KHOAN*G84,0),0) -> 0 | O84: =IF(D84="Khoán",IF(TONG_GIO_KHOAN>0,-TONG_CONGNHAT/TONG_GIO_KHOAN*G84,0),0) -> 0 | P84: =IF(D84="Công nhật",H84*IFERROR(IF(INDEX(NV_DGCN,MATCH(B84,NV_MA,0))="",DG_CONGNHAT,INDEX(NV_DGCN,MATCH(B84,NV_MA,0))),DG_CONGNHAT),0) -> 0 | Q84: =IF(B84="","",IF(D84="Khoán",ROUNDDOWN(J84+K84+L84+M84+N84+O84,-3),P84+M84)) | R84: =IF(B84="","",ROUNDDOWN(TIENAN_CONG*H84,-3)) | S84: =IF(B84="","",Q84+R84)
A85: =IF(B85="","",80) | B85: =IF(BCC_KHOAN!B85="","",BCC_KHOAN!B85) | C85: =IF(B85="","",IFERROR(INDEX(NV_TEN,MATCH(B85,NV_MA,0)),"MÃ KHÔNG CÓ")) | D85: =IF(B85="","",IFERROR(INDEX(NV_HINHTHUC,MATCH(B85,NV_MA,0)),"")) | E85: =IF(D85="Khoán",IFERROR(INDEX(NV_HESO,MATCH(B85,NV_MA,0)),0),"") | F85: =IF(D85="Khoán",IFERROR(INDEX(HS_SX!$B$5:$B$30,MATCH(E85,HS_SX!$A$5:$A$30,0)),0),"") | G85: =IF(B85="","",IFERROR(INDEX(BCC_GIO,MATCH(B85,BCC_MA,0)),0)) | H85: =IF(B85="","",G85/GIO_CONG) | I85: =IF(D85="Khoán",IF(GIO_TB>0,G85/GIO_TB*KL_CHEBIEN,0),0) -> 0 | J85: =IF(D85="Khoán",F85*I85,0) -> 0 | K85: =IF(D85="Khoán",IF(TONG_GIO_KHOAN>0,QUY_HANGING/TONG_GIO_KHOAN*G85,0),0) -> 0 | L85: =IF(D85="Khoán",IF(TONG_GIO_KHOAN>0,QUY_KHAC/TONG_GIO_KHOAN*G85,0),0) -> 0 | M85: =IF(B85="",0,SUMIFS(KHOAN_KHAC!$F$5:$F$39,KHOAN_KHAC!$G$5:$G$39,B85)) -> 0 | N85: =IF(D85="Khoán",IF(TONG_GIO_KHOAN>0,QUY_CHEN/TONG_GIO_KHOAN*G85,0),0) -> 0 | O85: =IF(D85="Khoán",IF(TONG_GIO_KHOAN>0,-TONG_CONGNHAT/TONG_GIO_KHOAN*G85,0),0) -> 0 | P85: =IF(D85="Công nhật",H85*IFERROR(IF(INDEX(NV_DGCN,MATCH(B85,NV_MA,0))="",DG_CONGNHAT,INDEX(NV_DGCN,MATCH(B85,NV_MA,0))),DG_CONGNHAT),0) -> 0 | Q85: =IF(B85="","",IF(D85="Khoán",ROUNDDOWN(J85+K85+L85+M85+N85+O85,-3),P85+M85)) | R85: =IF(B85="","",ROUNDDOWN(TIENAN_CONG*H85,-3)) | S85: =IF(B85="","",Q85+R85)
A86: =IF(B86="","",81) | B86: =IF(BCC_KHOAN!B86="","",BCC_KHOAN!B86) | C86: =IF(B86="","",IFERROR(INDEX(NV_TEN,MATCH(B86,NV_MA,0)),"MÃ KHÔNG CÓ")) | D86: =IF(B86="","",IFERROR(INDEX(NV_HINHTHUC,MATCH(B86,NV_MA,0)),"")) | E86: =IF(D86="Khoán",IFERROR(INDEX(NV_HESO,MATCH(B86,NV_MA,0)),0),"") | F86: =IF(D86="Khoán",IFERROR(INDEX(HS_SX!$B$5:$B$30,MATCH(E86,HS_SX!$A$5:$A$30,0)),0),"") | G86: =IF(B86="","",IFERROR(INDEX(BCC_GIO,MATCH(B86,BCC_MA,0)),0)) | H86: =IF(B86="","",G86/GIO_CONG) | I86: =IF(D86="Khoán",IF(GIO_TB>0,G86/GIO_TB*KL_CHEBIEN,0),0) -> 0 | J86: =IF(D86="Khoán",F86*I86,0) -> 0 | K86: =IF(D86="Khoán",IF(TONG_GIO_KHOAN>0,QUY_HANGING/TONG_GIO_KHOAN*G86,0),0) -> 0 | L86: =IF(D86="Khoán",IF(TONG_GIO_KHOAN>0,QUY_KHAC/TONG_GIO_KHOAN*G86,0),0) -> 0 | M86: =IF(B86="",0,SUMIFS(KHOAN_KHAC!$F$5:$F$39,KHOAN_KHAC!$G$5:$G$39,B86)) -> 0 | N86: =IF(D86="Khoán",IF(TONG_GIO_KHOAN>0,QUY_CHEN/TONG_GIO_KHOAN*G86,0),0) -> 0 | O86: =IF(D86="Khoán",IF(TONG_GIO_KHOAN>0,-TONG_CONGNHAT/TONG_GIO_KHOAN*G86,0),0) -> 0 | P86: =IF(D86="Công nhật",H86*IFERROR(IF(INDEX(NV_DGCN,MATCH(B86,NV_MA,0))="",DG_CONGNHAT,INDEX(NV_DGCN,MATCH(B86,NV_MA,0))),DG_CONGNHAT),0) -> 0 | Q86: =IF(B86="","",IF(D86="Khoán",ROUNDDOWN(J86+K86+L86+M86+N86+O86,-3),P86+M86)) | R86: =IF(B86="","",ROUNDDOWN(TIENAN_CONG*H86,-3)) | S86: =IF(B86="","",Q86+R86)
A87: =IF(B87="","",82) | B87: =IF(BCC_KHOAN!B87="","",BCC_KHOAN!B87) | C87: =IF(B87="","",IFERROR(INDEX(NV_TEN,MATCH(B87,NV_MA,0)),"MÃ KHÔNG CÓ")) | D87: =IF(B87="","",IFERROR(INDEX(NV_HINHTHUC,MATCH(B87,NV_MA,0)),"")) | E87: =IF(D87="Khoán",IFERROR(INDEX(NV_HESO,MATCH(B87,NV_MA,0)),0),"") | F87: =IF(D87="Khoán",IFERROR(INDEX(HS_SX!$B$5:$B$30,MATCH(E87,HS_SX!$A$5:$A$30,0)),0),"") | G87: =IF(B87="","",IFERROR(INDEX(BCC_GIO,MATCH(B87,BCC_MA,0)),0)) | H87: =IF(B87="","",G87/GIO_CONG) | I87: =IF(D87="Khoán",IF(GIO_TB>0,G87/GIO_TB*KL_CHEBIEN,0),0) -> 0 | J87: =IF(D87="Khoán",F87*I87,0) -> 0 | K87: =IF(D87="Khoán",IF(TONG_GIO_KHOAN>0,QUY_HANGING/TONG_GIO_KHOAN*G87,0),0) -> 0 | L87: =IF(D87="Khoán",IF(TONG_GIO_KHOAN>0,QUY_KHAC/TONG_GIO_KHOAN*G87,0),0) -> 0 | M87: =IF(B87="",0,SUMIFS(KHOAN_KHAC!$F$5:$F$39,KHOAN_KHAC!$G$5:$G$39,B87)) -> 0 | N87: =IF(D87="Khoán",IF(TONG_GIO_KHOAN>0,QUY_CHEN/TONG_GIO_KHOAN*G87,0),0) -> 0 | O87: =IF(D87="Khoán",IF(TONG_GIO_KHOAN>0,-TONG_CONGNHAT/TONG_GIO_KHOAN*G87,0),0) -> 0 | P87: =IF(D87="Công nhật",H87*IFERROR(IF(INDEX(NV_DGCN,MATCH(B87,NV_MA,0))="",DG_CONGNHAT,INDEX(NV_DGCN,MATCH(B87,NV_MA,0))),DG_CONGNHAT),0) -> 0 | Q87: =IF(B87="","",IF(D87="Khoán",ROUNDDOWN(J87+K87+L87+M87+N87+O87,-3),P87+M87)) | R87: =IF(B87="","",ROUNDDOWN(TIENAN_CONG*H87,-3)) | S87: =IF(B87="","",Q87+R87)
A88: =IF(B88="","",83) | B88: =IF(BCC_KHOAN!B88="","",BCC_KHOAN!B88) | C88: =IF(B88="","",IFERROR(INDEX(NV_TEN,MATCH(B88,NV_MA,0)),"MÃ KHÔNG CÓ")) | D88: =IF(B88="","",IFERROR(INDEX(NV_HINHTHUC,MATCH(B88,NV_MA,0)),"")) | E88: =IF(D88="Khoán",IFERROR(INDEX(NV_HESO,MATCH(B88,NV_MA,0)),0),"") | F88: =IF(D88="Khoán",IFERROR(INDEX(HS_SX!$B$5:$B$30,MATCH(E88,HS_SX!$A$5:$A$30,0)),0),"") | G88: =IF(B88="","",IFERROR(INDEX(BCC_GIO,MATCH(B88,BCC_MA,0)),0)) | H88: =IF(B88="","",G88/GIO_CONG) | I88: =IF(D88="Khoán",IF(GIO_TB>0,G88/GIO_TB*KL_CHEBIEN,0),0) -> 0 | J88: =IF(D88="Khoán",F88*I88,0) -> 0 | K88: =IF(D88="Khoán",IF(TONG_GIO_KHOAN>0,QUY_HANGING/TONG_GIO_KHOAN*G88,0),0) -> 0 | L88: =IF(D88="Khoán",IF(TONG_GIO_KHOAN>0,QUY_KHAC/TONG_GIO_KHOAN*G88,0),0) -> 0 | M88: =IF(B88="",0,SUMIFS(KHOAN_KHAC!$F$5:$F$39,KHOAN_KHAC!$G$5:$G$39,B88)) -> 0 | N88: =IF(D88="Khoán",IF(TONG_GIO_KHOAN>0,QUY_CHEN/TONG_GIO_KHOAN*G88,0),0) -> 0 | O88: =IF(D88="Khoán",IF(TONG_GIO_KHOAN>0,-TONG_CONGNHAT/TONG_GIO_KHOAN*G88,0),0) -> 0 | P88: =IF(D88="Công nhật",H88*IFERROR(IF(INDEX(NV_DGCN,MATCH(B88,NV_MA,0))="",DG_CONGNHAT,INDEX(NV_DGCN,MATCH(B88,NV_MA,0))),DG_CONGNHAT),0) -> 0 | Q88: =IF(B88="","",IF(D88="Khoán",ROUNDDOWN(J88+K88+L88+M88+N88+O88,-3),P88+M88)) | R88: =IF(B88="","",ROUNDDOWN(TIENAN_CONG*H88,-3)) | S88: =IF(B88="","",Q88+R88)
A89: =IF(B89="","",84) | B89: =IF(BCC_KHOAN!B89="","",BCC_KHOAN!B89) | C89: =IF(B89="","",IFERROR(INDEX(NV_TEN,MATCH(B89,NV_MA,0)),"MÃ KHÔNG CÓ")) | D89: =IF(B89="","",IFERROR(INDEX(NV_HINHTHUC,MATCH(B89,NV_MA,0)),"")) | E89: =IF(D89="Khoán",IFERROR(INDEX(NV_HESO,MATCH(B89,NV_MA,0)),0),"") | F89: =IF(D89="Khoán",IFERROR(INDEX(HS_SX!$B$5:$B$30,MATCH(E89,HS_SX!$A$5:$A$30,0)),0),"") | G89: =IF(B89="","",IFERROR(INDEX(BCC_GIO,MATCH(B89,BCC_MA,0)),0)) | H89: =IF(B89="","",G89/GIO_CONG) | I89: =IF(D89="Khoán",IF(GIO_TB>0,G89/GIO_TB*KL_CHEBIEN,0),0) -> 0 | J89: =IF(D89="Khoán",F89*I89,0) -> 0 | K89: =IF(D89="Khoán",IF(TONG_GIO_KHOAN>0,QUY_HANGING/TONG_GIO_KHOAN*G89,0),0) -> 0 | L89: =IF(D89="Khoán",IF(TONG_GIO_KHOAN>0,QUY_KHAC/TONG_GIO_KHOAN*G89,0),0) -> 0 | M89: =IF(B89="",0,SUMIFS(KHOAN_KHAC!$F$5:$F$39,KHOAN_KHAC!$G$5:$G$39,B89)) -> 0 | N89: =IF(D89="Khoán",IF(TONG_GIO_KHOAN>0,QUY_CHEN/TONG_GIO_KHOAN*G89,0),0) -> 0 | O89: =IF(D89="Khoán",IF(TONG_GIO_KHOAN>0,-TONG_CONGNHAT/TONG_GIO_KHOAN*G89,0),0) -> 0 | P89: =IF(D89="Công nhật",H89*IFERROR(IF(INDEX(NV_DGCN,MATCH(B89,NV_MA,0))="",DG_CONGNHAT,INDEX(NV_DGCN,MATCH(B89,NV_MA,0))),DG_CONGNHAT),0) -> 0 | Q89: =IF(B89="","",IF(D89="Khoán",ROUNDDOWN(J89+K89+L89+M89+N89+O89,-3),P89+M89)) | R89: =IF(B89="","",ROUNDDOWN(TIENAN_CONG*H89,-3)) | S89: =IF(B89="","",Q89+R89)
A90: =IF(B90="","",85) | B90: =IF(BCC_KHOAN!B90="","",BCC_KHOAN!B90) | C90: =IF(B90="","",IFERROR(INDEX(NV_TEN,MATCH(B90,NV_MA,0)),"MÃ KHÔNG CÓ")) | D90: =IF(B90="","",IFERROR(INDEX(NV_HINHTHUC,MATCH(B90,NV_MA,0)),"")) | E90: =IF(D90="Khoán",IFERROR(INDEX(NV_HESO,MATCH(B90,NV_MA,0)),0),"") | F90: =IF(D90="Khoán",IFERROR(INDEX(HS_SX!$B$5:$B$30,MATCH(E90,HS_SX!$A$5:$A$30,0)),0),"") | G90: =IF(B90="","",IFERROR(INDEX(BCC_GIO,MATCH(B90,BCC_MA,0)),0)) | H90: =IF(B90="","",G90/GIO_CONG) | I90: =IF(D90="Khoán",IF(GIO_TB>0,G90/GIO_TB*KL_CHEBIEN,0),0) -> 0 | J90: =IF(D90="Khoán",F90*I90,0) -> 0 | K90: =IF(D90="Khoán",IF(TONG_GIO_KHOAN>0,QUY_HANGING/TONG_GIO_KHOAN*G90,0),0) -> 0 | L90: =IF(D90="Khoán",IF(TONG_GIO_KHOAN>0,QUY_KHAC/TONG_GIO_KHOAN*G90,0),0) -> 0 | M90: =IF(B90="",0,SUMIFS(KHOAN_KHAC!$F$5:$F$39,KHOAN_KHAC!$G$5:$G$39,B90)) -> 0 | N90: =IF(D90="Khoán",IF(TONG_GIO_KHOAN>0,QUY_CHEN/TONG_GIO_KHOAN*G90,0),0) -> 0 | O90: =IF(D90="Khoán",IF(TONG_GIO_KHOAN>0,-TONG_CONGNHAT/TONG_GIO_KHOAN*G90,0),0) -> 0 | P90: =IF(D90="Công nhật",H90*IFERROR(IF(INDEX(NV_DGCN,MATCH(B90,NV_MA,0))="",DG_CONGNHAT,INDEX(NV_DGCN,MATCH(B90,NV_MA,0))),DG_CONGNHAT),0) -> 0 | Q90: =IF(B90="","",IF(D90="Khoán",ROUNDDOWN(J90+K90+L90+M90+N90+O90,-3),P90+M90)) | R90: =IF(B90="","",ROUNDDOWN(TIENAN_CONG*H90,-3)) | S90: =IF(B90="","",Q90+R90)
A91: =IF(B91="","",86) | B91: =IF(BCC_KHOAN!B91="","",BCC_KHOAN!B91) | C91: =IF(B91="","",IFERROR(INDEX(NV_TEN,MATCH(B91,NV_MA,0)),"MÃ KHÔNG CÓ")) | D91: =IF(B91="","",IFERROR(INDEX(NV_HINHTHUC,MATCH(B91,NV_MA,0)),"")) | E91: =IF(D91="Khoán",IFERROR(INDEX(NV_HESO,MATCH(B91,NV_MA,0)),0),"") | F91: =IF(D91="Khoán",IFERROR(INDEX(HS_SX!$B$5:$B$30,MATCH(E91,HS_SX!$A$5:$A$30,0)),0),"") | G91: =IF(B91="","",IFERROR(INDEX(BCC_GIO,MATCH(B91,BCC_MA,0)),0)) | H91: =IF(B91="","",G91/GIO_CONG) | I91: =IF(D91="Khoán",IF(GIO_TB>0,G91/GIO_TB*KL_CHEBIEN,0),0) -> 0 | J91: =IF(D91="Khoán",F91*I91,0) -> 0 | K91: =IF(D91="Khoán",IF(TONG_GIO_KHOAN>0,QUY_HANGING/TONG_GIO_KHOAN*G91,0),0) -> 0 | L91: =IF(D91="Khoán",IF(TONG_GIO_KHOAN>0,QUY_KHAC/TONG_GIO_KHOAN*G91,0),0) -> 0 | M91: =IF(B91="",0,SUMIFS(KHOAN_KHAC!$F$5:$F$39,KHOAN_KHAC!$G$5:$G$39,B91)) -> 0 | N91: =IF(D91="Khoán",IF(TONG_GIO_KHOAN>0,QUY_CHEN/TONG_GIO_KHOAN*G91,0),0) -> 0 | O91: =IF(D91="Khoán",IF(TONG_GIO_KHOAN>0,-TONG_CONGNHAT/TONG_GIO_KHOAN*G91,0),0) -> 0 | P91: =IF(D91="Công nhật",H91*IFERROR(IF(INDEX(NV_DGCN,MATCH(B91,NV_MA,0))="",DG_CONGNHAT,INDEX(NV_DGCN,MATCH(B91,NV_MA,0))),DG_CONGNHAT),0) -> 0 | Q91: =IF(B91="","",IF(D91="Khoán",ROUNDDOWN(J91+K91+L91+M91+N91+O91,-3),P91+M91)) | R91: =IF(B91="","",ROUNDDOWN(TIENAN_CONG*H91,-3)) | S91: =IF(B91="","",Q91+R91)
A92: =IF(B92="","",87) | B92: =IF(BCC_KHOAN!B92="","",BCC_KHOAN!B92) | C92: =IF(B92="","",IFERROR(INDEX(NV_TEN,MATCH(B92,NV_MA,0)),"MÃ KHÔNG CÓ")) | D92: =IF(B92="","",IFERROR(INDEX(NV_HINHTHUC,MATCH(B92,NV_MA,0)),"")) | E92: =IF(D92="Khoán",IFERROR(INDEX(NV_HESO,MATCH(B92,NV_MA,0)),0),"") | F92: =IF(D92="Khoán",IFERROR(INDEX(HS_SX!$B$5:$B$30,MATCH(E92,HS_SX!$A$5:$A$30,0)),0),"") | G92: =IF(B92="","",IFERROR(INDEX(BCC_GIO,MATCH(B92,BCC_MA,0)),0)) | H92: =IF(B92="","",G92/GIO_CONG) | I92: =IF(D92="Khoán",IF(GIO_TB>0,G92/GIO_TB*KL_CHEBIEN,0),0) -> 0 | J92: =IF(D92="Khoán",F92*I92,0) -> 0 | K92: =IF(D92="Khoán",IF(TONG_GIO_KHOAN>0,QUY_HANGING/TONG_GIO_KHOAN*G92,0),0) -> 0 | L92: =IF(D92="Khoán",IF(TONG_GIO_KHOAN>0,QUY_KHAC/TONG_GIO_KHOAN*G92,0),0) -> 0 | M92: =IF(B92="",0,SUMIFS(KHOAN_KHAC!$F$5:$F$39,KHOAN_KHAC!$G$5:$G$39,B92)) -> 0 | N92: =IF(D92="Khoán",IF(TONG_GIO_KHOAN>0,QUY_CHEN/TONG_GIO_KHOAN*G92,0),0) -> 0 | O92: =IF(D92="Khoán",IF(TONG_GIO_KHOAN>0,-TONG_CONGNHAT/TONG_GIO_KHOAN*G92,0),0) -> 0 | P92: =IF(D92="Công nhật",H92*IFERROR(IF(INDEX(NV_DGCN,MATCH(B92,NV_MA,0))="",DG_CONGNHAT,INDEX(NV_DGCN,MATCH(B92,NV_MA,0))),DG_CONGNHAT),0) -> 0 | Q92: =IF(B92="","",IF(D92="Khoán",ROUNDDOWN(J92+K92+L92+M92+N92+O92,-3),P92+M92)) | R92: =IF(B92="","",ROUNDDOWN(TIENAN_CONG*H92,-3)) | S92: =IF(B92="","",Q92+R92)
A93: =IF(B93="","",88) | B93: =IF(BCC_KHOAN!B93="","",BCC_KHOAN!B93) | C93: =IF(B93="","",IFERROR(INDEX(NV_TEN,MATCH(B93,NV_MA,0)),"MÃ KHÔNG CÓ")) | D93: =IF(B93="","",IFERROR(INDEX(NV_HINHTHUC,MATCH(B93,NV_MA,0)),"")) | E93: =IF(D93="Khoán",IFERROR(INDEX(NV_HESO,MATCH(B93,NV_MA,0)),0),"") | F93: =IF(D93="Khoán",IFERROR(INDEX(HS_SX!$B$5:$B$30,MATCH(E93,HS_SX!$A$5:$A$30,0)),0),"") | G93: =IF(B93="","",IFERROR(INDEX(BCC_GIO,MATCH(B93,BCC_MA,0)),0)) | H93: =IF(B93="","",G93/GIO_CONG) | I93: =IF(D93="Khoán",IF(GIO_TB>0,G93/GIO_TB*KL_CHEBIEN,0),0) -> 0 | J93: =IF(D93="Khoán",F93*I93,0) -> 0 | K93: =IF(D93="Khoán",IF(TONG_GIO_KHOAN>0,QUY_HANGING/TONG_GIO_KHOAN*G93,0),0) -> 0 | L93: =IF(D93="Khoán",IF(TONG_GIO_KHOAN>0,QUY_KHAC/TONG_GIO_KHOAN*G93,0),0) -> 0 | M93: =IF(B93="",0,SUMIFS(KHOAN_KHAC!$F$5:$F$39,KHOAN_KHAC!$G$5:$G$39,B93)) -> 0 | N93: =IF(D93="Khoán",IF(TONG_GIO_KHOAN>0,QUY_CHEN/TONG_GIO_KHOAN*G93,0),0) -> 0 | O93: =IF(D93="Khoán",IF(TONG_GIO_KHOAN>0,-TONG_CONGNHAT/TONG_GIO_KHOAN*G93,0),0) -> 0 | P93: =IF(D93="Công nhật",H93*IFERROR(IF(INDEX(NV_DGCN,MATCH(B93,NV_MA,0))="",DG_CONGNHAT,INDEX(NV_DGCN,MATCH(B93,NV_MA,0))),DG_CONGNHAT),0) -> 0 | Q93: =IF(B93="","",IF(D93="Khoán",ROUNDDOWN(J93+K93+L93+M93+N93+O93,-3),P93+M93)) | R93: =IF(B93="","",ROUNDDOWN(TIENAN_CONG*H93,-3)) | S93: =IF(B93="","",Q93+R93)
A94: =IF(B94="","",89) | B94: =IF(BCC_KHOAN!B94="","",BCC_KHOAN!B94) | C94: =IF(B94="","",IFERROR(INDEX(NV_TEN,MATCH(B94,NV_MA,0)),"MÃ KHÔNG CÓ")) | D94: =IF(B94="","",IFERROR(INDEX(NV_HINHTHUC,MATCH(B94,NV_MA,0)),"")) | E94: =IF(D94="Khoán",IFERROR(INDEX(NV_HESO,MATCH(B94,NV_MA,0)),0),"") | F94: =IF(D94="Khoán",IFERROR(INDEX(HS_SX!$B$5:$B$30,MATCH(E94,HS_SX!$A$5:$A$30,0)),0),"") | G94: =IF(B94="","",IFERROR(INDEX(BCC_GIO,MATCH(B94,BCC_MA,0)),0)) | H94: =IF(B94="","",G94/GIO_CONG) | I94: =IF(D94="Khoán",IF(GIO_TB>0,G94/GIO_TB*KL_CHEBIEN,0),0) -> 0 | J94: =IF(D94="Khoán",F94*I94,0) -> 0 | K94: =IF(D94="Khoán",IF(TONG_GIO_KHOAN>0,QUY_HANGING/TONG_GIO_KHOAN*G94,0),0) -> 0 | L94: =IF(D94="Khoán",IF(TONG_GIO_KHOAN>0,QUY_KHAC/TONG_GIO_KHOAN*G94,0),0) -> 0 | M94: =IF(B94="",0,SUMIFS(KHOAN_KHAC!$F$5:$F$39,KHOAN_KHAC!$G$5:$G$39,B94)) -> 0 | N94: =IF(D94="Khoán",IF(TONG_GIO_KHOAN>0,QUY_CHEN/TONG_GIO_KHOAN*G94,0),0) -> 0 | O94: =IF(D94="Khoán",IF(TONG_GIO_KHOAN>0,-TONG_CONGNHAT/TONG_GIO_KHOAN*G94,0),0) -> 0 | P94: =IF(D94="Công nhật",H94*IFERROR(IF(INDEX(NV_DGCN,MATCH(B94,NV_MA,0))="",DG_CONGNHAT,INDEX(NV_DGCN,MATCH(B94,NV_MA,0))),DG_CONGNHAT),0) -> 0 | Q94: =IF(B94="","",IF(D94="Khoán",ROUNDDOWN(J94+K94+L94+M94+N94+O94,-3),P94+M94)) | R94: =IF(B94="","",ROUNDDOWN(TIENAN_CONG*H94,-3)) | S94: =IF(B94="","",Q94+R94)
A95: =IF(B95="","",90) | B95: =IF(BCC_KHOAN!B95="","",BCC_KHOAN!B95) | C95: =IF(B95="","",IFERROR(INDEX(NV_TEN,MATCH(B95,NV_MA,0)),"MÃ KHÔNG CÓ")) | D95: =IF(B95="","",IFERROR(INDEX(NV_HINHTHUC,MATCH(B95,NV_MA,0)),"")) | E95: =IF(D95="Khoán",IFERROR(INDEX(NV_HESO,MATCH(B95,NV_MA,0)),0),"") | F95: =IF(D95="Khoán",IFERROR(INDEX(HS_SX!$B$5:$B$30,MATCH(E95,HS_SX!$A$5:$A$30,0)),0),"") | G95: =IF(B95="","",IFERROR(INDEX(BCC_GIO,MATCH(B95,BCC_MA,0)),0)) | H95: =IF(B95="","",G95/GIO_CONG) | I95: =IF(D95="Khoán",IF(GIO_TB>0,G95/GIO_TB*KL_CHEBIEN,0),0) -> 0 | J95: =IF(D95="Khoán",F95*I95,0) -> 0 | K95: =IF(D95="Khoán",IF(TONG_GIO_KHOAN>0,QUY_HANGING/TONG_GIO_KHOAN*G95,0),0) -> 0 | L95: =IF(D95="Khoán",IF(TONG_GIO_KHOAN>0,QUY_KHAC/TONG_GIO_KHOAN*G95,0),0) -> 0 | M95: =IF(B95="",0,SUMIFS(KHOAN_KHAC!$F$5:$F$39,KHOAN_KHAC!$G$5:$G$39,B95)) -> 0 | N95: =IF(D95="Khoán",IF(TONG_GIO_KHOAN>0,QUY_CHEN/TONG_GIO_KHOAN*G95,0),0) -> 0 | O95: =IF(D95="Khoán",IF(TONG_GIO_KHOAN>0,-TONG_CONGNHAT/TONG_GIO_KHOAN*G95,0),0) -> 0 | P95: =IF(D95="Công nhật",H95*IFERROR(IF(INDEX(NV_DGCN,MATCH(B95,NV_MA,0))="",DG_CONGNHAT,INDEX(NV_DGCN,MATCH(B95,NV_MA,0))),DG_CONGNHAT),0) -> 0 | Q95: =IF(B95="","",IF(D95="Khoán",ROUNDDOWN(J95+K95+L95+M95+N95+O95,-3),P95+M95)) | R95: =IF(B95="","",ROUNDDOWN(TIENAN_CONG*H95,-3)) | S95: =IF(B95="","",Q95+R95)
A96: =IF(B96="","",91) | B96: =IF(BCC_KHOAN!B96="","",BCC_KHOAN!B96) | C96: =IF(B96="","",IFERROR(INDEX(NV_TEN,MATCH(B96,NV_MA,0)),"MÃ KHÔNG CÓ")) | D96: =IF(B96="","",IFERROR(INDEX(NV_HINHTHUC,MATCH(B96,NV_MA,0)),"")) | E96: =IF(D96="Khoán",IFERROR(INDEX(NV_HESO,MATCH(B96,NV_MA,0)),0),"") | F96: =IF(D96="Khoán",IFERROR(INDEX(HS_SX!$B$5:$B$30,MATCH(E96,HS_SX!$A$5:$A$30,0)),0),"") | G96: =IF(B96="","",IFERROR(INDEX(BCC_GIO,MATCH(B96,BCC_MA,0)),0)) | H96: =IF(B96="","",G96/GIO_CONG) | I96: =IF(D96="Khoán",IF(GIO_TB>0,G96/GIO_TB*KL_CHEBIEN,0),0) -> 0 | J96: =IF(D96="Khoán",F96*I96,0) -> 0 | K96: =IF(D96="Khoán",IF(TONG_GIO_KHOAN>0,QUY_HANGING/TONG_GIO_KHOAN*G96,0),0) -> 0 | L96: =IF(D96="Khoán",IF(TONG_GIO_KHOAN>0,QUY_KHAC/TONG_GIO_KHOAN*G96,0),0) -> 0 | M96: =IF(B96="",0,SUMIFS(KHOAN_KHAC!$F$5:$F$39,KHOAN_KHAC!$G$5:$G$39,B96)) -> 0 | N96: =IF(D96="Khoán",IF(TONG_GIO_KHOAN>0,QUY_CHEN/TONG_GIO_KHOAN*G96,0),0) -> 0 | O96: =IF(D96="Khoán",IF(TONG_GIO_KHOAN>0,-TONG_CONGNHAT/TONG_GIO_KHOAN*G96,0),0) -> 0 | P96: =IF(D96="Công nhật",H96*IFERROR(IF(INDEX(NV_DGCN,MATCH(B96,NV_MA,0))="",DG_CONGNHAT,INDEX(NV_DGCN,MATCH(B96,NV_MA,0))),DG_CONGNHAT),0) -> 0 | Q96: =IF(B96="","",IF(D96="Khoán",ROUNDDOWN(J96+K96+L96+M96+N96+O96,-3),P96+M96)) | R96: =IF(B96="","",ROUNDDOWN(TIENAN_CONG*H96,-3)) | S96: =IF(B96="","",Q96+R96)
A97: =IF(B97="","",92) | B97: =IF(BCC_KHOAN!B97="","",BCC_KHOAN!B97) | C97: =IF(B97="","",IFERROR(INDEX(NV_TEN,MATCH(B97,NV_MA,0)),"MÃ KHÔNG CÓ")) | D97: =IF(B97="","",IFERROR(INDEX(NV_HINHTHUC,MATCH(B97,NV_MA,0)),"")) | E97: =IF(D97="Khoán",IFERROR(INDEX(NV_HESO,MATCH(B97,NV_MA,0)),0),"") | F97: =IF(D97="Khoán",IFERROR(INDEX(HS_SX!$B$5:$B$30,MATCH(E97,HS_SX!$A$5:$A$30,0)),0),"") | G97: =IF(B97="","",IFERROR(INDEX(BCC_GIO,MATCH(B97,BCC_MA,0)),0)) | H97: =IF(B97="","",G97/GIO_CONG) | I97: =IF(D97="Khoán",IF(GIO_TB>0,G97/GIO_TB*KL_CHEBIEN,0),0) -> 0 | J97: =IF(D97="Khoán",F97*I97,0) -> 0 | K97: =IF(D97="Khoán",IF(TONG_GIO_KHOAN>0,QUY_HANGING/TONG_GIO_KHOAN*G97,0),0) -> 0 | L97: =IF(D97="Khoán",IF(TONG_GIO_KHOAN>0,QUY_KHAC/TONG_GIO_KHOAN*G97,0),0) -> 0 | M97: =IF(B97="",0,SUMIFS(KHOAN_KHAC!$F$5:$F$39,KHOAN_KHAC!$G$5:$G$39,B97)) -> 0 | N97: =IF(D97="Khoán",IF(TONG_GIO_KHOAN>0,QUY_CHEN/TONG_GIO_KHOAN*G97,0),0) -> 0 | O97: =IF(D97="Khoán",IF(TONG_GIO_KHOAN>0,-TONG_CONGNHAT/TONG_GIO_KHOAN*G97,0),0) -> 0 | P97: =IF(D97="Công nhật",H97*IFERROR(IF(INDEX(NV_DGCN,MATCH(B97,NV_MA,0))="",DG_CONGNHAT,INDEX(NV_DGCN,MATCH(B97,NV_MA,0))),DG_CONGNHAT),0) -> 0 | Q97: =IF(B97="","",IF(D97="Khoán",ROUNDDOWN(J97+K97+L97+M97+N97+O97,-3),P97+M97)) | R97: =IF(B97="","",ROUNDDOWN(TIENAN_CONG*H97,-3)) | S97: =IF(B97="","",Q97+R97)
A98: =IF(B98="","",93) | B98: =IF(BCC_KHOAN!B98="","",BCC_KHOAN!B98) | C98: =IF(B98="","",IFERROR(INDEX(NV_TEN,MATCH(B98,NV_MA,0)),"MÃ KHÔNG CÓ")) | D98: =IF(B98="","",IFERROR(INDEX(NV_HINHTHUC,MATCH(B98,NV_MA,0)),"")) | E98: =IF(D98="Khoán",IFERROR(INDEX(NV_HESO,MATCH(B98,NV_MA,0)),0),"") | F98: =IF(D98="Khoán",IFERROR(INDEX(HS_SX!$B$5:$B$30,MATCH(E98,HS_SX!$A$5:$A$30,0)),0),"") | G98: =IF(B98="","",IFERROR(INDEX(BCC_GIO,MATCH(B98,BCC_MA,0)),0)) | H98: =IF(B98="","",G98/GIO_CONG) | I98: =IF(D98="Khoán",IF(GIO_TB>0,G98/GIO_TB*KL_CHEBIEN,0),0) -> 0 | J98: =IF(D98="Khoán",F98*I98,0) -> 0 | K98: =IF(D98="Khoán",IF(TONG_GIO_KHOAN>0,QUY_HANGING/TONG_GIO_KHOAN*G98,0),0) -> 0 | L98: =IF(D98="Khoán",IF(TONG_GIO_KHOAN>0,QUY_KHAC/TONG_GIO_KHOAN*G98,0),0) -> 0 | M98: =IF(B98="",0,SUMIFS(KHOAN_KHAC!$F$5:$F$39,KHOAN_KHAC!$G$5:$G$39,B98)) -> 0 | N98: =IF(D98="Khoán",IF(TONG_GIO_KHOAN>0,QUY_CHEN/TONG_GIO_KHOAN*G98,0),0) -> 0 | O98: =IF(D98="Khoán",IF(TONG_GIO_KHOAN>0,-TONG_CONGNHAT/TONG_GIO_KHOAN*G98,0),0) -> 0 | P98: =IF(D98="Công nhật",H98*IFERROR(IF(INDEX(NV_DGCN,MATCH(B98,NV_MA,0))="",DG_CONGNHAT,INDEX(NV_DGCN,MATCH(B98,NV_MA,0))),DG_CONGNHAT),0) -> 0 | Q98: =IF(B98="","",IF(D98="Khoán",ROUNDDOWN(J98+K98+L98+M98+N98+O98,-3),P98+M98)) | R98: =IF(B98="","",ROUNDDOWN(TIENAN_CONG*H98,-3)) | S98: =IF(B98="","",Q98+R98)
A99: =IF(B99="","",94) | B99: =IF(BCC_KHOAN!B99="","",BCC_KHOAN!B99) | C99: =IF(B99="","",IFERROR(INDEX(NV_TEN,MATCH(B99,NV_MA,0)),"MÃ KHÔNG CÓ")) | D99: =IF(B99="","",IFERROR(INDEX(NV_HINHTHUC,MATCH(B99,NV_MA,0)),"")) | E99: =IF(D99="Khoán",IFERROR(INDEX(NV_HESO,MATCH(B99,NV_MA,0)),0),"") | F99: =IF(D99="Khoán",IFERROR(INDEX(HS_SX!$B$5:$B$30,MATCH(E99,HS_SX!$A$5:$A$30,0)),0),"") | G99: =IF(B99="","",IFERROR(INDEX(BCC_GIO,MATCH(B99,BCC_MA,0)),0)) | H99: =IF(B99="","",G99/GIO_CONG) | I99: =IF(D99="Khoán",IF(GIO_TB>0,G99/GIO_TB*KL_CHEBIEN,0),0) -> 0 | J99: =IF(D99="Khoán",F99*I99,0) -> 0 | K99: =IF(D99="Khoán",IF(TONG_GIO_KHOAN>0,QUY_HANGING/TONG_GIO_KHOAN*G99,0),0) -> 0 | L99: =IF(D99="Khoán",IF(TONG_GIO_KHOAN>0,QUY_KHAC/TONG_GIO_KHOAN*G99,0),0) -> 0 | M99: =IF(B99="",0,SUMIFS(KHOAN_KHAC!$F$5:$F$39,KHOAN_KHAC!$G$5:$G$39,B99)) -> 0 | N99: =IF(D99="Khoán",IF(TONG_GIO_KHOAN>0,QUY_CHEN/TONG_GIO_KHOAN*G99,0),0) -> 0 | O99: =IF(D99="Khoán",IF(TONG_GIO_KHOAN>0,-TONG_CONGNHAT/TONG_GIO_KHOAN*G99,0),0) -> 0 | P99: =IF(D99="Công nhật",H99*IFERROR(IF(INDEX(NV_DGCN,MATCH(B99,NV_MA,0))="",DG_CONGNHAT,INDEX(NV_DGCN,MATCH(B99,NV_MA,0))),DG_CONGNHAT),0) -> 0 | Q99: =IF(B99="","",IF(D99="Khoán",ROUNDDOWN(J99+K99+L99+M99+N99+O99,-3),P99+M99)) | R99: =IF(B99="","",ROUNDDOWN(TIENAN_CONG*H99,-3)) | S99: =IF(B99="","",Q99+R99)
A100: =IF(B100="","",95) | B100: =IF(BCC_KHOAN!B100="","",BCC_KHOAN!B100) | C100: =IF(B100="","",IFERROR(INDEX(NV_TEN,MATCH(B100,NV_MA,0)),"MÃ KHÔNG CÓ")) | D100: =IF(B100="","",IFERROR(INDEX(NV_HINHTHUC,MATCH(B100,NV_MA,0)),"")) | E100: =IF(D100="Khoán",IFERROR(INDEX(NV_HESO,MATCH(B100,NV_MA,0)),0),"") | F100: =IF(D100="Khoán",IFERROR(INDEX(HS_SX!$B$5:$B$30,MATCH(E100,HS_SX!$A$5:$A$30,0)),0),"") | G100: =IF(B100="","",IFERROR(INDEX(BCC_GIO,MATCH(B100,BCC_MA,0)),0)) | H100: =IF(B100="","",G100/GIO_CONG) | I100: =IF(D100="Khoán",IF(GIO_TB>0,G100/GIO_TB*KL_CHEBIEN,0),0) -> 0 | J100: =IF(D100="Khoán",F100*I100,0) -> 0 | K100: =IF(D100="Khoán",IF(TONG_GIO_KHOAN>0,QUY_HANGING/TONG_GIO_KHOAN*G100,0),0) -> 0 | L100: =IF(D100="Khoán",IF(TONG_GIO_KHOAN>0,QUY_KHAC/TONG_GIO_KHOAN*G100,0),0) -> 0 | M100: =IF(B100="",0,SUMIFS(KHOAN_KHAC!$F$5:$F$39,KHOAN_KHAC!$G$5:$G$39,B100)) -> 0 | N100: =IF(D100="Khoán",IF(TONG_GIO_KHOAN>0,QUY_CHEN/TONG_GIO_KHOAN*G100,0),0) -> 0 | O100: =IF(D100="Khoán",IF(TONG_GIO_KHOAN>0,-TONG_CONGNHAT/TONG_GIO_KHOAN*G100,0),0) -> 0 | P100: =IF(D100="Công nhật",H100*IFERROR(IF(INDEX(NV_DGCN,MATCH(B100,NV_MA,0))="",DG_CONGNHAT,INDEX(NV_DGCN,MATCH(B100,NV_MA,0))),DG_CONGNHAT),0) -> 0 | Q100: =IF(B100="","",IF(D100="Khoán",ROUNDDOWN(J100+K100+L100+M100+N100+O100,-3),P100+M100)) | R100: =IF(B100="","",ROUNDDOWN(TIENAN_CONG*H100,-3)) | S100: =IF(B100="","",Q100+R100)
C102: TỔNG CỘNG | G102: =SUM(G6:G100) -> 455 | H102: =SUM(H6:H100) -> 56.875 | I102: =SUM(I6:I100) -> 45254.58 | J102: =SUM(J6:J100) -> 3.4073218e+08 | K102: =SUM(K6:K100) -> 0 | L102: =SUM(L6:L100) -> -22450000 | M102: =SUM(M6:M100) -> 400000 | N102: =SUM(N6:N100) -> 14751800 | ... S102: =SUM(S6:S100) -> 355521000

Sheet KIEM_TRA
A1: KIỂM TRA TRƯỚC KHI CHỐT – tất cả phải OK
A2: Thay cho các ô TRUE/FALSE rải rác trong file cũ.
A4: # | B4: Nội dung kiểm tra | C4: Giá trị | D4: Kết quả | E4: Cách xử lý nếu LỖI
A5: 1 | B5: Tổng tiền ăn phân bổ so với quỹ tiền ăn (lệch do làm tròn ≤ 1.000 đ/người) | C5: =QUY_TIENAN-SUM(LUONG_KHOAN!$R$6:$R$100) -> 545 | D5: =IF(ABS(C5)<=COUNTA(BCC_MA)*LAMTRON,"OK","LỖI") -> OK | E5: Kiểm tra THAM_SO!C12 và cột Ngày công
A6: 2 | B6: Tổng lương khoán đã phân bổ so với tổng các quỹ (hanging + chèn + CV khác + đích danh − công nhật + khoán SP) | C6: =(QUY_HANGING+QUY_CHEN+QUY_KHAC+THAM_SO!$C$23-TONG_CONGNHAT+THAM_SO!$C$28)-SUMIFS(LUONG_KHOAN!$Q$6:$Q$100,LUONG_KHOAN!$D$6:$D$100,"Khoán") -> 976.18462 | D6: =IF(ABS(C6)<=COUNTA(BCC_MA)*LAMTRON,"OK","LỖI") -> OK | E6: Có người khoán không có trong BCC hoặc hệ số trống
A7: 3 | B7: Số lao động khoán có giờ công trong tháng | C7: =COUNTIFS(LUONG_KHOAN!$D$6:$D$100,"Khoán",LUONG_KHOAN!$G$6:$G$100,">0") -> 3 | D7: =IF(C7=SO_LD_DINHMUC,"OK","XEM LẠI") -> XEM LẠI | E7: Khác THAM_SO!C11 (42). Nếu định mức là số người thực tế → sửa C11; nếu là hằng số → bỏ qua
A8: 4 | B8: Mã NV trùng trong NHAN_VIEN | C8: =SUMPRODUCT((NV_MA<>"")*(COUNTIF(NV_MA,NV_MA)>1)) -> 0 | D8: =IF(C8=0,"OK","LỖI") -> OK | E8: Sửa mã trùng (file cũ: Trần Văn Tâm & Trần Đình Hải cùng mã)
A9: 5 | B9: Mã NV trùng trong BCC_KHOAN | C9: =SUMPRODUCT((BCC_MA<>"")*(COUNTIF(BCC_MA,BCC_MA)>1)) -> 0 | D9: =IF(C9=0,"OK","LỖI") -> OK | E9: Một người chỉ một dòng chấm công
A10: 6 | B10: Mã trong BCC không có trong danh mục | C10: =COUNTIF(LUONG_KHOAN!$C$6:$C$100,"MÃ KHÔNG CÓ") -> 0 | D10: =IF(C10=0,"OK","LỖI") -> OK | E10: Thêm người vào NHAN_VIEN
A11: 7 | B11: Người khoán có hệ số không có trong bảng HS_SX | C11: =COUNTIFS(LUONG_KHOAN!$D$6:$D$100,"Khoán",LUONG_KHOAN!$F$6:$F$100,0) -> 0 | D11: =IF(C11=0,"OK","LỖI") -> OK | E11: Bổ sung hệ số vào HS_SX
A12: 8 | B12: Mã đích danh trong KHOAN_KHAC không tồn tại | C12: =COUNTIF(KHOAN_KHAC!$H$5:$H$39,"MÃ KHÔNG CÓ") -> 0 | D12: =IF(C12=0,"OK","LỖI") -> OK | E12: Sửa mã ở KHOAN_KHAC cột G
A13: 9 | B13: Tổng giờ BCC = tổng giờ LUONG_KHOAN | C13: =BCC_KHOAN!$AJ$102-SUM(LUONG_KHOAN!$G$6:$G$100) -> 0 | D13: =IF(C13=0,"OK","LỖI") -> OK | E13: Có dòng BCC ngoài vùng tính
A14: 10 | B14: Ô báo lỗi công thức trong LUONG_KHOAN | C14: =SUMPRODUCT(--ISERROR(LUONG_KHOAN!$A$6:$T$100)) -> 0 | D14: =IF(C14=0,"OK","LỖI") -> OK
A15: 11 | B15: Chi phí lương khoán bình quân (đ/tấn) – so với tháng trước | C15: =THAM_SO!$C$29 -> 316227.69 | D15: =IF(OR(C15<150000,C15>500000),"XEM LẠI","OK") -> OK | E15: Ngưỡng 150k–500k đ/tấn là tạm đặt để bắt nhầm đơn vị; HCNS chỉnh theo thực tế
A16: 12 | B16: ĐỘI XE: tài xế trong XE_CHUYEN / XE_CHI_PHI không có trong danh mục | C16: =COUNTIF(XE_CHUYEN!$C$5:$C$300,"MÃ KHÔNG CÓ")+COUNTIF(XE_CHI_PHI!$D$5:$D$500,"MÃ KHÔNG CÓ") -> 0 | D16: =IF(C16=0,"OK","LỖI") -> OK
A17: 13 | B17: ĐỘI XE: chuyến có tuyến không có trong bảng giá | C17: =COUNTIF(XE_CHUYEN!$J$5:$J$300,"TUYẾN KHÔNG CÓ") -> 0 | D17: =IF(C17=0,"OK","LỖI") -> OK | E17: Thêm tuyến vào XE_TUYEN
A18: 14 | B18: ĐỘI XE: chuyến thiếu phiếu điều động (x) | C18: =COUNTIF(XE_CHUYEN!$W$5:$W$300,"x") -> 2 | D18: =IF(C18=0,"OK","XEM LẠI") -> XEM LẠI | E18: Bổ sung chứng từ trước khi chi
A19: 15 | B19: ĐỘI XE: chi phí không có hoá đơn (x) nhưng "Được tính = Có" | C19: =COUNTIFS(XE_CHI_PHI!$L$5:$L$500,"x",XE_CHI_PHI!$J$5:$J$500,"Có") -> 8 | D19: =IF(C19=0,"OK","XEM LẠI") -> XEM LẠI | E19: Kế toán quyết định có chấp nhận không
B21: KẾT LUẬN | D21: =IF(COUNTIF(D5:D19,"LỖI")=0,"ĐƯỢC CHỐT","CHƯA ĐƯỢC CHỐT") -> ĐƯỢC CHỐT

Sheet XE_THAM_SO
A1: THAM SỐ LƯƠNG KHOÁN CHUYẾN ĐỘI XE CONTAINER
A2: File cũ chỉ ghi chép chuyến và chi phí, cột "Đơn giá chuyến / Hỗ trợ" để trống và Lương khoán (10.253.000) gõ tay vào Bảng lương. Các số dưới đây là VÍ DỤ để chạy công thức – HCNS điền theo quy chế lương tài xế.
B4: Tháng | C4: 2
B5: Năm | C5: 2026
B7: Tỷ giá quy đổi 1 LAK = ? VND | C7: 1.15 | D7: VÍ DỤ – lấy tỷ giá kế toán tháng
B8: Hỗ trợ vượt thời gian hành trình (đ/ngày vượt) | C8: 300000 | D8: VÍ DỤ – file cũ có cột "Hỗ trợ vượt thời gian/ngày" nhưng không có số
B9: Hỗ trợ dầu (đ/km) – 0 nếu công ty đổ dầu | C9: 0 | D9: VÍ DỤ – file cũ có cột "Hỗ trợ dầu/km" nhưng không có số
B10: Số ngày công/tháng để tính phép, lễ (tài xế khoán: không áp dụng) | C10: 0
B11: Tỷ lệ BHXH người lao động | C11: 0.105
B12: Làm tròn xuống đến (đ) | C12: 1000

Sheet XE_TUYEN
A1: BẢNG GIÁ KHOÁN THEO TUYẾN
A2: Mỗi tuyến một mã. Số ngày chuẩn = cột K "Số ngày hành trình (chuẩn)" file cũ. Đơn giá là VÍ DỤ – HCNS điền.
A4: Mã tuyến | B4: Hành trình | C4: Km chuẩn (cả đi về) | D4: Số ngày chuẩn | E4: Đơn giá chuyến (đ) | F4: Hỗ trợ vận chuyển (đ/tấn) | G4: Ghi chú
A5: NM-DN | B5: Nhà máy → Cảng Đà Nẵng / Tiên Sa → Nhà máy | C5: 220 | D5: 1 | E5: 1200000 | F5: 0 | G5: Chạy cảng xuất hàng
A6: NM-KT | B6: Nhà máy → Kon Tum / Ngọc Hồi → Nhà máy | C6: 700 | D6: 3 | E6: 3500000 | F6: 0
A7: NM-GL-CL | B7: Nhà máy → Gia Lai đóng hàng → Chu Lai → Nhà máy | C7: 800 | D7: 3 | E7: 3800000 | F7: 0
A8: NM-LAO-K2 | B8: Nhà máy → Kho 2 (Lào) → Nhà máy | C8: 900 | D8: 5 | E8: 6500000 | F8: 0 | G8: Có chi phí LAK dọc đường
A9: NM-MODA | B9: Nhà máy → Mỏ đá Tứ Hạ → Nhà máy | C9: 60 | D9: 1 | E9: 500000 | F9: 0

Sheet XE_CHUYEN
A1: NHẬT KÝ CHUYẾN – mỗi chuyến một dòng (thay cho 6 sheet tài xế)
A2: Nhập ô xanh. Lương chuyến = Đơn giá tuyến + Vượt ngày × hỗ trợ + Km × hỗ trợ dầu + Tấn × hỗ trợ vận chuyển. Dữ liệu mẫu lấy từ file tháng 02/2026.
A4: Số chuyến | B4: Mã NV tài xế | C4: Tài xế (tự tra) | D4: Ngày đi | E4: Ngày về | F4: Tổng ngày | G4: BS xe | H4: Rơ moóc | I4: Mã tuyến | J4: Hành trình (tự tra) | K4: Km đi | L4: Km về | M4: Nội dung / số cont | N4: Số PĐĐ | O4: Ngày chuẩn | P4: Vượt ngày | Q4: Đơn giá chuyến | R4: Hỗ trợ vượt ngày | S4: Hỗ trợ dầu | T4: Tấn hàng | U4: Hỗ trợ vận chuyển | V4: LƯƠNG CHUYẾN | W4: Phiếu điều động (v/x) | X4: Lý lịch vận tải (v/x) | Y4: Ghi chú
A5: 1 | B5: 046083009048 | C5: =IF(B5="","",IFERROR(INDEX(NV_TEN,MATCH(B5,NV_MA,0)),"MÃ KHÔNG CÓ")) -> Hoàng Hòa | D5: 46062 | E5: 46062 | F5: =IF(OR(D5="",E5=""),"",E5-D5+1) -> 1 | G5: 75H-03843 | H5: 75RM-00154 | I5: NM-DN | J5: =IF(I5="","",IFERROR(INDEX(TUYEN_MOTA,MATCH(I5,TUYEN_MA,0)),"TUYẾN KHÔNG CÓ")) -> Nhà máy → Cảng Đà Nẵng / Tiên Sa → Nhà máy | K5: 110 | L5: 110 | M5: CSGU 2292807, CXDU 2353815 | O5: =IF(I5="","",IFERROR(INDEX(TUYEN_NGAY,MATCH(I5,TUYEN_MA,0)),0)) -> 1 | P5: =IF(OR(F5="",O5=""),"",MAX(0,F5-O5)) -> 0 | Q5: =IF(I5="","",IFERROR(INDEX(TUYEN_DG,MATCH(I5,TUYEN_MA,0)),0)) -> 1200000 | R5: =IF(P5="","",P5*HT_VUOTNGAY) -> 0 | S5: =IF(I5="","",(N(K5)+N(L5))*HT_DAU_KM) -> 0 | T5: 0 | U5: =IF(I5="","",N(T5)*IFERROR(INDEX(TUYEN_HTVC,MATCH(I5,TUYEN_MA,0)),0)) -> 0 | V5: =IF(I5="","",Q5+R5+S5+U5) -> 1200000 | W5: v
A6: 2 | B6: 046083009048 | C6: =IF(B6="","",IFERROR(INDEX(NV_TEN,MATCH(B6,NV_MA,0)),"MÃ KHÔNG CÓ")) -> Hoàng Hòa | D6: 46063 | E6: 46065 | F6: =IF(OR(D6="",E6=""),"",E6-D6+1) -> 3 | G6: 75H-03843 | H6: 75RM-00150 | I6: NM-KT | J6: =IF(I6="","",IFERROR(INDEX(TUYEN_MOTA,MATCH(I6,TUYEN_MA,0)),"TUYẾN KHÔNG CÓ")) -> Nhà máy → Kon Tum / Ngọc Hồi → Nhà máy | K6: 350 | L6: 350 | M6: NYKU9787299, NYKU3552569 – Tiên Sa → bóc cont → Kon Tum | O6: =IF(I6="","",IFERROR(INDEX(TUYEN_NGAY,MATCH(I6,TUYEN_MA,0)),0)) -> 3 | P6: =IF(OR(F6="",O6=""),"",MAX(0,F6-O6)) -> 0 | Q6: =IF(I6="","",IFERROR(INDEX(TUYEN_DG,MATCH(I6,TUYEN_MA,0)),0)) -> 3500000 | R6: =IF(P6="","",P6*HT_VUOTNGAY) -> 0 | S6: =IF(I6="","",(N(K6)+N(L6))*HT_DAU_KM) -> 0 | T6: 0 | U6: =IF(I6="","",N(T6)*IFERROR(INDEX(TUYEN_HTVC,MATCH(I6,TUYEN_MA,0)),0)) -> 0 | V6: =IF(I6="","",Q6+R6+S6+U6) -> 3500000 | W6: v | Y6: PĐĐ 09/02 22h30
A7: 3 | B7: 046083009048 | C7: =IF(B7="","",IFERROR(INDEX(NV_TEN,MATCH(B7,NV_MA,0)),"MÃ KHÔNG CÓ")) -> Hoàng Hòa | D7: 46067 | E7: 46067 | F7: =IF(OR(D7="",E7=""),"",E7-D7+1) -> 1 | G7: 75H-03843 | H7: 75RM-00755 | I7: NM-DN | J7: =IF(I7="","",IFERROR(INDEX(TUYEN_MOTA,MATCH(I7,TUYEN_MA,0)),"TUYẾN KHÔNG CÓ")) -> Nhà máy → Cảng Đà Nẵng / Tiên Sa → Nhà máy | K7: 110 | L7: 110 | M7: GCXU2254455, ONEU3175884 | O7: =IF(I7="","",IFERROR(INDEX(TUYEN_NGAY,MATCH(I7,TUYEN_MA,0)),0)) -> 1 | P7: =IF(OR(F7="",O7=""),"",MAX(0,F7-O7)) -> 0 | Q7: =IF(I7="","",IFERROR(INDEX(TUYEN_DG,MATCH(I7,TUYEN_MA,0)),0)) -> 1200000 | R7: =IF(P7="","",P7*HT_VUOTNGAY) -> 0 | S7: =IF(I7="","",(N(K7)+N(L7))*HT_DAU_KM) -> 0 | T7: 0 | U7: =IF(I7="","",N(T7)*IFERROR(INDEX(TUYEN_HTVC,MATCH(I7,TUYEN_MA,0)),0)) -> 0 | V7: =IF(I7="","",Q7+R7+S7+U7) -> 1200000 | W7: v
A8: 4 | B8: 046083009048 | C8: =IF(B8="","",IFERROR(INDEX(NV_TEN,MATCH(B8,NV_MA,0)),"MÃ KHÔNG CÓ")) -> Hoàng Hòa | D8: 46073 | E8: 46077 | F8: =IF(OR(D8="",E8=""),"",E8-D8+1) -> 5 | G8: 75H-03843 | H8: 75RM-00492 | I8: NM-LAO-K2 | J8: =IF(I8="","",IFERROR(INDEX(TUYEN_MOTA,MATCH(I8,TUYEN_MA,0)),"TUYẾN KHÔNG CÓ")) -> Nhà máy → Kho 2 (Lào) → Nhà máy | K8: 450 | L8: 450 | M8: Chở hàng kho 2 | O8: =IF(I8="","",IFERROR(INDEX(TUYEN_NGAY,MATCH(I8,TUYEN_MA,0)),0)) -> 5 | P8: =IF(OR(F8="",O8=""),"",MAX(0,F8-O8)) -> 0 | Q8: =IF(I8="","",IFERROR(INDEX(TUYEN_DG,MATCH(I8,TUYEN_MA,0)),0)) -> 6500000 | R8: =IF(P8="","",P8*HT_VUOTNGAY) -> 0 | S8: =IF(I8="","",(N(K8)+N(L8))*HT_DAU_KM) -> 0 | T8: 0 | U8: =IF(I8="","",N(T8)*IFERROR(INDEX(TUYEN_HTVC,MATCH(I8,TUYEN_MA,0)),0)) -> 0 | V8: =IF(I8="","",Q8+R8+S8+U8) -> 6500000 | W8: v | X8: v
A9: 5 | B9: 046096005123 | C9: =IF(B9="","",IFERROR(INDEX(NV_TEN,MATCH(B9,NV_MA,0)),"MÃ KHÔNG CÓ")) -> Bùi Văn Nghĩa | D9: 46059 | E9: 46063 | F9: =IF(OR(D9="",E9=""),"",E9-D9+1) -> 5 | G9: 75H-04285 | H9: 75RM-00756 | I9: NM-GL-CL | J9: =IF(I9="","",IFERROR(INDEX(TUYEN_MOTA,MATCH(I9,TUYEN_MA,0)),"TUYẾN KHÔNG CÓ")) -> Nhà máy → Gia Lai đóng hàng → Chu Lai → Nhà máy | K9: 400 | L9: 400 | M9: CSNU 1538032, BSIU 2836867 – kéo cont rỗng vào Gia Lai, hạ Chu Lai | O9: =IF(I9="","",IFERROR(INDEX(TUYEN_NGAY,MATCH(I9,TUYEN_MA,0)),0)) -> 3 | P9: =IF(OR(F9="",O9=""),"",MAX(0,F9-O9)) -> 2 | Q9: =IF(I9="","",IFERROR(INDEX(TUYEN_DG,MATCH(I9,TUYEN_MA,0)),0)) -> 3800000 | R9: =IF(P9="","",P9*HT_VUOTNGAY) -> 600000 | S9: =IF(I9="","",(N(K9)+N(L9))*HT_DAU_KM) -> 0 | T9: 0 | U9: =IF(I9="","",N(T9)*IFERROR(INDEX(TUYEN_HTVC,MATCH(I9,TUYEN_MA,0)),0)) -> 0 | V9: =IF(I9="","",Q9+R9+S9+U9) -> 4400000 | W9: v | Y9: 06/02–08/02
A10: 6 | B10: 046096005123 | C10: =IF(B10="","",IFERROR(INDEX(NV_TEN,MATCH(B10,NV_MA,0)),"MÃ KHÔNG CÓ")) -> Bùi Văn Nghĩa | D10: 46065 | E10: 46068 | F10: =IF(OR(D10="",E10=""),"",E10-D10+1) -> 4 | G10: 75H-04285 | H10: 75RM-00495 | I10: NM-LAO-K2 | J10: =IF(I10="","",IFERROR(INDEX(TUYEN_MOTA,MATCH(I10,TUYEN_MA,0)),"TUYẾN KHÔNG CÓ")) -> Nhà máy → Kho 2 (Lào) → Nhà máy | K10: 450 | L10: 450 | M10: Chở hàng kho 2 | O10: =IF(I10="","",IFERROR(INDEX(TUYEN_NGAY,MATCH(I10,TUYEN_MA,0)),0)) -> 5 | P10: =IF(OR(F10="",O10=""),"",MAX(0,F10-O10)) -> 0 | Q10: =IF(I10="","",IFERROR(INDEX(TUYEN_DG,MATCH(I10,TUYEN_MA,0)),0)) -> 6500000 | R10: =IF(P10="","",P10*HT_VUOTNGAY) -> 0 | S10: =IF(I10="","",(N(K10)+N(L10))*HT_DAU_KM) -> 0 | T10: 0 | U10: =IF(I10="","",N(T10)*IFERROR(INDEX(TUYEN_HTVC,MATCH(I10,TUYEN_MA,0)),0)) -> 0 | V10: =IF(I10="","",Q10+R10+S10+U10) -> 6500000 | W10: v | X10: v
A11: 7 | B11: 046096005123 | C11: =IF(B11="","",IFERROR(INDEX(NV_TEN,MATCH(B11,NV_MA,0)),"MÃ KHÔNG CÓ")) -> Bùi Văn Nghĩa | D11: 46076 | E11: 46076 | F11: =IF(OR(D11="",E11=""),"",E11-D11+1) -> 1 | G11: 75H-04285 | I11: NM-DN | J11: =IF(I11="","",IFERROR(INDEX(TUYEN_MOTA,MATCH(I11,TUYEN_MA,0)),"TUYẾN KHÔNG CÓ")) -> Nhà máy → Cảng Đà Nẵng / Tiên Sa → Nhà máy | K11: 110 | L11: 110 | M11: NXKU 9913756 | O11: =IF(I11="","",IFERROR(INDEX(TUYEN_NGAY,MATCH(I11,TUYEN_MA,0)),0)) -> 1 | P11: =IF(OR(F11="",O11=""),"",MAX(0,F11-O11)) -> 0 | Q11: =IF(I11="","",IFERROR(INDEX(TUYEN_DG,MATCH(I11,TUYEN_MA,0)),0)) -> 1200000 | R11: =IF(P11="","",P11*HT_VUOTNGAY) -> 0 | S11: =IF(I11="","",(N(K11)+N(L11))*HT_DAU_KM) -> 0 | T11: 0 | U11: =IF(I11="","",N(T11)*IFERROR(INDEX(TUYEN_HTVC,MATCH(I11,TUYEN_MA,0)),0)) -> 0 | V11: =IF(I11="","",Q11+R11+S11+U11) -> 1200000 | W11: x | Y11: Thiếu phiếu điều động
A12: 8 | B12: 046096005123 | C12: =IF(B12="","",IFERROR(INDEX(NV_TEN,MATCH(B12,NV_MA,0)),"MÃ KHÔNG CÓ")) -> Bùi Văn Nghĩa | D12: 46081 | E12: 46081 | F12: =IF(OR(D12="",E12=""),"",E12-D12+1) -> 1 | G12: 75H-04285 | I12: NM-DN | J12: =IF(I12="","",IFERROR(INDEX(TUYEN_MOTA,MATCH(I12,TUYEN_MA,0)),"TUYẾN KHÔNG CÓ")) -> Nhà máy → Cảng Đà Nẵng / Tiên Sa → Nhà máy | K12: 110 | L12: 110 | M12: SIKU 3024100, SIKU 3029734 | O12: =IF(I12="","",IFERROR(INDEX(TUYEN_NGAY,MATCH(I12,TUYEN_MA,0)),0)) -> 1 | P12: =IF(OR(F12="",O12=""),"",MAX(0,F12-O12)) -> 0 | Q12: =IF(I12="","",IFERROR(INDEX(TUYEN_DG,MATCH(I12,TUYEN_MA,0)),0)) -> 1200000 | R12: =IF(P12="","",P12*HT_VUOTNGAY) -> 0 | S12: =IF(I12="","",(N(K12)+N(L12))*HT_DAU_KM) -> 0 | T12: 0 | U12: =IF(I12="","",N(T12)*IFERROR(INDEX(TUYEN_HTVC,MATCH(I12,TUYEN_MA,0)),0)) -> 0 | V12: =IF(I12="","",Q12+R12+S12+U12) -> 1200000 | W12: x
A13: 9 | B13: 046082013042 | C13: =IF(B13="","",IFERROR(INDEX(NV_TEN,MATCH(B13,NV_MA,0)),"MÃ KHÔNG CÓ")) -> Nguyễn Hữu Mạnh Cường | D13: 46054 | E13: 46054 | F13: =IF(OR(D13="",E13=""),"",E13-D13+1) -> 1 | G13: 75H-03841 | H13: 75RM-00498 | I13: NM-DN | J13: =IF(I13="","",IFERROR(INDEX(TUYEN_MOTA,MATCH(I13,TUYEN_MA,0)),"TUYẾN KHÔNG CÓ")) -> Nhà máy → Cảng Đà Nẵng / Tiên Sa → Nhà máy | K13: 110 | L13: 110 | M13: ONEU 2971634, ONEU 3130663 | O13: =IF(I13="","",IFERROR(INDEX(TUYEN_NGAY,MATCH(I13,TUYEN_MA,0)),0)) -> 1 | P13: =IF(OR(F13="",O13=""),"",MAX(0,F13-O13)) -> 0 | Q13: =IF(I13="","",IFERROR(INDEX(TUYEN_DG,MATCH(I13,TUYEN_MA,0)),0)) -> 1200000 | R13: =IF(P13="","",P13*HT_VUOTNGAY) -> 0 | S13: =IF(I13="","",(N(K13)+N(L13))*HT_DAU_KM) -> 0 | T13: 0 | U13: =IF(I13="","",N(T13)*IFERROR(INDEX(TUYEN_HTVC,MATCH(I13,TUYEN_MA,0)),0)) -> 0 | V13: =IF(I13="","",Q13+R13+S13+U13) -> 1200000 | W13: v
A14: 10 | B14: 046082013042 | C14: =IF(B14="","",IFERROR(INDEX(NV_TEN,MATCH(B14,NV_MA,0)),"MÃ KHÔNG CÓ")) -> Nguyễn Hữu Mạnh Cường | D14: 46056 | E14: 46056 | F14: =IF(OR(D14="",E14=""),"",E14-D14+1) -> 1 | G14: 75H-03841 | H14: 75RM-00154 | I14: NM-DN | J14: =IF(I14="","",IFERROR(INDEX(TUYEN_MOTA,MATCH(I14,TUYEN_MA,0)),"TUYẾN KHÔNG CÓ")) -> Nhà máy → Cảng Đà Nẵng / Tiên Sa → Nhà máy | K14: 110 | L14: 110 | M14: UETU 2184681, TGBU 3014343 | O14: =IF(I14="","",IFERROR(INDEX(TUYEN_NGAY,MATCH(I14,TUYEN_MA,0)),0)) -> 1 | P14: =IF(OR(F14="",O14=""),"",MAX(0,F14-O14)) -> 0 | Q14: =IF(I14="","",IFERROR(INDEX(TUYEN_DG,MATCH(I14,TUYEN_MA,0)),0)) -> 1200000 | R14: =IF(P14="","",P14*HT_VUOTNGAY) -> 0 | S14: =IF(I14="","",(N(K14)+N(L14))*HT_DAU_KM) -> 0 | T14: 0 | U14: =IF(I14="","",N(T14)*IFERROR(INDEX(TUYEN_HTVC,MATCH(I14,TUYEN_MA,0)),0)) -> 0 | V14: =IF(I14="","",Q14+R14+S14+U14) -> 1200000 | W14: v
A15: 11 | B15: 046082013042 | C15: =IF(B15="","",IFERROR(INDEX(NV_TEN,MATCH(B15,NV_MA,0)),"MÃ KHÔNG CÓ")) -> Nguyễn Hữu Mạnh Cường | D15: 46058 | E15: 46061 | F15: =IF(OR(D15="",E15=""),"",E15-D15+1) -> 4 | G15: 75H-03841 | H15: 75RM-00151 | I15: NM-KT | J15: =IF(I15="","",IFERROR(INDEX(TUYEN_MOTA,MATCH(I15,TUYEN_MA,0)),"TUYẾN KHÔNG CÓ")) -> Nhà máy → Kon Tum / Ngọc Hồi → Nhà máy | K15: 350 | L15: 350 | M15: Kon Tum – Chu Lai | N15: 03843 | O15: =IF(I15="","",IFERROR(INDEX(TUYEN_NGAY,MATCH(I15,TUYEN_MA,0)),0)) -> 3 | P15: =IF(OR(F15="",O15=""),"",MAX(0,F15-O15)) -> 1 | Q15: =IF(I15="","",IFERROR(INDEX(TUYEN_DG,MATCH(I15,TUYEN_MA,0)),0)) -> 3500000 | R15: =IF(P15="","",P15*HT_VUOTNGAY) -> 300000 | S15: =IF(I15="","",(N(K15)+N(L15))*HT_DAU_KM) -> 0 | T15: 0 | U15: =IF(I15="","",N(T15)*IFERROR(INDEX(TUYEN_HTVC,MATCH(I15,TUYEN_MA,0)),0)) -> 0 | V15: =IF(I15="","",Q15+R15+S15+U15) -> 3800000 | W15: v | Y15: Vượt 1 ngày
A16: 12 | B16: 046082013042 | C16: =IF(B16="","",IFERROR(INDEX(NV_TEN,MATCH(B16,NV_MA,0)),"MÃ KHÔNG CÓ")) -> Nguyễn Hữu Mạnh Cường | D16: 46064 | E16: 46064 | F16: =IF(OR(D16="",E16=""),"",E16-D16+1) -> 1 | G16: 75H-03841 | H16: 75RM-0154 | I16: NM-DN | J16: =IF(I16="","",IFERROR(INDEX(TUYEN_MOTA,MATCH(I16,TUYEN_MA,0)),"TUYẾN KHÔNG CÓ")) -> Nhà máy → Cảng Đà Nẵng / Tiên Sa → Nhà máy | K16: 110 | L16: 110 | M16: ONEU 3020223, SEKU 1504680 | O16: =IF(I16="","",IFERROR(INDEX(TUYEN_NGAY,MATCH(I16,TUYEN_MA,0)),0)) -> 1 | P16: =IF(OR(F16="",O16=""),"",MAX(0,F16-O16)) -> 0 | Q16: =IF(I16="","",IFERROR(INDEX(TUYEN_DG,MATCH(I16,TUYEN_MA,0)),0)) -> 1200000 | R16: =IF(P16="","",P16*HT_VUOTNGAY) -> 0 | S16: =IF(I16="","",(N(K16)+N(L16))*HT_DAU_KM) -> 0 | T16: 0 | U16: =IF(I16="","",N(T16)*IFERROR(INDEX(TUYEN_HTVC,MATCH(I16,TUYEN_MA,0)),0)) -> 0 | V16: =IF(I16="","",Q16+R16+S16+U16) -> 1200000 | W16: v
A17: 13 | B17: 046082013042 | C17: =IF(B17="","",IFERROR(INDEX(NV_TEN,MATCH(B17,NV_MA,0)),"MÃ KHÔNG CÓ")) -> Nguyễn Hữu Mạnh Cường | D17: 46065 | E17: 46065 | F17: =IF(OR(D17="",E17=""),"",E17-D17+1) -> 1 | G17: 75H-03841 | H17: 75RM-0755 | I17: NM-DN | J17: =IF(I17="","",IFERROR(INDEX(TUYEN_MOTA,MATCH(I17,TUYEN_MA,0)),"TUYẾN KHÔNG CÓ")) -> Nhà máy → Cảng Đà Nẵng / Tiên Sa → Nhà máy | K17: 110 | L17: 110 | M17: FTAU1312235, ONEU 2671262 | O17: =IF(I17="","",IFERROR(INDEX(TUYEN_NGAY,MATCH(I17,TUYEN_MA,0)),0)) -> 1 | P17: =IF(OR(F17="",O17=""),"",MAX(0,F17-O17)) -> 0 | Q17: =IF(I17="","",IFERROR(INDEX(TUYEN_DG,MATCH(I17,TUYEN_MA,0)),0)) -> 1200000 | R17: =IF(P17="","",P17*HT_VUOTNGAY) -> 0 | S17: =IF(I17="","",(N(K17)+N(L17))*HT_DAU_KM) -> 0 | T17: 0 | U17: =IF(I17="","",N(T17)*IFERROR(INDEX(TUYEN_HTVC,MATCH(I17,TUYEN_MA,0)),0)) -> 0 | V17: =IF(I17="","",Q17+R17+S17+U17) -> 1200000 | W17: v
A18: 14 | B18: 046082013042 | C18: =IF(B18="","",IFERROR(INDEX(NV_TEN,MATCH(B18,NV_MA,0)),"MÃ KHÔNG CÓ")) -> Nguyễn Hữu Mạnh Cường | D18: 46068 | E18: 46068 | F18: =IF(OR(D18="",E18=""),"",E18-D18+1) -> 1 | G18: 75H-03841 | H18: 75RM-0151 | I18: NM-DN | J18: =IF(I18="","",IFERROR(INDEX(TUYEN_MOTA,MATCH(I18,TUYEN_MA,0)),"TUYẾN KHÔNG CÓ")) -> Nhà máy → Cảng Đà Nẵng / Tiên Sa → Nhà máy | K18: 110 | L18: 110 | M18: ONEU 2417303, ONEU 3040111 | O18: =IF(I18="","",IFERROR(INDEX(TUYEN_NGAY,MATCH(I18,TUYEN_MA,0)),0)) -> 1 | P18: =IF(OR(F18="",O18=""),"",MAX(0,F18-O18)) -> 0 | Q18: =IF(I18="","",IFERROR(INDEX(TUYEN_DG,MATCH(I18,TUYEN_MA,0)),0)) -> 1200000 | R18: =IF(P18="","",P18*HT_VUOTNGAY) -> 0 | S18: =IF(I18="","",(N(K18)+N(L18))*HT_DAU_KM) -> 0 | T18: 0 | U18: =IF(I18="","",N(T18)*IFERROR(INDEX(TUYEN_HTVC,MATCH(I18,TUYEN_MA,0)),0)) -> 0 | V18: =IF(I18="","",Q18+R18+S18+U18) -> 1200000 | W18: v
A19: 15 | B19: 046082013042 | C19: =IF(B19="","",IFERROR(INDEX(NV_TEN,MATCH(B19,NV_MA,0)),"MÃ KHÔNG CÓ")) -> Nguyễn Hữu Mạnh Cường | D19: 46078 | E19: 46078 | F19: =IF(OR(D19="",E19=""),"",E19-D19+1) -> 1 | G19: 75H-03841 | H19: 75RM-00756 | I19: NM-DN | J19: =IF(I19="","",IFERROR(INDEX(TUYEN_MOTA,MATCH(I19,TUYEN_MA,0)),"TUYẾN KHÔNG CÓ")) -> Nhà máy → Cảng Đà Nẵng / Tiên Sa → Nhà máy | K19: 110 | L19: 110 | M19: EGSU3535635, GCXU2214703 | O19: =IF(I19="","",IFERROR(INDEX(TUYEN_NGAY,MATCH(I19,TUYEN_MA,0)),0)) -> 1 | P19: =IF(OR(F19="",O19=""),"",MAX(0,F19-O19)) -> 0 | Q19: =IF(I19="","",IFERROR(INDEX(TUYEN_DG,MATCH(I19,TUYEN_MA,0)),0)) -> 1200000 | R19: =IF(P19="","",P19*HT_VUOTNGAY) -> 0 | S19: =IF(I19="","",(N(K19)+N(L19))*HT_DAU_KM) -> 0 | T19: 0 | U19: =IF(I19="","",N(T19)*IFERROR(INDEX(TUYEN_HTVC,MATCH(I19,TUYEN_MA,0)),0)) -> 0 | V19: =IF(I19="","",Q19+R19+S19+U19) -> 1200000 | W19: v
A20: 16 | B20: 046082013042 | C20: =IF(B20="","",IFERROR(INDEX(NV_TEN,MATCH(B20,NV_MA,0)),"MÃ KHÔNG CÓ")) -> Nguyễn Hữu Mạnh Cường | D20: 46080 | E20: 46080 | F20: =IF(OR(D20="",E20=""),"",E20-D20+1) -> 1 | G20: 75H-03841 | H20: 75RM-00494 | I20: NM-MODA | J20: =IF(I20="","",IFERROR(INDEX(TUYEN_MOTA,MATCH(I20,TUYEN_MA,0)),"TUYẾN KHÔNG CÓ")) -> Nhà máy → Mỏ đá Tứ Hạ → Nhà máy | K20: 30 | L20: 30 | M20: Đi chở đá (Tứ Hạ) | O20: =IF(I20="","",IFERROR(INDEX(TUYEN_NGAY,MATCH(I20,TUYEN_MA,0)),0)) -> 1 | P20: =IF(OR(F20="",O20=""),"",MAX(0,F20-O20)) -> 0 | Q20: =IF(I20="","",IFERROR(INDEX(TUYEN_DG,MATCH(I20,TUYEN_MA,0)),0)) -> 500000 | R20: =IF(P20="","",P20*HT_VUOTNGAY) -> 0 | S20: =IF(I20="","",(N(K20)+N(L20))*HT_DAU_KM) -> 0 | T20: 0 | U20: =IF(I20="","",N(T20)*IFERROR(INDEX(TUYEN_HTVC,MATCH(I20,TUYEN_MA,0)),0)) -> 0 | V20: =IF(I20="","",Q20+R20+S20+U20) -> 500000
A21: =IF(B21="","",ROW()-4) | C21: =IF(B21="","",IFERROR(INDEX(NV_TEN,MATCH(B21,NV_MA,0)),"MÃ KHÔNG CÓ")) | F21: =IF(OR(D21="",E21=""),"",E21-D21+1) | J21: =IF(I21="","",IFERROR(INDEX(TUYEN_MOTA,MATCH(I21,TUYEN_MA,0)),"TUYẾN KHÔNG CÓ")) | O21: =IF(I21="","",IFERROR(INDEX(TUYEN_NGAY,MATCH(I21,TUYEN_MA,0)),0)) | P21: =IF(OR(F21="",O21=""),"",MAX(0,F21-O21)) | Q21: =IF(I21="","",IFERROR(INDEX(TUYEN_DG,MATCH(I21,TUYEN_MA,0)),0)) | R21: =IF(P21="","",P21*HT_VUOTNGAY) | S21: =IF(I21="","",(N(K21)+N(L21))*HT_DAU_KM) | U21: =IF(I21="","",N(T21)*IFERROR(INDEX(TUYEN_HTVC,MATCH(I21,TUYEN_MA,0)),0)) | V21: =IF(I21="","",Q21+R21+S21+U21)
A22: =IF(B22="","",ROW()-4) | C22: =IF(B22="","",IFERROR(INDEX(NV_TEN,MATCH(B22,NV_MA,0)),"MÃ KHÔNG CÓ")) | F22: =IF(OR(D22="",E22=""),"",E22-D22+1) | J22: =IF(I22="","",IFERROR(INDEX(TUYEN_MOTA,MATCH(I22,TUYEN_MA,0)),"TUYẾN KHÔNG CÓ")) | O22: =IF(I22="","",IFERROR(INDEX(TUYEN_NGAY,MATCH(I22,TUYEN_MA,0)),0)) | P22: =IF(OR(F22="",O22=""),"",MAX(0,F22-O22)) | Q22: =IF(I22="","",IFERROR(INDEX(TUYEN_DG,MATCH(I22,TUYEN_MA,0)),0)) | R22: =IF(P22="","",P22*HT_VUOTNGAY) | S22: =IF(I22="","",(N(K22)+N(L22))*HT_DAU_KM) | U22: =IF(I22="","",N(T22)*IFERROR(INDEX(TUYEN_HTVC,MATCH(I22,TUYEN_MA,0)),0)) | V22: =IF(I22="","",Q22+R22+S22+U22)
A23: =IF(B23="","",ROW()-4) | C23: =IF(B23="","",IFERROR(INDEX(NV_TEN,MATCH(B23,NV_MA,0)),"MÃ KHÔNG CÓ")) | F23: =IF(OR(D23="",E23=""),"",E23-D23+1) | J23: =IF(I23="","",IFERROR(INDEX(TUYEN_MOTA,MATCH(I23,TUYEN_MA,0)),"TUYẾN KHÔNG CÓ")) | O23: =IF(I23="","",IFERROR(INDEX(TUYEN_NGAY,MATCH(I23,TUYEN_MA,0)),0)) | P23: =IF(OR(F23="",O23=""),"",MAX(0,F23-O23)) | Q23: =IF(I23="","",IFERROR(INDEX(TUYEN_DG,MATCH(I23,TUYEN_MA,0)),0)) | R23: =IF(P23="","",P23*HT_VUOTNGAY) | S23: =IF(I23="","",(N(K23)+N(L23))*HT_DAU_KM) | U23: =IF(I23="","",N(T23)*IFERROR(INDEX(TUYEN_HTVC,MATCH(I23,TUYEN_MA,0)),0)) | V23: =IF(I23="","",Q23+R23+S23+U23)
A24: =IF(B24="","",ROW()-4) | C24: =IF(B24="","",IFERROR(INDEX(NV_TEN,MATCH(B24,NV_MA,0)),"MÃ KHÔNG CÓ")) | F24: =IF(OR(D24="",E24=""),"",E24-D24+1) | J24: =IF(I24="","",IFERROR(INDEX(TUYEN_MOTA,MATCH(I24,TUYEN_MA,0)),"TUYẾN KHÔNG CÓ")) | O24: =IF(I24="","",IFERROR(INDEX(TUYEN_NGAY,MATCH(I24,TUYEN_MA,0)),0)) | P24: =IF(OR(F24="",O24=""),"",MAX(0,F24-O24)) | Q24: =IF(I24="","",IFERROR(INDEX(TUYEN_DG,MATCH(I24,TUYEN_MA,0)),0)) | R24: =IF(P24="","",P24*HT_VUOTNGAY) | S24: =IF(I24="","",(N(K24)+N(L24))*HT_DAU_KM) | U24: =IF(I24="","",N(T24)*IFERROR(INDEX(TUYEN_HTVC,MATCH(I24,TUYEN_MA,0)),0)) | V24: =IF(I24="","",Q24+R24+S24+U24)
A25: =IF(B25="","",ROW()-4) | C25: =IF(B25="","",IFERROR(INDEX(NV_TEN,MATCH(B25,NV_MA,0)),"MÃ KHÔNG CÓ")) | F25: =IF(OR(D25="",E25=""),"",E25-D25+1) | J25: =IF(I25="","",IFERROR(INDEX(TUYEN_MOTA,MATCH(I25,TUYEN_MA,0)),"TUYẾN KHÔNG CÓ")) | O25: =IF(I25="","",IFERROR(INDEX(TUYEN_NGAY,MATCH(I25,TUYEN_MA,0)),0)) | P25: =IF(OR(F25="",O25=""),"",MAX(0,F25-O25)) | Q25: =IF(I25="","",IFERROR(INDEX(TUYEN_DG,MATCH(I25,TUYEN_MA,0)),0)) | R25: =IF(P25="","",P25*HT_VUOTNGAY) | S25: =IF(I25="","",(N(K25)+N(L25))*HT_DAU_KM) | U25: =IF(I25="","",N(T25)*IFERROR(INDEX(TUYEN_HTVC,MATCH(I25,TUYEN_MA,0)),0)) | V25: =IF(I25="","",Q25+R25+S25+U25)
A26: =IF(B26="","",ROW()-4) | C26: =IF(B26="","",IFERROR(INDEX(NV_TEN,MATCH(B26,NV_MA,0)),"MÃ KHÔNG CÓ")) | F26: =IF(OR(D26="",E26=""),"",E26-D26+1) | J26: =IF(I26="","",IFERROR(INDEX(TUYEN_MOTA,MATCH(I26,TUYEN_MA,0)),"TUYẾN KHÔNG CÓ")) | O26: =IF(I26="","",IFERROR(INDEX(TUYEN_NGAY,MATCH(I26,TUYEN_MA,0)),0)) | P26: =IF(OR(F26="",O26=""),"",MAX(0,F26-O26)) | Q26: =IF(I26="","",IFERROR(INDEX(TUYEN_DG,MATCH(I26,TUYEN_MA,0)),0)) | R26: =IF(P26="","",P26*HT_VUOTNGAY) | S26: =IF(I26="","",(N(K26)+N(L26))*HT_DAU_KM) | U26: =IF(I26="","",N(T26)*IFERROR(INDEX(TUYEN_HTVC,MATCH(I26,TUYEN_MA,0)),0)) | V26: =IF(I26="","",Q26+R26+S26+U26)
A27: =IF(B27="","",ROW()-4) | C27: =IF(B27="","",IFERROR(INDEX(NV_TEN,MATCH(B27,NV_MA,0)),"MÃ KHÔNG CÓ")) | F27: =IF(OR(D27="",E27=""),"",E27-D27+1) | J27: =IF(I27="","",IFERROR(INDEX(TUYEN_MOTA,MATCH(I27,TUYEN_MA,0)),"TUYẾN KHÔNG CÓ")) | O27: =IF(I27="","",IFERROR(INDEX(TUYEN_NGAY,MATCH(I27,TUYEN_MA,0)),0)) | P27: =IF(OR(F27="",O27=""),"",MAX(0,F27-O27)) | Q27: =IF(I27="","",IFERROR(INDEX(TUYEN_DG,MATCH(I27,TUYEN_MA,0)),0)) | R27: =IF(P27="","",P27*HT_VUOTNGAY) | S27: =IF(I27="","",(N(K27)+N(L27))*HT_DAU_KM) | U27: =IF(I27="","",N(T27)*IFERROR(INDEX(TUYEN_HTVC,MATCH(I27,TUYEN_MA,0)),0)) | V27: =IF(I27="","",Q27+R27+S27+U27)
A28: =IF(B28="","",ROW()-4) | C28: =IF(B28="","",IFERROR(INDEX(NV_TEN,MATCH(B28,NV_MA,0)),"MÃ KHÔNG CÓ")) | F28: =IF(OR(D28="",E28=""),"",E28-D28+1) | J28: =IF(I28="","",IFERROR(INDEX(TUYEN_MOTA,MATCH(I28,TUYEN_MA,0)),"TUYẾN KHÔNG CÓ")) | O28: =IF(I28="","",IFERROR(INDEX(TUYEN_NGAY,MATCH(I28,TUYEN_MA,0)),0)) | P28: =IF(OR(F28="",O28=""),"",MAX(0,F28-O28)) | Q28: =IF(I28="","",IFERROR(INDEX(TUYEN_DG,MATCH(I28,TUYEN_MA,0)),0)) | R28: =IF(P28="","",P28*HT_VUOTNGAY) | S28: =IF(I28="","",(N(K28)+N(L28))*HT_DAU_KM) | U28: =IF(I28="","",N(T28)*IFERROR(INDEX(TUYEN_HTVC,MATCH(I28,TUYEN_MA,0)),0)) | V28: =IF(I28="","",Q28+R28+S28+U28)
A29: =IF(B29="","",ROW()-4) | C29: =IF(B29="","",IFERROR(INDEX(NV_TEN,MATCH(B29,NV_MA,0)),"MÃ KHÔNG CÓ")) | F29: =IF(OR(D29="",E29=""),"",E29-D29+1) | J29: =IF(I29="","",IFERROR(INDEX(TUYEN_MOTA,MATCH(I29,TUYEN_MA,0)),"TUYẾN KHÔNG CÓ")) | O29: =IF(I29="","",IFERROR(INDEX(TUYEN_NGAY,MATCH(I29,TUYEN_MA,0)),0)) | P29: =IF(OR(F29="",O29=""),"",MAX(0,F29-O29)) | Q29: =IF(I29="","",IFERROR(INDEX(TUYEN_DG,MATCH(I29,TUYEN_MA,0)),0)) | R29: =IF(P29="","",P29*HT_VUOTNGAY) | S29: =IF(I29="","",(N(K29)+N(L29))*HT_DAU_KM) | U29: =IF(I29="","",N(T29)*IFERROR(INDEX(TUYEN_HTVC,MATCH(I29,TUYEN_MA,0)),0)) | V29: =IF(I29="","",Q29+R29+S29+U29)
A30: =IF(B30="","",ROW()-4) | C30: =IF(B30="","",IFERROR(INDEX(NV_TEN,MATCH(B30,NV_MA,0)),"MÃ KHÔNG CÓ")) | F30: =IF(OR(D30="",E30=""),"",E30-D30+1) | J30: =IF(I30="","",IFERROR(INDEX(TUYEN_MOTA,MATCH(I30,TUYEN_MA,0)),"TUYẾN KHÔNG CÓ")) | O30: =IF(I30="","",IFERROR(INDEX(TUYEN_NGAY,MATCH(I30,TUYEN_MA,0)),0)) | P30: =IF(OR(F30="",O30=""),"",MAX(0,F30-O30)) | Q30: =IF(I30="","",IFERROR(INDEX(TUYEN_DG,MATCH(I30,TUYEN_MA,0)),0)) | R30: =IF(P30="","",P30*HT_VUOTNGAY) | S30: =IF(I30="","",(N(K30)+N(L30))*HT_DAU_KM) | U30: =IF(I30="","",N(T30)*IFERROR(INDEX(TUYEN_HTVC,MATCH(I30,TUYEN_MA,0)),0)) | V30: =IF(I30="","",Q30+R30+S30+U30)
A31: =IF(B31="","",ROW()-4) | C31: =IF(B31="","",IFERROR(INDEX(NV_TEN,MATCH(B31,NV_MA,0)),"MÃ KHÔNG CÓ")) | F31: =IF(OR(D31="",E31=""),"",E31-D31+1) | J31: =IF(I31="","",IFERROR(INDEX(TUYEN_MOTA,MATCH(I31,TUYEN_MA,0)),"TUYẾN KHÔNG CÓ")) | O31: =IF(I31="","",IFERROR(INDEX(TUYEN_NGAY,MATCH(I31,TUYEN_MA,0)),0)) | P31: =IF(OR(F31="",O31=""),"",MAX(0,F31-O31)) | Q31: =IF(I31="","",IFERROR(INDEX(TUYEN_DG,MATCH(I31,TUYEN_MA,0)),0)) | R31: =IF(P31="","",P31*HT_VUOTNGAY) | S31: =IF(I31="","",(N(K31)+N(L31))*HT_DAU_KM) | U31: =IF(I31="","",N(T31)*IFERROR(INDEX(TUYEN_HTVC,MATCH(I31,TUYEN_MA,0)),0)) | V31: =IF(I31="","",Q31+R31+S31+U31)
A32: =IF(B32="","",ROW()-4) | C32: =IF(B32="","",IFERROR(INDEX(NV_TEN,MATCH(B32,NV_MA,0)),"MÃ KHÔNG CÓ")) | F32: =IF(OR(D32="",E32=""),"",E32-D32+1) | J32: =IF(I32="","",IFERROR(INDEX(TUYEN_MOTA,MATCH(I32,TUYEN_MA,0)),"TUYẾN KHÔNG CÓ")) | O32: =IF(I32="","",IFERROR(INDEX(TUYEN_NGAY,MATCH(I32,TUYEN_MA,0)),0)) | P32: =IF(OR(F32="",O32=""),"",MAX(0,F32-O32)) | Q32: =IF(I32="","",IFERROR(INDEX(TUYEN_DG,MATCH(I32,TUYEN_MA,0)),0)) | R32: =IF(P32="","",P32*HT_VUOTNGAY) | S32: =IF(I32="","",(N(K32)+N(L32))*HT_DAU_KM) | U32: =IF(I32="","",N(T32)*IFERROR(INDEX(TUYEN_HTVC,MATCH(I32,TUYEN_MA,0)),0)) | V32: =IF(I32="","",Q32+R32+S32+U32)
... A199: =IF(B199="","",ROW()-4) | C199: =IF(B199="","",IFERROR(INDEX(NV_TEN,MATCH(B199,NV_MA,0)),"MÃ KHÔNG CÓ")) | F199: =IF(OR(D199="",E199=""),"",E199-D199+1) | J199: =IF(I199="","",IFERROR(INDEX(TUYEN_MOTA,MATCH(I199,TUYEN_MA,0)),"TUYẾN KHÔNG CÓ")) | O199: =IF(I199="","",IFERROR(INDEX(TUYEN_NGAY,MATCH(I199,TUYEN_MA,0)),0)) | P199: =IF(OR(F199="",O199=""),"",MAX(0,F199-O199)) | Q199: =IF(I199="","",IFERROR(INDEX(TUYEN_DG,MATCH(I199,TUYEN_MA,0)),0)) | R199: =IF(P199="","",P199*HT_VUOTNGAY) | S199: =IF(I199="","",(N(K199)+N(L199))*HT_DAU_KM) | U199: =IF(I199="","",N(T199)*IFERROR(INDEX(TUYEN_HTVC,MATCH(I199,TUYEN_MA,0)),0)) | V199: =IF(I199="","",Q199+R199+S199+U199)

Sheet XE_CHI_PHI
A1: TẠM ỨNG & CHI PHÍ PHÁT SINH ĐỘI XE – mỗi khoản một dòng
A2: Loại: "Tạm ứng" (công ty đưa tiền) hoặc "Chi phí" (tài xế đã chi). Tiền tệ VND/LAK. "Được tính" = công ty chấp nhận hoàn. Dữ liệu mẫu từ file tháng 02/2026.
A4: STT | B4: Ngày | C4: Mã NV tài xế | D4: Tài xế (tự tra) | E4: Số chuyến | F4: Nội dung | G4: Loại | H4: Tiền tệ | I4: Số tiền | J4: Được tính (Có/Không) | K4: Quy đổi VND | L4: Hoá đơn (v/x) | M4: Ghi chú
A5: 1 | B5: 46057 | C5: 046083009048 | D5: =IF(C5="","",IFERROR(INDEX(NV_TEN,MATCH(C5,NV_MA,0)),"MÃ KHÔNG CÓ")) -> Hoàng Hòa | F5: Đổ thêm dầu bên Lào | G5: Tạm ứng | H5: LAK | I5: 5000000 | J5: Có | K5: =IF(I5="","",IF(H5="LAK",I5*TYGIA_LAK,I5)) -> 5750000 | L5: v
A6: 2 | B6: 46059 | C6: 046083009048 | D6: =IF(C6="","",IFERROR(INDEX(NV_TEN,MATCH(C6,NV_MA,0)),"MÃ KHÔNG CÓ")) -> Hoàng Hòa | F6: CA từ Hình Hợp → Kho 2 | G6: Chi phí | H6: LAK | I6: 600000 | J6: Có | K6: =IF(I6="","",IF(H6="LAK",I6*TYGIA_LAK,I6)) -> 690000 | L6: x
A7: 3 | B7: 46059 | C7: 046083009048 | D7: =IF(C7="","",IFERROR(INDEX(NV_TEN,MATCH(C7,NV_MA,0)),"MÃ KHÔNG CÓ")) -> Hoàng Hòa | F7: Trạm cân Nam Thon | G7: Chi phí | H7: LAK | I7: 1000000 | J7: Có | K7: =IF(I7="","",IF(H7="LAK",I7*TYGIA_LAK,I7)) -> 1150000
A8: 4 | B8: 46059 | C8: 046083009048 | D8: =IF(C8="","",IFERROR(INDEX(NV_TEN,MATCH(C8,NV_MA,0)),"MÃ KHÔNG CÓ")) -> Hoàng Hòa | F8: Trạm cân Tha Khẹt | G8: Chi phí | H8: LAK | I8: 1000000 | J8: Có | K8: =IF(I8="","",IF(H8="LAK",I8*TYGIA_LAK,I8)) -> 1150000
A9: 5 | B9: 46059 | C9: 046083009048 | D9: =IF(C9="","",IFERROR(INDEX(NV_TEN,MATCH(C9,NV_MA,0)),"MÃ KHÔNG CÓ")) -> Hoàng Hòa | F9: CA Tha Khẹt | G9: Chi phí | H9: LAK | I9: 500000 | J9: Có | K9: =IF(I9="","",IF(H9="LAK",I9*TYGIA_LAK,I9)) -> 575000
A10: 6 | B10: 46059 | C10: 046083009048 | D10: =IF(C10="","",IFERROR(INDEX(NV_TEN,MATCH(C10,NV_MA,0)),"MÃ KHÔNG CÓ")) -> Hoàng Hòa | F10: CA Salavan | G10: Chi phí | H10: LAK | I10: 200000 | J10: Có | K10: =IF(I10="","",IF(H10="LAK",I10*TYGIA_LAK,I10)) -> 230000
A11: 7 | B11: 46059 | C11: 046083009048 | D11: =IF(C11="","",IFERROR(INDEX(NV_TEN,MATCH(C11,NV_MA,0)),"MÃ KHÔNG CÓ")) -> Hoàng Hòa | F11: CA LN Savannakhet | G11: Chi phí | H11: LAK | I11: 600000 | J11: Có | K11: =IF(I11="","",IF(H11="LAK",I11*TYGIA_LAK,I11)) -> 690000
A12: 8 | B12: 46059 | C12: 046083009048 | D12: =IF(C12="","",IFERROR(INDEX(NV_TEN,MATCH(C12,NV_MA,0)),"MÃ KHÔNG CÓ")) -> Hoàng Hòa | F12: Trạm cân Đông Hen | G12: Chi phí | H12: LAK | I12: 2000000 | J12: Có | K12: =IF(I12="","",IF(H12="LAK",I12*TYGIA_LAK,I12)) -> 2300000
A13: 9 | B13: 46059 | C13: 046083009048 | D13: =IF(C13="","",IFERROR(INDEX(NV_TEN,MATCH(C13,NV_MA,0)),"MÃ KHÔNG CÓ")) -> Hoàng Hòa | F13: CA Si Tha Buộc | G13: Chi phí | H13: LAK | I13: 800000 | J13: Có | K13: =IF(I13="","",IF(H13="LAK",I13*TYGIA_LAK,I13)) -> 920000
A14: 10 | B14: 46059 | C14: 046083009048 | D14: =IF(C14="","",IFERROR(INDEX(NV_TEN,MATCH(C14,NV_MA,0)),"MÃ KHÔNG CÓ")) -> Hoàng Hòa | F14: CA Sê Pôn | G14: Chi phí | H14: LAK | I14: 200000 | J14: Có | K14: =IF(I14="","",IF(H14="LAK",I14*TYGIA_LAK,I14)) -> 230000
A15: 11 | B15: 46059 | C15: 046083009048 | D15: =IF(C15="","",IFERROR(INDEX(NV_TEN,MATCH(C15,NV_MA,0)),"MÃ KHÔNG CÓ")) -> Hoàng Hòa | F15: CA Trạm B | G15: Chi phí | H15: LAK | I15: 200000 | J15: Có | K15: =IF(I15="","",IF(H15="LAK",I15*TYGIA_LAK,I15)) -> 230000
A16: 12 | B16: 46059 | C16: 046083009048 | D16: =IF(C16="","",IFERROR(INDEX(NV_TEN,MATCH(C16,NV_MA,0)),"MÃ KHÔNG CÓ")) -> Hoàng Hòa | F16: CA 3 Trạm | G16: Chi phí | H16: VND | I16: 2000000 | J16: Có | K16: =IF(I16="","",IF(H16="LAK",I16*TYGIA_LAK,I16)) -> 2000000
A17: 13 | B17: 46059 | C17: 046083009048 | D17: =IF(C17="","",IFERROR(INDEX(NV_TEN,MATCH(C17,NV_MA,0)),"MÃ KHÔNG CÓ")) -> Hoàng Hòa | F17: Xịt thùng cont | G17: Chi phí | H17: VND | I17: 150000 | J17: Có | K17: =IF(I17="","",IF(H17="LAK",I17*TYGIA_LAK,I17)) -> 150000 | L17: x
A18: 14 | B18: 46062 | C18: 046083009048 | D18: =IF(C18="","",IFERROR(INDEX(NV_TEN,MATCH(C18,NV_MA,0)),"MÃ KHÔNG CÓ")) -> Hoàng Hòa | E18: 1 | F18: CA Đà Nẵng | G18: Chi phí | H18: VND | I18: 400000 | J18: Có | K18: =IF(I18="","",IF(H18="LAK",I18*TYGIA_LAK,I18)) -> 400000
A19: 15 | B19: 46062 | C19: 046083009048 | D19: =IF(C19="","",IFERROR(INDEX(NV_TEN,MATCH(C19,NV_MA,0)),"MÃ KHÔNG CÓ")) -> Hoàng Hòa | E19: 1 | F19: Vé hầm Hải Vân | G19: Chi phí | H19: VND | I19: 275000 | J19: Có | K19: =IF(I19="","",IF(H19="LAK",I19*TYGIA_LAK,I19)) -> 275000 | L19: v
A20: 16 | B20: 46063 | C20: 046083009048 | D20: =IF(C20="","",IFERROR(INDEX(NV_TEN,MATCH(C20,NV_MA,0)),"MÃ KHÔNG CÓ")) -> Hoàng Hòa | E20: 2 | F20: CA Đà Nẵng | G20: Chi phí | H20: VND | I20: 400000 | J20: Có | K20: =IF(I20="","",IF(H20="LAK",I20*TYGIA_LAK,I20)) -> 400000
A21: 17 | B21: 46063 | C21: 046083009048 | D21: =IF(C21="","",IFERROR(INDEX(NV_TEN,MATCH(C21,NV_MA,0)),"MÃ KHÔNG CÓ")) -> Hoàng Hòa | E21: 2 | F21: Làm lốp, rửa xe, bơm mỡ | G21: Chi phí | H21: VND | I21: 500000 | J21: Có | K21: =IF(I21="","",IF(H21="LAK",I21*TYGIA_LAK,I21)) -> 500000 | L21: v
A22: 18 | B22: 46063 | C22: 046083009048 | D22: =IF(C22="","",IFERROR(INDEX(NV_TEN,MATCH(C22,NV_MA,0)),"MÃ KHÔNG CÓ")) -> Hoàng Hòa | E22: 2 | F22: CA Ngọc Hồi | G22: Chi phí | H22: VND | I22: 200000 | J22: Có | K22: =IF(I22="","",IF(H22="LAK",I22*TYGIA_LAK,I22)) -> 200000
A23: 19 | B23: 46063 | C23: 046083009048 | D23: =IF(C23="","",IFERROR(INDEX(NV_TEN,MATCH(C23,NV_MA,0)),"MÃ KHÔNG CÓ")) -> Hoàng Hòa | E23: 2 | F23: CA Đèo Lò Xo | G23: Chi phí | H23: VND | I23: 400000 | J23: Có | K23: =IF(I23="","",IF(H23="LAK",I23*TYGIA_LAK,I23)) -> 400000
A24: 20 | B24: 46063 | C24: 046083009048 | D24: =IF(C24="","",IFERROR(INDEX(NV_TEN,MATCH(C24,NV_MA,0)),"MÃ KHÔNG CÓ")) -> Hoàng Hòa | E24: 2 | F24: CA Quảng Nam | G24: Chi phí | H24: VND | I24: 400000 | J24: Có | K24: =IF(I24="","",IF(H24="LAK",I24*TYGIA_LAK,I24)) -> 400000
A25: 21 | B25: 46063 | C25: 046083009048 | D25: =IF(C25="","",IFERROR(INDEX(NV_TEN,MATCH(C25,NV_MA,0)),"MÃ KHÔNG CÓ")) -> Hoàng Hòa | E25: 2 | F25: Làm lốp lưu động | G25: Chi phí | H25: VND | I25: 500000 | J25: Có | K25: =IF(I25="","",IF(H25="LAK",I25*TYGIA_LAK,I25)) -> 500000 | L25: v
A26: 22 | B26: 46063 | C26: 046083009048 | D26: =IF(C26="","",IFERROR(INDEX(NV_TEN,MATCH(C26,NV_MA,0)),"MÃ KHÔNG CÓ")) -> Hoàng Hòa | E26: 2 | F26: CA Đà Nẵng | G26: Chi phí | H26: VND | I26: 400000 | J26: Có | K26: =IF(I26="","",IF(H26="LAK",I26*TYGIA_LAK,I26)) -> 400000
A27: 23 | B27: 46067 | C27: 046083009048 | D27: =IF(C27="","",IFERROR(INDEX(NV_TEN,MATCH(C27,NV_MA,0)),"MÃ KHÔNG CÓ")) -> Hoàng Hòa | E27: 3 | F27: CA Đà Nẵng | G27: Chi phí | H27: VND | I27: 400000 | J27: Có | K27: =IF(I27="","",IF(H27="LAK",I27*TYGIA_LAK,I27)) -> 400000
